Workbook

Sheet Listing
A1: Property Address | B1: =TEXTJOIN(", ", TRUE, B20:B23) -> 8075 Catherine Ave, Pasadena, MD, 21122 | C1: =TEXTJOIN(", ", TRUE, C20:C23) -> 330 Salisbury Rd, Edgewater, MD, 21037 | D1: =TEXTJOIN(", ", TRUE, D20:D23) -> 5117 Keota Terrace, College Park, MD, 20740 | E1: =TEXTJOIN(", ", TRUE, E20:E23) -> 2404 Chestnut Terrace Ct Unit #101, Odenton, MD, 21113 | F1: =TEXTJOIN(", ", TRUE, F20:F23) -> 3501 Falling Run , Laurel , MD, 20724 | G1: =TEXTJOIN(", ", TRUE, G20:G23) -> 6312 Springbrook Ln, Clinton, MD, 20735 | H1: =TEXTJOIN(", ", TRUE, H20:H23) -> 407 Frankle St, Brooklyn, MD, 21225 | I1: =TEXTJOIN(", ", TRUE, I20:I23) -> 5129 Niagara Pl, College Park , MD, 20740 | ... M1: =TEXTJOIN(", ", TRUE, M20:M23) -> 7 Waldron Ave, Pikesville , MD, 21208 | N1: =TEXTJOIN(", ", TRUE, N21:N24) -> Middle River , MD, 21220, Baltimore | O1: =TEXTJOIN(", ", TRUE, O20:O23) -> 5129 Niagara Pl, college park , MD, 20740 | P1: =TEXTJOIN(", ", TRUE, P20:P23) -> 7 Waldron Ave, Pikesville , MD, 21208 | Q1: =TEXTJOIN(", ", TRUE, Q20:Q23) -> 6919 Decatur Place , Hyattsville, MD, 20784 | R1: =TEXTJOIN(", ", TRUE, R20:R23) -> 599 Lions Gate, Odenton, MD, 21113 | S1: =TEXTJOIN(", ", TRUE, S20:S23) -> 17 Blue Sky Dr, Owings Mill, MD, 21117 | T1: =TEXTJOIN(", ", TRUE, T20:T23) -> 2 North Star Ct, Pikesville, MD, 21208 | U1: =TEXTJOIN(", ", TRUE, U20:U23) -> 3661 Cragsmoor Rd, Ellicot City, MD, 21042 | V1: =TEXTJOIN(", ", TRUE, V20:V23) -> 24624 Showbarn Circle, Damascus, MD, 20872 | ... AK1: =TEXTJOIN(", ", TRUE, AK20:AK23)
A2: Street Number (Formula) | B2: =IFERROR(LEFT(B20,FIND(" ",B20)-1),B20) -> 8075 | C2: =IFERROR(LEFT(C20,FIND(" ",C20)-1),C20) -> 330 | D2: =IFERROR(LEFT(D20,FIND(" ",D20)-1),D20) -> 5117 | E2: =IFERROR(LEFT(E20,FIND(" ",E20)-1),E20) -> 2404 | F2: =IFERROR(LEFT(F20,FIND(" ",F20)-1),F20) -> 3501 | G2: =IFERROR(LEFT(G20,FIND(" ",G20)-1),G20) -> 6312 | H2: =IFERROR(LEFT(H20,FIND(" ",H20)-1),H20) -> 407 | I2: =IFERROR(LEFT(I20,FIND(" ",I20)-1),I20) -> 5129 | ... M2: =IFERROR(LEFT(M20,FIND(" ",M20)-1),M20) -> 7 | N2: =IFERROR(LEFT(N21,FIND(" ",N21)-1),N21) -> Middle | O2: =IFERROR(LEFT(O20,FIND(" ",O20)-1),O20) -> 5129 | P2: =IFERROR(LEFT(P20,FIND(" ",P20)-1),P20) -> 7 | Q2: =IFERROR(LEFT(Q20,FIND(" ",Q20)-1),Q20) -> 6919 | R2: =IFERROR(LEFT(R20,FIND(" ",R20)-1),R20) -> 599 | S2: =IFERROR(LEFT(S20,FIND(" ",S20)-1),S20) -> 17 | T2: =IFERROR(LEFT(T20,FIND(" ",T20)-1),T20) -> 2 | U2: =IFERROR(LEFT(U20,FIND(" ",U20)-1),U20) -> 3661 | V2: =IFERROR(LEFT(V20,FIND(" ",V20)-1),V20) -> 24624 | ... AK2: =IFERROR(LEFT(AK20,FIND(" ",AK20)-1),AK20)
A3: Street Name (Formula) | B3: =MID(B20,FIND("@",SUBSTITUTE(B20," ","@",LEN(B20)-LEN(SUBSTITUTE(B20," ",""))-(3-1)))+1,LEN(B20)) -> Catherine Ave | C3: =MID(C20,FIND("@",SUBSTITUTE(C20," ","@",LEN(C20)-LEN(SUBSTITUTE(C20," ",""))-(3-1)))+1,LEN(C20)) -> Salisbury Rd | D3: =MID(D20,FIND("@",SUBSTITUTE(D20," ","@",LEN(D20)-LEN(SUBSTITUTE(D20," ",""))-(3-1)))+1,LEN(D20)) -> Keota Terrace | E3: =MID(E20,FIND("@",SUBSTITUTE(E20," ","@",LEN(E20)-LEN(SUBSTITUTE(E20," ",""))-(3-1)))+1,LEN(E20)) -> Ct Unit #101 | F3: =MID(F20,FIND("@",SUBSTITUTE(F20," ","@",LEN(F20)-LEN(SUBSTITUTE(F20," ",""))-(3-1)))+1,LEN(F20)) -> Falling Run | G3: =MID(G20,FIND("@",SUBSTITUTE(G20," ","@",LEN(G20)-LEN(SUBSTITUTE(G20," ",""))-(3-1)))+1,LEN(G20)) -> Springbrook Ln | H3: =MID(H20,FIND("@",SUBSTITUTE(H20," ","@",LEN(H20)-LEN(SUBSTITUTE(H20," ",""))-(3-1)))+1,LEN(H20)) -> Frankle St | I3: =MID(I20,FIND("@",SUBSTITUTE(I20," ","@",LEN(I20)-LEN(SUBSTITUTE(I20," ",""))-(3-1)))+1,LEN(I20)) -> Niagara Pl | ... AK3: =MID(AK20,FIND("@",SUBSTITUTE(AK20," ","@",LEN(AK20)-LEN(SUBSTITUTE(AK20," ",""))-(3-1)))+1,LEN(AK20)) -> #VALUE!
A4: Tax ID | B4: 20338822989400 | C4: 17212330322 | D4: 17212330322 | E4: 20457190103089 | F4: 17090917732 | G4: 17090917732 | I4: 17010018655 | J4: 4151502202950 | K4: 20206090051276 | L4: 4151700006441 | M4: 4030303053560 | N4: 17020163147 | O4: 20444590073911 | P4: 1402261650 | Q4: 4042100013000 | R4: 4032200014402 | S4: 161202043215 | T4: 20315690216404 | U4: 17070815365 | V4: 160203463072 | AG4: 20341813498500 | AH4: 17161802693 | AI4: 20289290048537
A5: Timestamp (Formula) | B5: 44259.765 | C5: 44224.762 | D5: 44265.624 | E5: 44260.671 | F5: 44224.757 | G5: 44272.64 | L5: 44256.636 | M5: 44278.585 | N5: {=transpose('Import fr LIF'!41:41)} -> 44273.722 | O5: {=transpose('Import fr LIF'!42:42)} -> 44274.711 | P5: {=transpose('Import fr LIF'!43:43)} -> 44278.585 | Q5: {=transpose('Import fr LIF'!44:44)} -> 44284.651 | R5: {=transpose('Import fr LIF'!45:45)} -> 44284.726 | S5: {=transpose('Import fr LIF'!46:46)} -> 44284.797 | T5: {=transpose('Import fr LIF'!47:47)} -> 44284.8 | U5: {=transpose('Import fr LIF'!48:48)} -> 44284.804 | V5: {=transpose('Import fr LIF'!49:49)} -> 44285.639 | W5: {=transpose('Import fr LIF'!50:50)} -> 44286.553 | X5: {=transpose('Import fr LIF'!51:51)} -> 44288.631 | Y5: {=transpose('Import fr LIF'!52:52)} -> 44288.813 | Z5: {=transpose('Import fr LIF'!53:53)} -> 44293.745 | AA5: {=transpose('Import fr LIF'!54:54)} -> 44298.711 | AB5: {=transpose('Import fr LIF'!55:55)} -> 44298.742 | AC5: {=transpose('Import fr LIF'!56:56)} -> 44299.388 | AD5: {=transpose('Import fr LIF'!57:57)} -> #REF! | AE5: {=transpose('Import fr LIF'!58:58)} -> 44299.73 | AF5: {=transpose('Import fr LIF'!59:59)} -> 44301.612 | AG5: {=transpose('Import fr LIF'!60:60)} -> 44302.646 | AH5: {=transpose('Import fr LIF'!61:61)} -> 44306.735 | AI5: {=transpose('Import fr LIF'!64:64)} -> 44314.707 | AJ5: {=transpose('Import fr LIF'!65:65)} -> 44326.614 | AK5: {=transpose('Import fr LIF'!66:66)}
A6: Agent Name | B6: Justin | C6: Justin | D6: Justin | E6: Justin | F6: Justin | G6: Justin | H6: Justin | I6: Justin | J6: Shaq | K6: Justin | L6: Shaq | M6: Shaq | N6: Shaq | O6: Justin | P6: Shaq | Q6: John | R6: Justin | S6: Justin | T6: Justin | U6: Justin | V6: Justin | W6: Justin | X6: Justin | Y6: Justin | Z6: Shaq | AA6: Justin | AB6: Justin | AC6: Shaq | AE6: Justin | AF6: Shaq | AG6: Justin | AH6: Justin | AI6: John | AJ6: Justin
A7: Date of Listing Appointment | B7: 44259 | C7: 44224 | D7: 44265 | E7: 44132 | F7: 44228 | G7: 44272 | H7: 44228 | I7: 44274 | J7: 44273 | K7: 44146 | L7: 44254 | M7: 44277 | N7: 44273 | O7: 44274 | P7: 44277 | Q7: 44284 | R7: 44288 | S7: 44288 | T7: 44288 | U7: 44294 | V7: 44285 | W7: 44286 | X7: 44287 | Y7: 44289 | Z7: 44293 | AA7: 44298 | AB7: 44293 | AC7: 44299 | AE7: 44301 | AF7: 44300 | AG7: 44298 | AH7: 44302 | AI7: 44314 | AJ7: 44335
A8: Seller 1 Name | B8: Gregory Jackson | C8: Cory Chambers | D8: Dennis Lamprey | E8: Kathleen L Dipeppe | F8: Maheswaran Natarajan | G8: Aimee Smith | H8: Amy Neary | I8: Mohammad Azad & Arafa Khatun | J8: Brian Valdivia | K8: Charles Gorum | L8: Brian Valdivia | M8: Jeffrey Rattell | N8: Brian Valdivia | O8: Mohammad Azad & Arafa Khatun | P8: Jeffrey Rattell | Q8: Residential Value, LLC | R8: Matthew Lake | S8: Perry Dollar | T8: Perry Dollar | U8: Joyce Gomez | V8: Dale Crum | W8: Rodell Colbert | X8: Mary J Smith | Y8: MON-CHOU FANN | Z8: James Sasser | AA8: Harris Mohammed | AB8: William Hauserman | AC8: Joby Gallo | AE8: James McNamara | AF8: Kevin Knight | AG8: Alain Chu | AH8: Cristina M Galdieri | AI8: Residential Value, LLC | AJ8: Alvester Gales
A9: Seller 1 Phone# | B9: 4102128803 | C9: 4102181104 | D9: 301-474-3476 | E9: 4438897314 | F9: 3018757291 | G9: 3019805645 | H9: 4438526091 | I9: 240-475-1039 | J9: 443-845-2273 | L9: 443-845-2273 | M9: 410-971-0702 | N9: 443-845-2273 | O9: 240-475-1039 | P9: 410-971-0702 | Q9: 301-674-0760 | R9: 3042035801 | S9: 4438015880 | T9: 4438015880 | U9: 2022151798 | W9: 4436232982 | X9: 2024656548 | Y9: 2402520781 | Z9: 443-768-4917 | AA9: 269-352-1885 | AB9: 304 268 7705 | AC9: 410-302-8762 | AE9: 4103407877 | AF9: 609-458-3611 | AG9: 2406023091 | AH9: 2408823626 | AI9: 301-674-0760
A10: Seller 1 Email | B10: firstnationsmtg9500@gmail.com | C10: cory33_1999@yahoo.com | D10: usmc1965dwlsr1@verizon.net | F10: n.maheswaran@gmail.com | G10: aimeelouisesmith@hotmail.com | H10: amymneary@gmail.com | I10: azadppy@yahoo.com | J10: bvaldivia46@gmail.com | K10: chuck@thegorums.com | L10: bvaldivia46@gmail.com | M10: jrattell@rescomsolutions.biz | N10: bvaldivia46@gmail.com | O10: azadppy@yahoo.com | P10: jrattell@rescomsolutions.biz | Q10: dsl227@aol.com | R10: mlake05@gmail.com | S10: Perry.Dollar@perrydollar.com | T10: Perry.Dollar@perrydollar.com | U10: gjoycet@hotmail.com | V10: decrum@hotmail.com | W10: rodell34@aol.com | X10: pps24wolf@gmail.com | Z10: jimbo12130@gmail.com | AA10: mailharrisnow@yahoo.com | AB10: williamhauserman@yahoo.com | AC10: gallo120@aol.com | AE10: james.mcnamara333@gmail.com | AF10: bigduke94@gmail.com | AG10: contrau@yahoo.com | AH10: tgaldieri@varsity.com | AI10: dsl227@aol.com | AJ10: alvester.gales@yahoo.com
A11: Seller 2 Name | F11: Soorriya Natarajan | G11: Steven Smith | I11: Arafa Khatun | J11: Angelo Pagonis | K11: Lisa Gorum | L11: Angelo Pagonis | N11: Angelo Pagonis | O11: Arafa Khatun | U11: Jose Gomez | V11: Francene Crum | Y11: JIANG MAN-SHIOW | AB11: Annette Hauserman | AC11: Robin Gallo | AG11: Giao Tran | AJ11: Annie Gales
A12: Seller 2 Phone# | J12: 410-960-1876 | K12: 4432533071 | L12: 410-960-1876 | N12: 410-960-1876 | AC12: 410-508-5341
A13: Seller 2 Email | F13: Soorriya_c@yahoo.com | G13: on listing agreement | J13: alphaservicesmd@gmail.com | K13: lisa@thegorums.com | L13: alphaservicesmd@gmail.com | N13: alphaservicesmd@gmail.com | AC13: rgallo1207@aol.com | AJ13: galesann@yahoo.com
A14: Exclusive Right to Sell already signed? (8 page packet) | B14: No | C14: No | D14: Yes | E14: Yes | F14: No | G14: No | H14: No | I14: No | J14: No | K14: No | L14: No | M14: No | N14: No | O14: No | P14: No | Q14: Yes | R14: No | S14: No | T14: No | U14: No | V14: No | W14: No | X14: No | Y14: No | Z14: No | AA14: No | AB14: No | AC14: No | AE14: No | AF14: No | AG14: No | AH14: No | AI14: Yes | AJ14: No
A15: Listing Price | B15: 330000 | C15: 300000 | D15: 320000 | E15: 255000 | F15: 370000 | G15: 275000 | H15: 230000 | J15: 146000 | K15: 1100000 | L15: 215000 | M15: 245000 | N15: 146000 | P15: 245000 | Q15: 405000 | R15: 315000 | S15: 260000 | T15: 260000 | X15: 580000 | Z15: 215000 | AA15: 310000 | AB15: 310000 | AC15: 285000 | AE15: 220000 | AF15: 216000 | AG15: 315000 | AH15: 320000 | AI15: 294900 | AJ15: 500000
A16: Projected MLS Active Date | B16: 44273 | C16: 44287 | D16: 44294 | E16: 44293 | F16: 44287 | G16: 44293 | H16: 44257 | I16: 44294 | J16: 44274 | K16: 44308 | L16: 44272 | M16: 44307 | N16: 44274 | O16: 44294 | P16: 44307 | Q16: 44288 | R16: 44300 | S16: 44335 | T16: 44368 | U16: 44314 | V16: 44337 | W16: 44336 | X16: 44317 | Y16: 44368 | Z16: 44321 | AA16: 44335 | AB16: 44285 | AC16: 44321 | AE16: 44365 | AF16: 44321 | AG16: 44316 | AH16: 44377 | AI16: 44316 | AJ16: 44371
A17: Projected Coming Soon Date | B17: 44265 | C17: 44277 | D17: 44286 | E17: 44284 | F17: 44277 | G17: 44286 | H17: 44249 | I17: 44289 | J17: 44274 | K17: 44287 | L17: 44260 | M17: 44286 | N17: 44274 | O17: 44289 | P17: 44286 | Q17: 44286 | R17: 44293 | S17: 44321 | T17: 44348 | U17: 44307 | V17: 44328 | W17: 44317 | X17: 44317 | Y17: 44348 | Z17: 44300 | AA17: 44293 | AB17: 44285 | AC17: 44307 | AE17: 44351 | AF17: 44307 | AG17: 44337 | AH17: 44356 | AI17: 44316 | AJ17: 44350
A18: Total Commission | B18: 6 | C18: 6 | D18: 6 | E18: 6 | F18: 5 % | G18: 6 | H18: 5 | I18: 5 | J18: 5 | K18: 4.5 | L18: 4.5 | M18: 6 | N18: 5 | O18: 5 | P18: 6 | Q18: 3.75 | R18: 5.5 | S18: 6 | T18: 6 | U18: 6 | V18: 5 | W18: 6 | X18: 4.5 | Y18: 6 | Z18: 5 | AA18: 5 + $495 | AB18: 4 + $495 | AC18: 5 | AE18: 5 | AF18: 5 | AG18: 6 +495 | AH18: 5.5 | AI18: 3.75 | AJ18: 6
A19: Listing-Side Commission | B19: 3.5 | C19: 3.5 | D19: 3.5 | E19: 3.5 | F19: 2.5 | G19: 3.5 | H19: 2.5 | I19: 2.5 | J19: 2 | K19: 2 | L19: 2.5 | M19: 3.5 | N19: 2 | O19: 2.5 | P19: 3.5 | Q19: 1.25 | R19: 3 | S19: 3.5 | T19: 3.5 | U19: 3.5 | V19: 2.5 | W19: 3.5 | X19: 2 | Y19: 3.5 | Z19: 2.5 | AA19: 2.5 | AB19: 4 | AC19: 2.5 | AE19: 2.5 | AF19: 2.5 | AG19: 3.5 | AH19: 3 | AI19: 1.25 | AJ19: 3.5
A20: Property Street Address | B20: 8075 Catherine Ave | C20: 330 Salisbury Rd | D20: 5117 Keota Terrace | E20: 2404 Chestnut Terrace Ct Unit #101 | F20: 3501 Falling Run | G20: 6312 Springbrook Ln | H20: 407 Frankle St | I20: 5129 Niagara Pl | J20: 825 Lannerton Rd | K20: 1201 John Ross Ct | L20: 666 Kittendale Cir | M20: 7 Waldron Ave | N20: 825 Lannerton Rd | O20: 5129 Niagara Pl | P20: 7 Waldron Ave | Q20: 6919 Decatur Place | R20: 599 Lions Gate | S20: 17 Blue Sky Dr | T20: 2 North Star Ct | U20: 3661 Cragsmoor Rd | V20: 24624 Showbarn Circle | W20: 1017 Brockton Court | X20: 4805 Church Rd (Map : 0046 Grid: 00C4 Parcel: 0055) | Y20: 12109 Cypress Spring Rd | Z20: 320 Margaret Ave | AA20: 6550 Frietchie Row | AB20: 802 Edmondson Ave, 21228-4457 | AC20: 1501 Saunders Way | AE20: 27 Clearwater Ct | AF20: 5959 Benton Heights Ave | AG20: 9943 valley park dr | AH20: 2254 Commissary Cir | AI20: 1700 Manning Road Glen Burnie, MD 21061 | AJ20: 20649 Anndyke Way,
A21: City | B21: Pasadena | C21: Edgewater | D21: College Park | E21: Odenton | F21: Laurel | G21: Clinton | H21: Brooklyn | I21: College Park | J21: Middle River | K21: Crownsville | L21: Middle River | M21: Pikesville | N21: Middle River | O21: college park | P21: Pikesville | Q21: Hyattsville | R21: Odenton | S21: Owings Mill | T21: Pikesville | U21: Ellicot City | V21: Damascus | W21: Glen Burnie | X21: Bowie | Y21: Clarksburg | Z21: Baltimore | AA21: Columbia, | AB21: Baltimore | AC21: Glen Burnie | AE21: Baltimore | AF21: Baltimore | AG21: Damascus | AH21: Odenton | AI21: Glen Burnie | AJ21: Germantown,
A22: State (Initials only) | B22: MD | C22: MD | D22: MD | E22: MD | F22: MD | G22: MD | H22: MD | I22: MD | J22: MD | K22: MD | L22: MD | M22: MD | N22: MD | O22: MD | P22: MD | Q22: MD | R22: MD | S22: MD | T22: MD | U22: MD | V22: MD | W22: MD | X22: MD | Y22: MD | Z22: MD | AA22: MD | AB22: MD | AC22: MD | AE22: MD | AF22: MD | AG22: MD | AH22: MD | AI22: MD | AJ22: MD
A23: Zip Code | B23: 21122 | C23: 21037 | D23: 20740 | E23: 21113 | F23: 20724 | G23: 20735 | H23: 21225 | I23: 20740 | J23: 21220 | K23: 21032 | L23: 21220 | M23: 21208 | N23: 21220 | O23: 20740 | P23: 21208 | Q23: 20784 | R23: 21113 | S23: 21117 | T23: 21208 | U23: 21042 | V23: 20872 | W23: 21060 | X23: 20720 | Y23: 20871 | Z23: 21221 | AA23: 21045-4506 | AB23: 21228-4457 | AC23: 21061 | AE23: 21220 | AF23: 21206 | AG23: 20872 | AH23: 21113 | AI23: 21061 | AJ23: 20874
A24: County | B24: Anne Arundel | C24: Anne Arundel | D24: Prince George's | E24: Anne Arundel | F24: Anne Arundel | G24: Prince George's | H24: Baltimore City | I24: Prince George's | J24: Baltimore | K24: Anne Arundel | L24: Baltimore | M24: Baltimore | N24: Baltimore | O24: Prince George's | P24: Baltimore | Q24: Prince George's | R24: Anne Arundel | S24: Baltimore | T24: Baltimore | U24: Howard | V24: Montgomery | W24: Anne Arundel | X24: Prince George's | Y24: Montgomery | Z24: Baltimore | AA24: Howard | AB24: NOT BALTIMORE CITY | AC24: Anne Arundel | AE24: Baltimore | AF24: Baltimore City | AG24: Montgomery | AH24: Anne Arundel | AI24: Anne Arundel | AJ24: Montgomery
A25: Property Subdivision | B25: Green Haven | C25: WOODLAND BEACH | D25: HOLLYWOOD | E25: Piney Orchard | F25: RUSSETT | G25: LEWIS SPRING MANOR | H25: Brooklyn | I25: SUNNYSIDE | J25: Maplecrest | K25: BELVIOR / BELVIOR FARMS | L25: CARROLLWOOD MANOR | M25: Ralston | N25: Maplecrest | O25: SUNNYSIDE | P25: Ralston | Q25: Woodlawn | R25: Lions Gate | S25: OWINGS RIDGE | T25: BEDFORD CROSSING | U25: Font Hill | V25: Damascus Hill | W25: BROOKSTONE | Y25: GREENWAY VILLAGE | Z25: Essex | AA25: VILLAGE OF OWEN BROWN | AC25: Harundale | AE25: CARROLLWOOD MANOR | AF25: CEDMONT | AG25: DAMASCUS VALLEY PARK | AH25: SEVEN OAKS | AI25: Harundale | AJ25: CHURCHILL TOWN SECTOR
A26: Property Status | B26: Vacant | C26: Tenant Occupied | D26: Owner Occupied | E26: Owner Occupied | F26: Tenant Occupied | G26: Owner Occupied | H26: Owner Occupied | I26: Tenant Occupied | J26: Vacant | K26: Owner Occupied | L26: Vacant | M26: Vacant | N26: Vacant | O26: Tenant Occupied | P26: Vacant | Q26: Vacant | R26: Tenant Occupied | S26: Tenant Occupied | T26: Tenant Occupied | U26: Owner Occupied | V26: Owner Occupied | W26: Owner Occupied | X26: Owner Occupied | Y26: Vacant | Z26: Tenant Occupied | AA26: Tenant Occupied | AB26: Tenant Occupied | AC26: Owner Occupied | AE26: Tenant Occupied | AF26: Owner Occupied | AG26: Vacant | AH26: Tenant Occupied | AI26: Vacant | AJ26: Owner Occupied
A27: If Tenant Occupied, Provide Additional on the below: | C27: tenant leaving | F27: tenant will be leaving | H27: owner is moving to North Carolina | I27: tenant to vacate 30-60 days | O27: tenant to vacate 30-60 days | R27: tenant vacating in May 31st, will be marketing during their last month | S27: tenant out july 13th | Z27: Tenants are vacating | AB27: tenant to purchase | AE27: vacating 30-45 days | AH27: tenant hoping to purchase
A28: Is Homeowner a Maryland Resident | B28: Yes | C28: Yes | D28: Yes | E28: Yes | F28: Yes | G28: Yes | H28: Yes | I28: No | J28: Yes | K28: Yes | L28: Yes | M28: Yes | N28: Yes | O28: No | P28: Yes | Q28: Yes | R28: Yes | S28: Yes | T28: Yes | U28: Yes | V28: Yes | X28: Yes | Y28: No | Z28: Yes | AA28: Yes | AB28: No | AC28: Yes | AE28: Yes | AF28: Yes | AG28: Yes | AH28: Yes | AI28: Yes | AJ28: Yes
A29: Showing Requirements? Check all that apply | B29: Schedule online | C29: Appointment Only - Client to approve all showings | D29: Schedule online | E29: Appointment Only - Client to approve all showings | F29: Schedule online | G29: 24 Hour notice, Appointment Only - Client to approve all showings | H29: Schedule online | I29: Schedule online | J29: Schedule online, Go and Show | K29: Appointment Only - Client to approve all showings | L29: Lockbox - Sentri, Schedule online | M29: Go and Show | N29: Schedule online, Go and Show | O29: Schedule online | P29: Go and Show | R29: 24 Hour notice, Lockbox - Sentri, Schedule online | S29: 24 Hour notice, Schedule online | T29: 24 Hour notice, Schedule online | U29: 24 Hour notice, Schedule online | V29: 24 Hour notice, Lockbox - Sentri | W29: 24 Hour notice, Schedule online | X29: 24 Hour notice | Y29: Schedule online | Z29: Appointment Only - Client to approve all showings | AA29: 24 Hour notice, Lockbox - Sentri | AB29: wont be listed for showings | AC29: 2 Hour notice | AE29: Lockbox - Sentri, Schedule online | AF29: Appointment Only - Client to approve all showings | AG29: Lockbox - Sentri | AH29: no showings unless tenant cant purchase | AI29: Lockbox - Combo, Schedule online | AJ29: 24 Hour notice
A30: Lockbox Type | B30: SentriLock | C30: SentriLock | D30: SentriLock | E30: gate code and sentri lock | F30: SentriLock | G30: SentriLock | H30: SentriLock | I30: SentriLock | J30: Combo | K30: SentriLock | L30: SentriLock | M30: SentriLock | N30: Combo | O30: SentriLock | P30: SentriLock | Q30: Combo | R30: SentriLock | S30: SentriLock | T30: SentriLock | U30: SentriLock | V30: SentriLock | W30: SentriLock | X30: None | Y30: SentriLock | Z30: SentriLock | AA30: SentriLock | AB30: None | AC30: SentriLock | AE30: SentriLock | AF30: SentriLock | AG30: SentriLock | AH30: None | AI30: Combo | AJ30: SentriLock
A31: Lockbox Location | B31: front door | D31: front door | G31: front door | I31: front door | J31: Front door | K31: front door | L31: Front Door | M31: Front Door | N31: Front door | O31: front door | P31: Front Door | Q31: Front Door | R31: front door | V31: front door | W31: front door | X31: na | Y31: front door | Z31: Front Door | AA31: front door | AB31: na | AC31: Front Door | AE31: front door | AF31: Front Railing | AG31: front door | AH31: na | AI31: front door | AJ31: front door
A32: Lockbox Combo (if any) | J32: 1901 | N32: 1901 | Q32: 1108 | V32: na | W32: sentri | X32: na | Y32: na | Z32: N/A | AA32: na | AB32: na | AC32: Sentri | AE32: na | AF32: NA | AG32: na | AH32: na | AI32: 1108 | AJ32: na
A33: Sign Allowed? Please provide details on location if needed (2+ business days to install) | B33: yard post | C33: yard post | D33: yard post | E33: yard post | F33: yard post | G33: yard post | H33: yard post | I33: yard post | J33: Yes | K33: LUXURY BRANDING | L33: Yes, front yard | M33: Yes | N33: Yes | O33: yard post | P33: Yes | R33: yard post | S33: yard post | T33: yard post | U33: yard post | V33: yard post | W33: yard post | X33: yard post | Y33: yard post | Z33: Yes | AA33: yard post | AB33: no | AC33: Yes | AE33: yard post | AF33: Front Yard | AH33: na | AI33: yes | AJ33: yard post
A34: Open House Date(s) | E34: 4/10-4/11 | L34: First weekend if possible | R34: April 23-24 ?
A35: Location Type | B35: Residential | C35: Residential | D35: Residential | E35: Residential | F35: Residential | G35: Residential | H35: Residential | I35: Residential | J35: Residential | K35: Residential | L35: Residential | M35: Residential | N35: Residential | O35: Residential | P35: Residential | Q35: Residential | R35: Residential | S35: Residential | T35: Residential | U35: Residential | V35: Residential | W35: Residential | X35: selling the land, does have house | Y35: Residential | Z35: Residential | AA35: Residential | AB35: Residential | AC35: Residential | AE35: Residential | AF35: Residential | AG35: Residential | AH35: Residential | AI35: Residential | AJ35: Residential
A36: Structure Type | B36: Detached | C36: Detached | D36: Detached | E36: Unit/Flat | F36: End of Row/Townhouse | G36: Detached | H36: Detached | I36: Detached | J36: End of Row/Townhouse | K36: Detached | L36: Twin/Semi-Detached | M36: Detached | N36: End of Row/Townhouse | O36: Detached | P36: Detached | Q36: Detached | R36: End of Row/Townhouse | S36: End of Row/Townhouse | T36: End of Row/Townhouse | U36: Detached | V36: Detached | W36: Detached | X36: Detached | Y36: Detached | Z36: Detached | AA36: End of Row/Townhouse | AB36: Detached | AC36: Detached | AE36: End of Row/Townhouse | AF36: Interior Row/Town House | AG36: Interior Row/Town House | AH36: Interior Row/Town House | AI36: Detached | AJ36: Detached
A37: Ownership | B37: Fee Simple | C37: Fee Simple | D37: Fee Simple | E37: Condominium | F37: Fee Simple | G37: Fee Simple | H37: Fee Simple | I37: Fee Simple | J37: Ground Rent | K37: Fee Simple | L37: Fee Simple | M37: Fee Simple | N37: Ground Rent | O37: Fee Simple | P37: Fee Simple | Q37: Fee Simple | R37: Fee Simple | S37: Fee Simple | T37: Fee Simple | U37: Fee Simple | W37: Fee Simple | X37: Fee Simple | Y37: Fee Simple | Z37: Fee Simple | AA37: Fee Simple | AB37: Fee Simple | AC37: Fee Simple | AE37: Fee Simple | AF37: Ground Rent | AH37: Fee Simple | AI37: Fee Simple | AJ37: Fee Simple
A38: If Ground Rent: list total annual payment, frequency, of payment, the name/address/phone# of the Ground Rent holder | J38: 120 / yr | N38: 120 / yr | AF38: 90/semi anually
A39: Property Specs. [Check all that apply] | AG39: HOA
A40: Front Foot Fee & Frequency (if any) | Q40: N/A
A41: If Water Oriented, Water Privileged, or Waterfront [Check all that apply]
A42: Building Style (Check all that apply) | B42: Ranch/Rambler | C42: Ranch/Rambler | D42: Ranch/Rambler | G42: Cape Cod | H42: Colonial | I42: Spilt Foyer | J42: Colonial | K42: Colonial | L42: Colonial | M42: Victorian | N42: Colonial | O42: Spilt Foyer | P42: Victorian | Q42: Split Level | R42: Colonial | S42: Colonial | T42: Colonial | U42: Colonial | V42: Spilt Foyer | W42: Colonial | Y42: Colonial | Z42: Cape Cod | AA42: Colonial | AB42: Colonial | AC42: Ranch/Rambler | AE42: Colonial | AF42: Colonial | AG42: Colonial | AH42: Colonial | AI42: Ranch/Rambler | AJ42: Colonial
A43: Construction Materials (Check all that apply) | B43: Vinyl Siding | G43: Brick | I43: Brick | J43: Brick | K43: Brick | L43: Vinyl Siding | M43: Stone, Wood Siding | N43: Brick | O43: Brick | P43: Stone, Wood Siding | Q43: Vinyl Siding | R43: Vinyl Siding | T43: Brick | U43: Brick Front | W43: Vinyl Siding | Y43: Brick | AA43: Brick Front | AB43: Vinyl Siding | AC43: Aluminum Siding | AF43: Brick | AH43: Vinyl Siding | AI43: Vinyl Siding
A44: Water Source (Check all that apply) | B44: Public | C44: Private | D44: Public | E44: Public | F44: Public | G44: Public | H44: Public | I44: Public | J44: Public | K44: Private | L44: Public | M44: Public | N44: Public | O44: Public | P44: Public | Q44: Public | R44: Public | S44: Public | T44: Public | U44: Public | V44: Public | W44: Public | Y44: Public | Z44: Public | AA44: Public | AB44: Public | AC44: Public | AE44: Public | AF44: Public | AG44: Public | AH44: Public | AI44: Public | AJ44: Public
A45: Sewer Septic (Check all that apply) | B45: Public Sewer | C45: private sewer | D45: Public Sewer | E45: Public Sewer | F45: Public Sewer | G45: Public Sewer | H45: Public Sewer | I45: Public Sewer | J45: Public Sewer | K45: Septic Exists | L45: Public Sewer | M45: Public Sewer | N45: Public Sewer | O45: Public Sewer | P45: Public Sewer | Q45: Public Sewer | R45: Public Sewer | S45: Public Sewer | T45: Public Sewer | U45: Public Sewer | V45: Public Sewer | W45: Public Sewer | Y45: Public Sewer | Z45: Public Sewer | AA45: Public Sewer | AB45: Public Sewer | AC45: Public Sewer | AE45: Public Sewer | AF45: Public Sewer | AG45: Public Sewer | AH45: Public Sewer | AI45: Public Sewer | AJ45: Public Sewer
A46: Hot Water Source (Check all that apply) | C46: Natural Gas | E46: Natural Gas | F46: Natural Gas | G46: Electric | J46: Natural Gas | L46: Electric | M46: Natural Gas | N46: Natural Gas | P46: Natural Gas | Q46: Natural Gas | R46: Electric | S46: Electric | T46: Electric | U46: Electric | V46: Electric | W46: Electric | Y46: Natural Gas | Z46: Natural Gas | AA46: Natural Gas | AC46: Natural Gas | AE46: Electric | AF46: Natural Gas | AG46: Electric | AH46: Electric | AI46: Electric | AJ46: Electric
A47: Cooling Type (Check all that apply) | C47: Central A/C | D47: Central A/C | E47: Central A/C | F47: Central A/C | G47: Central A/C | I47: Central A/C | J47: Central A/C | K47: Central A/C | L47: Central A/C | M47: Window Unit(s) | N47: Central A/C | O47: Central A/C | P47: Window Unit(s) | Q47: Central A/C | R47: Central A/C | S47: Central A/C | T47: Central A/C | U47: Central A/C | V47: Central A/C | W47: Central A/C | Y47: Central A/C | Z47: Window Unit(s) | AA47: Central A/C | AB47: Central A/C | AC47: Central A/C | AE47: Central A/C | AF47: Central A/C | AG47: Central A/C | AH47: Central A/C | AI47: Central A/C | AJ47: Central A/C
A48: Heating Type (Check all that apply) | C48: Electric | E48: Electric | F48: Electric | G48: Oil | I48: Heat Pump | J48: Forced Air | K48: Heat Pump, Forced Air | L48: Heat Pump | M48: Baseboard | N48: Forced Air | O48: Heat Pump | P48: Baseboard | Q48: Forced Air | R48: Electric | S48: Heat Pump | T48: Heat Pump | U48: Heat Pump | V48: Electric | W48: Electric | Y48: Heat Pump | Z48: Forced Air | AA48: Forced Air | AC48: Heat Pump | AE48: Electric, Forced Air | AF48: Forced Air | AG48: Forced Air | AH48: Electric | AI48: Electric | AJ48: Electric, Heat Pump
A49: Cooling & Heating Fuel (Check all that apply) [Cooling] | C49: Electric | D49: Electric | E49: Electric | F49: Electric | G49: Electric | H49: Other | I49: Electric | J49: Electric | L49: Electric | N49: Electric | O49: Electric | Q49: Electric | R49: Electric | S49: Electric | T49: Electric | U49: Electric | V49: Electric | W49: Electric | Y49: Electric | AA49: Electric | AB49: Electric | AE49: Electric | AF49: Electric | AH49: Electric | AI49: Electric | AJ49: Electric
A50: Cooling & Heating Fuel (Check all that apply) [Heating] | E50: Natural Gas | F50: Natural Gas | G50: Oil | H50: Other | I50: Natural Gas | J50: Natural Gas | N50: Natural Gas | O50: Natural Gas | Q50: Natural Gas | R50: Electric | S50: Electric | T50: Electric | U50: Electric | V50: Electric | W50: Electric | Y50: Natural Gas | AA50: Natural Gas | AB50: Natural Gas | AE50: Electric | AF50: Natural Gas | AH50: Electric | AI50: Natural Gas | AJ50: Electric
A51: Home Security System | E51: Owned | AI51: None
A52: If Home Security System Rented: payment, frequency, and who system is rented from
A53: Levels/Stories | B53: 1 | C53: 1 | D53: 1 | E53: 1 | F53: 3 | G53: 3 | H53: 3 | I53: 2 | J53: 2 | K53: 3 | L53: 3 | M53: 3 | N53: 2 | O53: 2 | P53: 3 | Q53: 4 | R53: 3 | S53: 2 | T53: 3 | U53: 3 | V53: 2 | W53: 3 | Y53: 3 | Z53: 3 | AA53: 2 | AB53: 3 | AC53: 1 | AE53: 3 | AF53: 3 | AG53: 2 | AH53: 3 | AI53: 1 | AJ53: 3
A54: Basement Type (if any) | B54: improved crawl space | C54: crawl space | D54: none | G54: Fully Finished | H54: Fully Finished | K54: Fully Finished | L54: Fully Finished | M54: Unfinished | P54: Unfinished | Q54: Fully Finished | R54: Fully Finished | S54: Fully Finished | T54: Fully Finished | U54: Fully Finished | V54: Fully Finished | W54: Fully Finished | Y54: Fully Finished | AA54: none | AB54: partially finished | AE54: Fully Finished | AF54: Fully Finished | AG54: Fully Finished | AH54: none | AJ54: Fully Finished
A55: How many Bedrooms are on each level? [Upper Level 2] | M55: 1 | P55: 1 | Q55: 1 | W55: 1
A56: How many Bedrooms are on each level? [Upper Level 1] | F56: 3 | G56: 1 | H56: 3 | I56: 3 | J56: 3 | K56: 3 | L56: 2 | M56: 2 | N56: 3 | O56: 3 | P56: 2 | Q56: 2 | R56: 2 | S56: 3 | T56: 3 | U56: 4 | V56: 3 | W56: 3 | Y56: 4 | Z56: 2 | AA56: 3 | AB56: 3 | AE56: 3 | AF56: 3 | AG56: 3 | AH56: 3 | AJ56: 4
A57: How many Bedrooms are on each level? [Main Level] | B57: 3 | C57: 3 | D57: 3 | E57: 2 | G57: 2 | K57: 2 | M57: 2 | P57: 2 | Q57: 1 | Z57: 1 | AA57: 1 | AC57: 3 | AI57: 3
A58: How many Bedrooms are on each level? [Lower Level 1] | I58: 2 | K58: 1 | L58: 1 | O58: 2 | Q58: 1 | R58: 1 | Y58: 1 | AF58: 1
A59: How many FULL Bathrooms are on each level? [Upper Level 2] | M59: 1 | P59: 1
A60: How many FULL Bathrooms are on each level? [Upper Level 1] | F60: 2 | H60: 1 | I60: 1 | J60: 1 | K60: 1 | L60: 1 | M60: 1 | N60: 1 | O60: 1 | P60: 1 | Q60: 1 | R60: 2 | S60: 2 | T60: 2 | U60: 2 | V60: 2 | W60: 2 | Y60: 3 | Z60: 1 | AA60: 2 | AB60: 2 | AE60: 1 | AF60: 1 | AG60: 1 | AH60: 2 | AJ60: 2
A61: How many FULL Bathrooms are on each level? [Main Level] | B61: 2 | C61: 1 | D61: 1 | E61: 2 | G61: 1 | K61: 2 | M61: 1 | P61: 1 | Q61: 1 | Z61: 1 | AC61: 1 | AI61: 1
A62: How many FULL Bathrooms are on each level? [Lower Level 1] | G62: 1 | I62: 1 | K62: 1 | L62: 1 | O62: 1 | Q62: 1 | R62: 1 | T62: 1 | V62: 1 | W62: 1 | Y62: 1 | AE62: 1 | AF62: 1
A63: How many HALF Bathrooms are on each level? [Upper Level 2]
A64: How many HALF Bathrooms are on each level? [Upper Level 1]
A65: How many HALF Bathrooms are on each level? [Main Level] | C65: 1 | F65: 1 | H65: 1 | K65: 1 | L65: 1 | R65: 1 | S65: 1 | T65: 1 | U65: 1 | W65: 1 | Y65: 1 | AE65: 1 | AG65: 1 | AH65: 1 | AJ65: 1
A66: How many HALF Bathrooms are on each level? [Lower Level 1] | AH66: 1
A67: Additional Features | C67: Fireplace | E67: Fireplace, Pool (Community) | G67: Fireplace | H67: Fireplace | K67: Fireplace | M67: Fireplace | P67: Fireplace | T67: Fireplace | U67: Fireplace | V67: Pool (Personal) | Y67: Fireplace | AH67: Fireplace | AJ67: Fireplace
A68: Lot Size Acres | C68: 0.14 | G68: 0.33 | H68: 0.52 | J68: 0.1 | L68: 0.04 | M68: .22a | N68: 0.1 | P68: .22a | Q68: .16 acre | X68: 9.93 acres | AC68: 0.14a | AI68: .12 acres
A69: Type of Parking (if any) | B69: Driveway, Off Street, Parking Lot | C69: Driveway, Off Street, On Street | D69: Driveway, On Street | E69: Parking Lot | F69: Attached Garage, Driveway | G69: Driveway, Off Street | H69: Driveway, Off Street, On Street | I69: Driveway, On Street | J69: On Street | K69: Attached Garage, Driveway, Off Street | L69: On Street | M69: Driveway, On Street | N69: On Street | O69: Driveway, On Street | P69: Driveway, On Street | Q69: Driveway | R69: Parking Lot | S69: Parking Lot | T69: Parking Lot | U69: Driveway, On Street | V69: Attached Garage, Driveway | W69: Attached Garage | Y69: Attached Garage, Driveway | Z69: Driveway, On Street | AA69: Off Street, Parking Lot | AB69: Driveway | AC69: Detached Garage | AE69: Parking Lot | AF69: On Street | AG69: Parking Lot | AH69: Attached Garage | AI69: Driveway | AJ69: Attached Garage
A70: Number of Spaces by Type (if any) [Attached Garage] | F70: 1 | K70: 2 | V70: 2 | Y70: 2 | AH70: 1 | AJ70: 2
A71: Number of Spaces by Type (if any) [Attached Carport]
A72: Number of Spaces by Type (if any) [Detached Carport]
A73: Number of Spaces by Type (if any) [Detached Garage]
A74: Exclusions (Check off if excluded and/or not applicable to property) | B74: Alarm System, Clothes Dryer, Clothes Washer, Drapery/Curtain Rods, Draperies, Electronic Air Filter, Freezer, Furnace Humidifier, Garage Openers (list how many at the end of this form), Garage Opener Remotes (list how many at the end of this form), Garbage Disposal, Hot Tub, Equipment, and Cover, Intercom System, Playground Equipment, Pool, Equipment, and Cover, Satellite Dish, Screens, Storm Windows, TV Antenna, Trash Compactor, Wall Oven (list how many at the end of this form), Water Filter System, Water Treatment System, Window A/C Unit (list how many at the end of this form), Window Fan (list how many at the end of this form), Wood Stove | C74: Alarm System, Central Vacuum, Electronic Air Filter, Freezer, Furnace Humidifier, Garage Openers (list how many at the end of this form), Garage Opener Remotes (list how many at the end of this form), Garbage Disposal, Hot Tub, Equipment, and Cover, Intercom System, Playground Equipment, Pool, Equipment, and Cover, Satellite Dish, Storage Sheds (list how many at the end of this form), TV Antenna, Trash Compactor, Water Filter System, Water Treatment System, Window A/C Unit (list how many at the end of this form), Window Fan (list how many at the end of this form), Wood Stove | D74: Built-in Microwave, Central Vacuum, Drapery/Curtain Rods, Draperies, Electronic Air Filter, Exhaust Fans (list how many at the end of this form), Fireplace Sreen/Door, Furnace Humidifier, Garage Openers (list how many at the end of this form), Garage Opener Remotes (list how many at the end of this form), Garbage Disposal, Hot Tub, Equipment, and Cover, Intercom System, Playground Equipment, Pool, Equipment, and Cover, Refrigerator w/ Ice makers (list how many at the end of this form), Satellite Dish, Storm Windows, TV Antenna, Trash Compactor, Wall Oven (list how many at the end of this form), Water Filter System, Water Treatment System, Window A/C Unit (list how many at the end of this form), Window Fan (list how many at the end of this form), Wood Stove | E74: Alarm System, Central Vacuum, Cooktop, Drapery/Curtain Rods, Draperies, Electronic Air Filter, Exhaust Fans (list how many at the end of this form), Freezer, Furnace Humidifier, Garage Openers (list how many at the end of this form), Garage Opener Remotes (list how many at the end of this form), Garbage Disposal, Hot Tub, Equipment, and Cover, Intercom System, Playground Equipment, Pool, Equipment, and Cover, Refrigerator w/ Ice makers (list how many at the end of this form), Satellite Dish, Storage Sheds (list how many at the end of this form), Storm Door (list how many at the end of this form), Storm Windows, TV Antenna, Trash Compactor, Wall Oven (list how many at the end of this form), Water Filter System, Water Treatment System, Window A/C Unit (list how many at the end of this form), Window Fan (list how many at the end of this form), Wood Stove | F74: Alarm System, Central Vacuum, Electronic Air Filter, Exhaust Fans (list how many at the end of this form), Existing W/W Carpet, Freezer, Furnace Humidifier, Garbage Disposal, Hot Tub, Equipment, and Cover, Intercom System, Playground Equipment, Pool, Equipment, and Cover, Water Filter System, Water Treatment System, Window A/C Unit (list how many at the end of this form), Window Fan (list how many at the end of this form), Wood Stove | G74: Alarm System, Central Vacuum, Cooktop, Drapery/Curtain Rods, Draperies, Electronic Air Filter, Fireplace Sreen/Door, Freezer, Furnace Humidifier, Garage Openers (list how many at the end of this form), Garage Opener Remotes (list how many at the end of this form), Garbage Disposal, Hot Tub, Equipment, and Cover, Intercom System, Playground Equipment, Pool, Equipment, and Cover, Refrigerator w/ Ice makers (list how many at the end of this form), Satellite Dish, Screens, Shades/ Blinds, Storage Sheds (list how many at the end of this form), Storm Windows, TV Antenna, Trash Compactor, Wall Oven (list how many at the end of this form), Water Filter System, Water Treatment System, Window A/C Unit (list how many at the end of this form), Window Fan (list how many at the end of this form), Wood Stove | H74: Alarm System, Built-in Microwave, Central Vacuum, Electronic Air Filter, Freezer, Furnace Humidifier, Garage Openers (list how many at the end of this form), Garage Opener Remotes (list how many at the end of this form), Garbage Disposal, Hot Tub, Equipment, and Cover, Intercom System, Playground Equipment, Pool, Equipment, and Cover, Refrigerator (list how many at the end of this form), Refrigerator w/ Ice makers (list how many at the end of this form), Satellite Dish, Trash Compactor, Water Filter System, Water Treatment System, Window A/C Unit (list how many at the end of this form), Window Fan (list how many at the end of this form), Wood Stove | I74: Central Vacuum, Clothes Dryer, Clothes Washer, Cooktop, Drapery/Curtain Rods, Draperies, Electronic Air Filter, Freezer, Furnace Humidifier, Garage Openers (list how many at the end of this form), Garage Opener Remotes (list how many at the end of this form), Garbage Disposal, Hot Tub, Equipment, and Cover, Intercom System, Playground Equipment, Pool, Equipment, and Cover, Satellite Dish, Shades/ Blinds, Storage Sheds (list how many at the end of this form), Storm Door (list how many at the end of this form), Storm Windows, TV Antenna, Trash Compactor, Wall Oven (list how many at the end of this form), Water Filter System, Water Treatment System, Window A/C Unit (list how many at the end of this form), Window Fan (list how many at the end of this form), Wood Stove | J74: Pool, Equipment, and Cover | K74: Central Vacuum, Drapery/Curtain Rods, Draperies, Electronic Air Filter, Freezer, Furnace Humidifier, Garbage Disposal, Hot Tub, Equipment, and Cover, Intercom System, Playground Equipment, Pool, Equipment, and Cover, Satellite Dish, Screens, Shades/ Blinds, Storm Windows, TV Antenna, Trash Compactor, Wall Oven (list how many at the end of this form), Water Filter System, Water Treatment System, Window A/C Unit (list how many at the end of this form), Window Fan (list how many at the end of this form), Wood Stove | L74: Central Vacuum | N74: Pool, Equipment, and Cover | O74: Central Vacuum, Clothes Dryer, Clothes Washer, Cooktop, Drapery/Curtain Rods, Draperies, Electronic Air Filter, Freezer, Furnace Humidifier, Garage Openers (list how many at the end of this form), Garage Opener Remotes (list how many at the end of this form), Garbage Disposal, Hot Tub, Equipment, and Cover, Intercom System, Playground Equipment, Pool, Equipment, and Cover, Satellite Dish, Shades/ Blinds, Storage Sheds (list how many at the end of this form), Storm Door (list how many at the end of this form), Storm Windows, TV Antenna, Trash Compactor, Wall Oven (list how many at the end of this form), Water Filter System, Water Treatment System, Window A/C Unit (list how many at the end of this form), Window Fan (list how many at the end of this form), Wood Stove | Q74: Alarm System, Ceiling Fans (list how many at the end of this form), Central Vacuum, Clothes Dryer, Clothes Washer, Cooktop, Drapery/Curtain Rods, Draperies, Electronic Air Filter, Exhaust Fans (list how many at the end of this form), Fireplace Sreen/Door, Freezer, Furnace Humidifier, Garage Openers (list how many at the end of this form), Garage Opener Remotes (list how many at the end of this form), Hot Tub, Equipment, and Cover, Intercom System, Playground Equipment, Pool, Equipment, and Cover, Satellite Dish, Screens, Shades/ Blinds, Storage Sheds (list how many at the end of this form), Storm Door (list how many at the end of this form), Storm Windows, TV Antenna, Trash Compactor, Wall Oven (list how many at the end of this form), Water Filter System, Water Treatment System, Window A/C Unit (list how many at the end of this form), Window Fan (list how many at the end of this form), Wood Stove | R74: Central Vacuum, Cooktop, Drapery/Curtain Rods, Draperies, Electronic Air Filter, Freezer, Furnace Humidifier, Garage Openers (list how many at the end of this form), Garage Opener Remotes (list how many at the end of this form), Garbage Disposal, Hot Tub, Equipment, and Cover, Intercom System, Playground Equipment, Pool, Equipment, and Cover, Satellite Dish, Storage Sheds (list how many at the end of this form), Trash Compactor, Wall Oven (list how many at the end of this form), Water Filter System, Water Treatment System, Window A/C Unit (list how many at the end of this form), Window Fan (list how many at the end of this form), Wood Stove | V74: Central Vacuum, Cooktop, Electronic Air Filter, Fireplace Sreen/Door, Furnace Humidifier, Hot Tub, Equipment, and Cover, Intercom System, Playground Equipment, Refrigerator w/ Ice makers (list how many at the end of this form), Satellite Dish, Storm Door (list how many at the end of this form), Storm Windows, TV Antenna, Trash Compactor, Wall Oven (list how many at the end of this form), Water Filter System, Water Treatment System, Window A/C Unit (list how many at the end of this form), Window Fan (list how many at the end of this form), Wood Stove | Z74: Built-in Microwave, Ceiling Fans (list how many at the end of this form), Refrigerator (list how many at the end of this form), Stove or Range | AC74: Built-in Microwave, Ceiling Fans (list how many at the end of this form), Clothes Dryer, Clothes Washer, Refrigerator (list how many at the end of this form), Stove or Range | AE74: Alarm System, Central Vacuum, Draperies, Electronic Air Filter, Fireplace Sreen/Door, Freezer, Furnace Humidifier, Garage Openers (list how many at the end of this form), Garage Opener Remotes (list how many at the end of this form), Garbage Disposal, Hot Tub, Equipment, and Cover, Intercom System, Playground Equipment, Pool, Equipment, and Cover, Trash Compactor, Water Filter System, Water Treatment System, Window A/C Unit (list how many at the end of this form), Window Fan (list how many at the end of this form), Wood Stove | AF74: Built-in Microwave, Clothes Dryer, Clothes Washer, Dishwasher, Existing W/W Carpet, Refrigerator w/ Ice makers (list how many at the end of this form), Stove or Range | AI74: Built-in Microwave, Dishwasher, Existing W/W Carpet, Garbage Disposal, Refrigerator w/ Ice makers (list how many at the end of this form), Stove or Range
A75: Property Management Company 1 Name & Contact Info | S75: Tidewater | T75: long and foster | AH75: Champion Property Management
A76: Property Management Company 1 Name & Contact Info | T76: tara fowlks 4436323215 | AH76: Connie Giddings
A77: Is the Management Company Mandatory? [Yes]
A78: Is the Management Company Mandatory? [No]
A79: HOA Name | E79: CHESTNUT TERRACE | K79: BELVIOR FARMS | R79: LIONS GATE | AC79: HARUNDALE-OAKWOOD PARK CIVIC ASSOCIATION | AH79: SEVEN OAKS | AI79: Harundale - Oakwood Park Civic Assoc
A80: HOA fee & frequency | AC80: $45 / Annually | AI80: $45 annually
A81: Condo Association fee & frequency
A82: Association Recreation Fee
A83: Capital Contribution Fee
A84: Elevator Use Fee
A85: Other Fees (please be specfic)
A86: Conservation Easement (if any)
A87: Latent Defects ("NA" if none) | B87: NA | C87: NA | D87: NA | E87: NA | F87: NA | G87: NA | H87: NA | I87: NA | J87: NA | K87: NA | L87: NA | M87: NA | N87: NA | O87: f | P87: NA | Q87: None Noted | R87: na | S87: na | T87: na | U87: na | V87: na | W87: na | X87: na | Y87: na | Z87: None | AA87: na | AB87: na | AC87: None | AE87: na | AF87: NA | AG87: na | AH87: na | AI87: None | AJ87: na
A88: Add the Remarks for the MLS (this will be VERBATIM, take the time to fill out to increase the likelihood of selling) | G88: AS-IS | Q88: Listing agent will add all remarks | AI88: Fully renovated rancher featuring new siding, windows, gourmet kitchen with stainless appliances, granite counters and new cabinetry
A89: Timeframe within the next 24 hours that client will be available to take a call from our Listing Manager to go over scheduling of Staging, Photos, Sign, etc. (please give at least a 2-hour range) | J89: Anytime, Call Brian | L89: Immediately | N89: Anytime, Call Brian | AC89: Whenever - Retired | AI89: You can call david tomorrow | AJ89: June 1st
A90: If "Other" was selected anywhere on this form and more details are essential, please provide here | H90: please add AS-IS addendum | L90: The property is going to be sold in the LLC name: 3134 Wilkens, LLC ; please call the owner to get confirmation for the photo dates | AH90: 5.5 % commission if on the open market, 3 % commission if tenant is the buyer.
A91: Add Photos Here
A92: Property Constructed | B92: Before 1978 | D92: Before 1978 | E92: During or After 1978 | G92: Before 1978 | I92: Before 1978 | J92: Before 1978 | K92: During or After 1978 | L92: During or After 1978 | M92: Before 1978 | N92: Before 1978 | O92: Before 1978 | P92: Before 1978 | Q92: Before 1978 | R92: During or After 1978 | S92: During or After 1978 | T92: During or After 1978 | U92: During or After 1978 | V92: During or After 1978 | W92: During or After 1978 | Y92: During or After 1978 | Z92: Before 1978 | AA92: Before 1978 | AB92: Before 1978 | AC92: Before 1978 | AE92: During or After 1978 | AF92: Before 1978 | AG92: During or After 1978 | AH92: During or After 1978 | AI92: Before 1978 | AJ92: During or After 1978
B93: Absentee Owner | D93: 4042100013000 | E93: Absentee Owner | G93: Referral | I93: Absentee Owner | J93: Personal Sphere | K93: Ideal Agent | L93: Personal Sphere | M93: Absentee Owner | N93: Personal Sphere | O93: Absentee Owner | P93: Absentee Owner | Q93: Investor | R93: Absentee Owner | S93: Absentee Owner | T93: Absentee Owner | U93: Absentee Owner | V93: Personal Sphere | W93: Absentee Owner | X93: Ideal Agent | Y93: Absentee Owner | Z93: Personal Sphere | AA93: Absentee Owner | AB93: Absentee Owner | AC93: Personal Sphere | AE93: Absentee Owner | AF93: Personal Sphere | AG93: Absentee Owner | AH93: Absentee Owner | AI93: Investor | AJ93: Absentee Owner
A95: Sentri Lock Serial Number | V95: na
C96: 44291
AD100: =52*12 -> 624
AD101: Off Street, Parking Lot
A107: Sign Installation Request
A108: Active MLS added to Loop and share for siganture
A109: Add disclosures in MLS
...

Sheet Inventory
A1: Status | B1: Property Address | C1: Agent | D1: Seller 1/ Email/ Phone | E1: Seller 2/ Email/ Phone | F1: Added in RV? | G1: Opportunity | H1: HOA/Condo/Coop | I1: Sewer/Septic? | J1: Front Foot Fee? | K1: Photos Scheduled? | L1: Listing Price | M1: CS | N1: Active Date | O1: Expiration | P1: MLS Number | Q1: Sign Installation Request | R1: Add disclosures in MLS | S1: Setup Showing Instructions | T1: KW Ad in Command | U1: Send MLS Sheet out | V1: Pull tax record | W1: Lockbox assigned | X1: Source | Y1: Total Comm | Z1: LAC | AA1: BAC | AB1: Flat Fee | AC1: LA Signed Date | AD1: Buyer Name | AE1: Buyer's Agent | AF1: Financing (Cash, Conv, VA, etc) | AG1: Title | AH1: Lender | AI1: Lender Required Repairs | AJ1: Sales Price | AK1: EMD Amount | AL1: EMD Held by | AM1: Seller Contribution | AN1: Ratification Date | AO1: Closing Date | AP1: Financing Commintment | AQ1: Appraisal | AR1: Inspection | AS1: Pend in MLS | AT1: Buyer Agent Into | AU1: Seller Intro | AV1: Title Inro | AW1: TItle Docs Complete | AX1: Added Dates to Calendar | AY1: Greensheet/Commission Tab | AZ1: ALTA/HUD Received? | BA1: Order sign down | BB1: Closed in MLS | BC1: Notes | BD1: Has Dotloop? | BE1: Linked?
A2: Pre-Listing | B2: 8496 Inspiration Avenue, Walkersville, MD 21793 | C2: Justin | D2: Jarred Merriam lj_merriam@yahoo.com +13014733902 | E2: Lori Merriam | F2: TRUE | G2: TRUE | K2: 8/10 or 8/11 | P2: MDFR2003888 | Q2: FALSE | R2: FALSE | S2: FALSE | T2: FALSE | U2: FALSE | V2: TRUE | Y2: 0.06 | Z2: 0.035 | AA2: 0.025 | AB2: 495 | AC2: 44415 | AZ2: FALSE | BA2: FALSE | BC2: We would like to have coming soon 8/9/21 and photos scheduled for 8/10 or 8/11. Either photo company is fine, whoever has availability. The projected active date will be 8/12. We may look to have coming soon 8/12 and active 8/19, but for now lets shoot for the earlier timeline. MLS Draft created. MLS Missing: Marketing Date, Photos, Disclosures. | BD2: Y | BE2: Y
A3: Pre-Listing | B3: 125 Blackbird Hill Ln, Laurel, MD 20724 | C3: Justin | D3: Sherry Banks Home Mobile: 404-840-4227 Home Email: sirblubeard@gmail.com | E3: N/A | F3: TRUE | G3: TRUE | I3: Septic | K3: TRUE | O3: 44581 | P3: MDAA2006222 | Q3: FALSE | R3: FALSE | S3: FALSE | T3: FALSE | U3: FALSE | V3: TRUE | Y3: 0.055 | Z3: 0.03 | AA3: 0.025 | AB3: $595? | AC3: 44413 | AZ3: FALSE | BA3: FALSE | BC3: MLS Draft created. MLS Missing: Marketing Date, Photos, HOA Fee, Pool. Need MLS Remarks. Clarification on Commission Rate. Listing Agreement and Dotloop info has different value. No Signed Disclosures yet. | BD3: Y | BE3: N | BF3: Front fee fee Photo Schedule Staging Showing HOA Fee When are we making it Active
A4: Pre-Listing | B4: 2914 Tarragon Lane, Bowie, MD 20715 | C4: Jen | D4: James Skarwecki | E4: Anne Skarwecki tagaj@juno.com 3012620989 | F4: TRUE | G4: TRUE | O4: 44770 | P4: MDPG2006860 | Q4: FALSE | R4: FALSE | S4: FALSE | T4: FALSE | U4: FALSE | V4: TRUE | AZ4: FALSE | BA4: FALSE | BC4: MLS Draft created. MLS Missing: List Price, Marketing Date, HOA?, Property Style, Construction Materials, Water Source, Hot Water, Cooling Type, Cooling Fuel, Heating Type, Heating Fuel, Bed/Bath/Half Bath floors? Pool?, Garage Info Need Showing Instructions & Lockbox Info Need MLS Remarks No Listing Intake. No Signed Documents. 3.5 total comm? 2.5% buyer? | BD4: Y | BE4: Y
A5: Pre-Listing | B5: 500 King Farm Blvd Unit #104, Rockville, MD 20850-5839 | C5: John | F5: TRUE | G5: FALSE | P5: MDMC2008058 | Q5: FALSE | R5: FALSE | S5: FALSE | T5: FALSE | U5: FALSE | V5: FALSE | AZ5: FALSE | BA5: FALSE | BC5: Showing Instructions: Lockbox - Combo, 1108 on slider on back door CANNOT BE SCHEDULED UNTIL WEDNESDAY OF NEXT WEEK MLS Draft created. MLS Missing: Marketing Date, Expiration Date, List Price, Condo Fee, Condo Frequency, Condo Fee includes, Condo Amenities, Hot Water Source, Photos, MLS Remarks, MLS Documents. Need Showing Instructions | BD5: N | BE5: N
A6: Pre-Listing | B6: 17 Blue Sky Dr Owings Mill MD 21117 | C6: Justin | D6: Perry Dollar Home Mobile: 443-801-5880 Home Email: Perry.Dollar@perrydollar.com | E6: N/A | F6: TRUE | G6: TRUE | O6: 44649 | P6: MDBC2003924 | Q6: FALSE | R6: FALSE | S6: FALSE | T6: FALSE | U6: FALSE | V6: FALSE | Y6: 0.06 | Z6: =Y6-AA6 -> 0.035 | AA6: 0.025 | AB6: 495 | AC6: 44358 | AZ6: FALSE | BA6: FALSE | BC6: Drafted. Seller Signed LA. No Signed Disclosures Not in Opportunity MLS Draft created. MLS Missing: Marketing Date, HOA Fee & Frequency, Photos, Showing Instructions, MLS remarks Seller Signed Exclusive Rights to Sell. No Signed Disclosures. Exclusive Rights to Sell - Need Agent's signature | BD6: Y | BE6: N
A7: Pre-Listing | B7: 1006 Shreve Ct Crofton | C7: Justin | D7: Paul Kenney kenneycommunications@comcast.net 301-325-4819 | E7: N/A | F7: TRUE | G7: TRUE | Q7: FALSE | R7: FALSE | S7: FALSE | T7: FALSE | U7: FALSE | V7: FALSE | Y7: 0.06 | Z7: =Y7-AA7 -> 0.035 | AA7: 0.025 | AB7: 495 | AZ7: FALSE | BA7: FALSE | BC7: Seller Signed LA. No Signed Disclosures. Direct tenant purchase
A8: Pre-Listing | B8: 1032 Middlesex | C8: Justin | F8: FALSE | G8: FALSE | Q8: FALSE | R8: FALSE | S8: FALSE | T8: FALSE | U8: FALSE | V8: FALSE | AZ8: FALSE | BA8: FALSE | BC8: Direct tenant purchase
A9: Pre-Listing | B9: 529 Grovethorn | C9: Justin | F9: FALSE | G9: FALSE | Q9: FALSE | R9: FALSE | S9: FALSE | T9: FALSE | U9: FALSE | V9: FALSE | AZ9: FALSE | BA9: FALSE | BC9: Direct tenant purchase
A10: CS | B10: 11723B Hamilton Place, White Marsh, MD 21162 | C10: Shaq | D10: Gabriel Titalangha gtguemia@hotmail.com 410-865-9696 | E10: Hilda Ikundi mamonjohon@yahoo.com 443-985-2292 | F10: TRUE | G10: TRUE | K10: TRUE | L10: 525000 | M10: 44418 | N10: 44420 | O10: 6692181 | P10: MDBC2005954 | Q10: TRUE | R10: TRUE | S10: TRUE | T10: FALSE | U10: FALSE | V10: TRUE | W10: 1897470 | Y10: 0.045 | Z10: 0.025 | AA10: 0.02 | AB10: 0 | AC10: 44410 | AZ10: FALSE | BA10: FALSE | BC10: MLS Sheet, Netsheet | BD10: Y | BE10: Y
A11: Active | B11: 3012 Rices Ln | C11: Justin | D11: Sadi Wadi Home Email: sadiwadi@hotmail.com | E11: N/A | F11: TRUE | G11: TRUE | K11: TRUE | L11: 525000 | M11: 44407 | N11: 44414 | O11: 44677 | P11: MDBC2004306 | Q11: TRUE | R11: FALSE | S11: TRUE | T11: TRUE | U11: TRUE | V11: TRUE | W11: 965407 | Y11: 0.04 | Z11: 0.015 | AA11: 0.025 | AB11: 495 | AC11: 44312 | AZ11: FALSE | BA11: FALSE | BC11: Incomplete Exclusive Rights to Sell - Need seller phone number. Need Agent's signature. Need answers on #32 Addenda. Blanks on Section #6 and #15. Need to fix the initials made on page 1, Section 3 Fee Simple/Ground Rent field. No Signed Disclosures | BD11: Y | BE11: N
A12: Active | B12: 5620 Quincy St, Hyattsville, MD 20784-1235 | C12: John | D12: David Loring Company: Residential Value Work Mobile: 301-674-0160 Work Email: dsl227@aol.com | E12: N/A | F12: TRUE | G12: TRUE | K12: TRUE | L12: 365000 | M12: 44411 | N12: 44413 | O12: 44564 | P12: MDPG2005740 | Q12: Ordered | R12: FALSE | S12: TRUE | T12: TRUE | U12: TRUE | V12: TRUE | Y12: 0.0375 | Z12: 0.0125 | AA12: 0.025 | AB12: 0 | AC12: 44411 | AZ12: FALSE | BA12: FALSE | BC12: Showing Instructions: Lockbox - Combo/Front Door/1108, Go & Show. Need to upload MLS Documents. MLS Sheet (Shared 8/5/2021) | BD12: Y | BE12: Y
A13: Active | B13: 202 Broadway Avenue, Glen Burnie, MD 21061 | C13: John | D13: David Loring Company: Residential Value Work Mobile: 301-674-0160 Work Email: dsl227@aol.com | E13: N/A | F13: TRUE | G13: TRUE | K13: TRUE | L13: 355000 | M13: 44411 | N13: 44413 | O13: 44595 | P13: MDAA2005004 | Q13: TRUE | R13: TRUE | S13: TRUE | T13: TRUE | U13: TRUE | V13: TRUE | Y13: 0.0375 | Z13: 0.0125 | AA13: 0.025 | AB13: 0 | AC13: 44411 | AZ13: FALSE | BA13: FALSE | BC13: Showing Instructions: Lockbox - Combo/Front Door/1108, Go & Show. MLS Sheet (Shared 8/5/2021) | BD13: Y | BE13: Y
A14: Active | B14: 53 Parkhill Pl, Nottingham, MD 21236 | C14: Justin | D14: Scott Reibert Home Mobile: 443-509-1526 Home Email: scottreibert1@gmail.com | E14: Linda Reibert Home Email: lindagoray@msn.com 443-722-9099 | F14: TRUE | G14: TRUE | K14: TRUE | L14: 285000 | M14: 44407 | N14: 44413 | O14: 44751 | P14: MDBC2005942 | Q14: Ordered | R14: TRUE | S14: TRUE | T14: TRUE | U14: TRUE | V14: TRUE | Y14: 0.05 | Z14: 0.025 | AA14: 0.025 | AB14: 495 | AC14: 44390 | AZ14: FALSE | BA14: FALSE | BC14: Exclusive Rights to Sell (Shared 8/5/2021) MLS Sheet (Shared 8/5/2021) | BD14: Y | BE14: Y
A15: Active | B15: 547 Dahlgreen Road, Glen Burnie, MD 21061 | C15: Romont | D15: Carla Rich 443-875-7129 newleaf64@yahoo.com | E15: N/A | F15: TRUE | G15: TRUE | K15: TRUE | L15: 234900 | M15: 44411 | N15: 44413 | O15: 44598 | P15: MDAA2005518 | Q15: None | R15: TRUE | S15: TRUE | T15: TRUE | U15: TRUE | V15: TRUE | Y15: 0.06 | Z15: =Y15-AA15 -> 0.035 | AA15: 0.025 | AB15: 495 | AC15: 44407 | AZ15: FALSE | BA15: FALSE | BC15: Need agent signatures on Notice to Buyer and Seller, LBP after 1978. Missing Listed: County Addendum | BD15: Y | BE15: N
A16: Active | B16: 802 Edmondson Ave, Baltimore 21228 | C16: Justin | D16: William Hauserman williamhauserman@yahoo.com 304 268 7705 | E16: Annette Hauserman gailh@egismail.com | F16: TRUE | G16: TRUE | K16: TRUE | L16: 339000 | M16: 44405 | N16: 44412 | O16: 44662 | P16: MDBC2004054 | Q16: TRUE | R16: FALSE | S16: TRUE | T16: TRUE | U16: TRUE | V16: TRUE | Y16: 0.055 | Z16: =Y16-AA16 -> 0.03 | AA16: 0.025 | AB16: 495 | AC16: 44301 | AZ16: FALSE | BA16: FALSE | BC16: Missing Listed: Netsheet. Need to complete KWF Communication Consent, Financial Condition, MLS Accuracy, Notice to Buyer and Seller. | BD16: Y | BE16: Y
A17: Active | B17: 4613 Cherry Valley Dr | C17: John | D17: Stuart Newman slnewman4613@gmail.com 301-404-3166 | E17: Esther Newman 301-367-4432 esther.newman1126@gmail.com | F17: TRUE | G17: TRUE | K17: TRUE | L17: 625000 | M17: N/A | N17: 44405 | O17: 44558 | P17: MDMC2008402 | Q17: TRUE | R17: TRUE | S17: TRUE | T17: TRUE | U17: TRUE | V17: TRUE | Z17: =Y17-AA17 -> 0 | AC17: 44404 | AZ17: FALSE | BA17: FALSE | BC17: Signed MLS Sheet (Shared 7/29/2021) | BD17: Y | BE17: Y
A18: Active | B18: 530 Pritchard Drive, Linthicum Heights, MD | C18: John | D18: David Loring Company: Residential Value Work Mobile: 301-674-0160 Work Email: dsl227@aol.com | E18: N/A | F18: TRUE | G18: TRUE | K18: TRUE | L18: 379900 | M18: N/A | N18: 44399 | O18: 44561 | P18: MDAA2004064 | Q18: TRUE | R18: TRUE | S18: TRUE | T18: TRUE | U18: TRUE | V18: TRUE | Z18: =Y18-AA18 -> 0 | AZ18: FALSE | BA18: FALSE | BC18: Returned Listed: Exclusive Rights to Sell - Need initials on 19.A. | BD18: Y | BE18: Y
A19: Active | B19: 22991 Westview Dr Preston, MD 21655 | C19: Romont | D19: Verna Jenkins | E19: POA Loretta McCray Home Mobile: 213-447-1244 Home Email: consultlorettamccray@gmail.com | F19: TRUE | G19: TRUE | K19: TRUE | L19: 160000 | M19: N/A | N19: 44333 | O19: 44671 | P19: MDCM125542 | Q19: TRUE | R19: TRUE | S19: TRUE | T19: TRUE | U19: TRUE | V19: TRUE | X19: SOI | Y19: 0.06 | Z19: =Y19-AA19 -> 0.06 | AB19: 495 | AC19: 44324 | AZ19: FALSE | BA19: FALSE | BC19: BAC. Link Command to Dotloop. | BD19: Y | BE19: N
A20: Off Market | B20: 1922 Baltimore Annapolis Blvd, Annapolis | C20: Justin | D20: Tricia Johnson Home Mobile: 301-919-9433 Home Email: triciajohnson5@yahoo.com Home Address: 1922 Baltimore Annapolis Annapolis, MD 21409 US | E20: N/A | F20: TRUE | G20: TRUE | K20: TRUE | L20: 725000 | M20: 44366 | N20: N/A | O20: 44730 | P20: MDAA2000720 | Q20: None | R20: TRUE | S20: TRUE | T20: TRUE | U20: TRUE | V20: TRUE | Y20: 0.06 | Z20: =Y20-AA20 -> 0.035 | AA20: 0.025 | AB20: 495 | AC20: 44365 | AZ20: FALSE | BA20: FALSE | BC20: No listing intake, MLS Draft created. documents. Agent published. Missing Listed: Notification of Dual Agency within a Team, Netsheet, Incomplete answer LBP Addendum, Signed MLS Sheet (Shared 7/13/2021), Financial Addendum needs answer. Returned Listed: Residential Property Information - Seller names and address needed on first page. Exclusive Right to Sell - Please fill in Section 6. Please fill in blanks under Section 14. Please check boxes: Consent for DA, Financial Condition, MD Property Disclosure | BD20: Y | BE20: Y
A21: Active | B21: (Farm) 3815 Back Woods Rd Westminster | C21: Justin | D21: David Brathuhn GEORGIA560@AOL.COM 4105965840 | E21: N/A | F21: TRUE | G21: TRUE | L21: 300000 | M21: N/A | N21: 44334 | O21: 44582 | P21: MDCR203222 | Q21: TRUE | Y21: 0.1 | Z21: =Y21-AA21 -> 0.075 | AA21: 0.025 | AC21: 44218 | AZ21: FALSE | BA21: FALSE | BC21: Has two entries on Command. Link Command to Dotloop. | BD21: Y | BE21: N
A22: Active | B22: (Res) 3815 Back Woods Rd Westminster | C22: Justin | D22: David Brathuhn GEORGIA560@AOL.COM 4105965840 | E22: N/A | F22: TRUE | G22: TRUE | L22: 300000 | M22: N/A | N22: 44334 | O22: 44582 | P22: MDCR202154 | Q22: TRUE | AC22: 44218 | AZ22: FALSE | BA22: FALSE | BC22: Has two entries on Command. Link Command to Dotloop. | BD22: Y | BE22: N
A23: Active | B23: 1116 & 1120 Dicus Mill Rd Millersville, MD 21108 | C23: Justin | F23: FALSE | G23: FALSE | L23: 1650000 | M23: N/A | N23: 44013 | O23: 44511 | P23: MDAA438834 | Q23: TRUE | AC23: 44737 | AZ23: FALSE | BA23: FALSE | BC23: No Opportunity. No loop | BD23: N | BE23: N
A24: Active | B24: (Farm) 1132 Dicus Mill Rd Millersville, MD 21108 | C24: Justin | F24: FALSE | G24: FALSE | L24: 2500000 | M24: N/A | N24: 44013 | O24: 44511 | P24: MDAA429230 | Q24: TRUE | AZ24: FALSE | BA24: FALSE | BC24: No loop | BD24: N | BE24: N
A25: Active | B25: (Res) 1132 Dicus Mill Rd Millersville, MD 21108 | C25: Justin | F25: FALSE | G25: FALSE | L25: 900000 | M25: N/A | N25: 44013 | O25: 44511 | P25: MDAA438826 | Q25: TRUE | AZ25: FALSE | BA25: FALSE | BC25: No loop | BD25: N | BE25: N
A26: UC | B26: 3413 Moylan Dr | C26: John | F26: TRUE | G26: TRUE | K26: TRUE | M26: N/A | N26: 44372 | O26: 44518 | P26: MDPG2000788 | Q26: None | R26: TRUE | S26: TRUE | T26: TRUE | U26: TRUE | V26: TRUE | Y26: 0.0375 | Z26: 0.0125 | AA26: 0.025 | AB26: 0 | AC26: 44368 | AD26: William Umanzor and Veronica Umanzor | AE26: Cristhian Gonzalez | AF26: Conventional | AJ26: 500000 | AK26: 5000 | AN26: 44387 | AO26: 44417 | AS26: TRUE | AT26: N/A | AX26: N/A | AY26: Drafted | AZ26: FALSE | BA26: NA | BC26: Clear to Close | BD26: Y | BE26: Y
A27: UC | B27: 212 Gloucester Dr | C27: John | F27: TRUE | G27: TRUE | K27: TRUE | M27: N/A | N27: 44365 | O27: 44549 | P27: MDAA2000718 | Q27: None | R27: TRUE | S27: TRUE | T27: TRUE | U27: TRUE | V27: TRUE | Y27: 0.0375 | Z27: 0.0125 | AA27: 0.025 | AB27: 0 | AC27: 44375 | AD27: Tomas Guevara Carcamo and Henry Maldonado Bejarano | AE27: Noel Reyes | AF27: Conventional | AJ27: 320000 | AK27: 3200 | AN27: 44377 | AO27: 44418 | AS27: TRUE | AT27: N/A | AX27: N/A | AY27: Submitted | AZ27: FALSE | BA27: NA | BC27: COE moving to 8/10/2021. Missing UC: Need signed County Addendum. Returned Listed: MD RPD Disclosure Disclaimer - Need answer on page 4, Latent Defects. KWF Smoke Alarm - Need answer on first question. Returned UC: MD RPD Disclosure Disclaimer - Need answer on page 4, Latent Defects | BD27: Y | BE27: N
A28: UC | B28: 7906 Mansion House Crossing Pasadena | C28: Justin | F28: TRUE | G28: TRUE | K28: TRUE | M28: 44354 | N28: 44364 | O28: 44623 | P28: MDAA471220 | Q28: TRUE | R28: FALSE | S28: TRUE | T28: TRUE | U28: TRUE | V28: TRUE | Y28: 0.06 | Z28: =Y28-AA28 -> 0.035 | AA28: 0.025 | AB28: 495 | AC28: 44271 | AD28: Wei Qi Ang Gao | AE28: Han Wen Liu | AF28: Conventional | AJ28: 295000 | AK28: 5000 | AN28: 44370 | AO28: 44418 | AS28: TRUE | AT28: N/A | AX28: N/A | AY28: Drafted | AZ28: FALSE | BA28: TRUE | BC28: Clear to Close | BD28: Y | BE28: Y
A29: UC | B29: 1201 John Ross Ct | C29: Justin | F29: TRUE | G29: TRUE | K29: TRUE | M29: 44346 | N29: 44364 | O29: 44627 | P29: MDAA462562 | Q29: TRUE | R29: FALSE | S29: TRUE | T29: TRUE | U29: TRUE | V29: TRUE | Y29: 0.045 | Z29: =Y29-AA29 -> 0.02 | AA29: 0.025 | AB29: 495 | AC29: 44276 | AD29: David Hargadon and Kathryn Hargadon | AE29: Jeannie Miller | AF29: Conventional | AJ29: 1000000 | AK29: 9800 | AN29: 44372 | AO29: 44418 | AS29: TRUE | AT29: N/A | AX29: N/A | AY29: Drafted | AZ29: FALSE | BA29: TRUE | BC29: Missing Listed: Netsheet (Shared). Returned UC: Notice to Buyer and Seller - Need Buyer Agent's signature. | BD29: Y | BE29: Y
A30: UC | B30: 11 Old Station Rd Severna Park MD 21146 | C30: Patrick | D30: Patrick Codd Company: Keller Williams Flagship of Maryland Work Mobile: 443.534.3855 Work Email: pcodd@kw.com | E30: N/A | F30: TRUE | G30: TRUE | K30: TRUE | M30: 44357 | N30: 44358 | O30: 44440 | P30: MDAA471260 | Q30: TRUE | R30: TRUE | S30: TRUE | T30: TRUE | U30: TRUE | V30: TRUE | X30: Owner | AA30: 0.025 | AC30: 44349 | AD30: Michael Cornecelli and Ellie Cornecelli | AE30: Mark Hudson | AF30: Conventional | AJ30: 525000 | AK30: 15000 | AN30: 44368 | AO30: 44425 | AS30: TRUE | AT30: N/A | AX30: FALSE | AY30: Drafted | AZ30: FALSE | BA30: FALSE | BC30: Missing Listed: Netsheet | BD30: Y | BE30: Y
A31: UC | B31: 2254 Commissary Cir Odenton | C31: Justin | F31: TRUE | G31: TRUE | K31: TRUE | N31: 44385 | O31: 44671 | P31: MDAA2000894 | Q31: TRUE | R31: FALSE | S31: TRUE | T31: TRUE | U31: TRUE | V31: TRUE | Y31: 0.055 | Z31: =Y31-AA31 -> 0.03 | AA31: 0.025 | AB31: 495 | AC31: 44312 | AD31: Joseph Fong | AE31: Abhay Chaudhari | AF31: Conventional | AJ31: 361500 | AK31: 4000 | AN31: 44391 | AO31: 44425 | AS31: TRUE | AT31: N/A | AX31: TRUE | AZ31: FALSE | BA31: FALSE | BC31: Returned Listed: Exclusive Right to Sell - Initials needed on Fee Simple/Ground Rent Missing UC: EMD, HOA Docs Price Change Addendum on loop. Waiting for signatures. | BD31: Y | BE31: Y
A32: UC | B32: 560 Maryland Ave Lusby, MD 20657 | C32: Vince | D32: Mike Ricker Home Mobile: 301-536-7407 Home Email: mikericker560@yahoo.com | E32: N/A | F32: TRUE | G32: TRUE | K32: TRUE | M32: 44342 | N32: 44349 | O32: 44561 | P32: MDCA183196 | Q32: TRUE | R32: TRUE | S32: TRUE | T32: TRUE | U32: TRUE | V32: TRUE | X32: SOI | Y32: 0.05 | Z32: 0.025 | AA32: 0.025 | AB32: 495 | AC32: 44336 | AD32: Earnest Hairston and Michele Reese | AE32: Megan Ferra | AF32: FHA | AJ32: 335000 | AK32: 2500 | AN32: 44394 | AO32: 44425 | AS32: TRUE | AT32: N/A | AX32: FALSE | AZ32: FALSE | BA32: FALSE | BC32: Missing UC: Buyer signed County Addendum | BD32: Y | BE32: Y
A33: UC | B33: 8206 Courtland Manor Rd | C33: Evan | F33: TRUE | G33: TRUE | K33: TRUE | M33: 44404 | N33: 44405 | O33: 44469 | P33: MDBC2003180 | Q33: TRUE | R33: TRUE | S33: TRUE | T33: TRUE | U33: TRUE | V33: TRUE | Y33: 0.045 | Z33: 0.025 | AA33: 0.02 | AB33: 0 | AC33: 44377 | AD33: Ameta Coleman | AE33: Jennifer Kramer dela Cruz | AF33: FHA | AJ33: 221500 | AK33: 3000 | AN33: 44406 | AO33: 44428 | AS33: TRUE | AT33: N/A | AX33: FALSE | AZ33: FALSE | BA33: FALSE | BC33: Need to Split Contract Documents | BD33: Y | BE33: Y
A34: UC | B34: 7 Waldron Ave Pikesville | C34: Shaq | F34: TRUE | G34: TRUE | K34: FALSE | M34: 44378 | N34: 44379 | O34: 44643 | P34: MDBC523312 | Q34: TRUE | R34: FALSE | S34: TRUE | T34: TRUE | U34: TRUE | V34: TRUE | Y34: 0.05 | Z34: =Y34-AA34 -> 0.025 | AA34: 0.025 | AB34: 495 | AC34: 44369 | AD34: Kuba Sinla Ogundare and Beauty T Jenty Benjamin | AE34: Uchenna Onyewu | AF34: FHA | AJ34: 265000 | AK34: 5000 | AN34: 44392 | AO34: 44434 | AS34: TRUE | AT34: N/A | AX34: FALSE | AZ34: FALSE | BA34: FALSE | BC34: Returned UC: FHA Addendum - Interest rate needed. Missing Listed: Signed Netsheet (Shared 7/23/2021) | BD34: Y | BE34: N
A35: UC | B35: 8008 Dalesford Road, Parkville, MD 21234 | C35: Jen | F35: TRUE | G35: TRUE | K35: TRUE | M35: 44355 | N35: 44357 | O35: 44439 | P35: MDBC532202 | Q35: TRUE | R35: FALSE | S35: TRUE | T35: TRUE | U35: TRUE | V35: TRUE | Y35: 0.05 | Z35: 0.025 | AA35: 0.025 | AB35: 495 | AC35: 44350 | AD35: Gemcraft Homes Inc. | AE35: Lisa Hiatt | AF35: Cash | AJ35: 110000 | AK35: 5000 | AN35: 44383 | AO35: 44435 | AS35: TRUE | AT35: N/A | AX35: FALSE | AZ35: FALSE | BA35: FALSE | BC35: Clear to close. | BD35: Y | BE35: Y
A36: UC | B36: 637 Gayle Dr Linthicum Heights, MD 21090 | C36: Justin | F36: TRUE | G36: TRUE | K36: TRUE | M36: 44361 | N36: 44385 | O36: 44701 | P36: MDAA471822 | Q36: TRUE | R36: FALSE | S36: TRUE | T36: TRUE | U36: TRUE | V36: TRUE | Y36: 0.05 | Z36: 0.025 | AA36: 0.025 | AB36: 495 | AC36: 44336 | AD36: Padre S Gilliam | AE36: Harold Peters | AF36: VA | AJ36: 426500 | AK36: 1000 | AN36: 44390 | AO36: 44435 | AS36: TRUE | AT36: N/A | AX36: FALSE | AZ36: FALSE | BA36: FALSE | BC36: Missing Listed: Netsheet (Out for signature), Signed MLS Sheet (Shared 7/13/2021) Returned Listed: Exclusive Right to Sell - Seller phone number/email needed. Fill in Section 3 blanks and initials on Fee Simple/Ground Rent. | BD36: Y | BE36: Y
A37: UC | B37: 3220 Pine Crest Ct | C37: Shaq | F37: TRUE | G37: TRUE | K37: TRUE | N37: 44390 | O37: 44561 | P37: MDHR2001202 | Q37: TRUE | R37: FALSE | S37: TRUE | T37: TRUE | U37: TRUE | V37: TRUE | Y37: 0.05 | Z37: 0.025 | AA37: 0.025 | AB37: 495 | AC37: 44389 | AD37: Ahmed Jaloudi and Eman Alnatsheh | AE37: Angela Daniller | AF37: FHA | AJ37: 260000 | AK37: 1000 | AN37: 44392 | AO37: 44435 | AS37: TRUE | AT37: N/A | AX37: TRUE | AZ37: FALSE | BA37: FALSE | BC37: Missing Listed: Netsheet (Shared 7/23/2021) Missing UC: Proof of Funds | BD37: Y | BE37: Y
A38: UC | B38: 1354 Hazel Nut Ct | C38: Justin | F38: TRUE | G38: TRUE | K38: TRUE | M38: 44393 | N38: 44399 | O38: 44736 | P38: MDAA2003690 | Q38: TRUE | R38: TRUE | S38: TRUE | T38: TRUE | U38: TRUE | V38: TRUE | Y38: 0.06 | Z38: 0.035 | AA38: 0.025 | AB38: 495 | AC38: 44372 | AD38: Michael E. Lougee & Betty R. Lougee | AE38: Beth Costello | AF38: Conventional | AJ38: 251000 | AK38: 10000 | AN38: 44406 | AO38: 44435 | AS38: TRUE | AT38: N/A | AX38: FALSE | AZ38: FALSE | BA38: FALSE | BC38: Missing Listed: Netsheet, signed MD Residential Property Information, Signed MLS Sheet (Shared 7/22/2021) Missing Agent's signature and initials on Disclosure Info LBP, Competitive Market Analysis, LBP after 1978, Notice to Buyer and Seller, Exclusive Right to Sell | BD38: Y | BE38: Y
A39: UC | B39: 789 Old Herald Harbor Rd, Crownsville, MD 21032 | C39: Vince | F39: TRUE | G39: TRUE | K39: TRUE | M39: 44392 | N39: 44399 | O39: 44561 | P39: MDAA2003632 | Q39: TRUE | R39: TRUE | S39: TRUE | T39: TRUE | U39: TRUE | V39: TRUE | Y39: 0.05 | Z39: 0.025 | AA39: 0.025 | AB39: 495 | AC39: 44378 | AD39: Evan Pickett & Christine Picciot | AE39: Katerina Erhard | AF39: Conventional | AJ39: 475000 | AK39: 10000 | AN39: 44407 | AO39: 44435 | AS39: TRUE | AT39: N/A | AX39: FALSE | AZ39: FALSE | BA39: FALSE | BC39: MLS Sheet (Shared 8/2/2021) UC: Copy of EMD, Fix County Addendum 2 Opportunities in command? | BD39: Y | BE39: Y
A40: UC | B40: 307 Dogwood Rd Millersville | C40: Justin | F40: TRUE | G40: TRUE | K40: TRUE | M40: 44396 | N40: 44406 | O40: 44621 | P40: MDAA2003634 | Q40: TRUE | R40: FALSE | S40: TRUE | T40: TRUE | U40: TRUE | V40: TRUE | Y40: 0.06 | Z40: =Y40-AA40 -> 0.035 | AA40: 0.025 | AB40: 495 | AC40: 44265 | AD40: Gerald G Stansbury & Neva G Stansbury | AE40: Ray Sharif | AF40: VA | AJ40: 460000 | AK40: 5000 | AN40: 44411 | AO40: 44438 | AS40: TRUE | AT40: N/A | AW40: Out to sellers | AX40: FALSE | AZ40: FALSE | BA40: FALSE | BC40: Need MLS Remarks. Need uploaded signed disclosures on MLS. Returned Listed: Exclusive Right to Sell - Need initials on fee simple/ground rent. Need Agent Signature. KWF Competitive Market - Need Agent Signature. Notice to Buyer and Seller - Need to complete seller signatures and need agent signature.. Disclosure Info LBP - Need Agent initials and signature. Smoke Alarm Disclosure - Need answers. Waiting on the signatures for Financial Condition and MD Residential Property Information. Need to split documents. Incomplete Contract: Need to complete informations Listing and Buying Agent. | BD40: Y | BE40: Y
A41: UC | B41: 2 North Star Ct Pikesville | C41: Justin | F41: TRUE | G41: TRUE | K41: TRUE | M41: 44396 | N41: 44406 | O41: 44649 | P41: MDBC2004072 | Q41: TRUE | R41: TRUE | S41: TRUE | T41: TRUE | U41: TRUE | V41: TRUE | Y41: 0.06 | Z41: =Y41-AA41 -> 0.035 | AA41: 0.025 | AB41: 495 | AC41: 44286 | AD41: HP Maryland I, LLC. | AE41: Lisa Hoover | AF41: Cash | AJ41: 265000 | AK41: 2650 | AN41: 44411 | AO41: 44439 | AS41: TRUE | AT41: N/A | AX41: FALSE | AZ41: FALSE | BA41: FALSE | BC41: Need signature on Tenant Occupied Addendum Returned Listed: Exclusive Right to Sell - Please answer checkbox on Section 22, Home Warranty. Missing Listed: Netsheet Signed MLS Sheet (Shared 7/29/2021). Incomplete Contract: Need to fill other infos on page 13, listing and buying agent infos. Need to split documents | BD41: Y | BE41: Y
A42: UC | B42: 24612 Showbarn Circle Damascus | C42: Justin | F42: TRUE | G42: TRUE | K42: TRUE | N42: 44407 | O42: 44772 | P42: MDMC2008394 | Q42: TRUE | R42: TRUE | S42: TRUE | T42: TRUE | U42: TRUE | V42: TRUE | Y42: 0.035 | Z42: 0.01 | AA42: 0.025 | AB42: 0 | AC42: 44406 | AD42: Christopher Bauman | AE42: Marcus Schwaderer | AF42: Cash | AJ42: 452700 | AK42: 10000 | AN42: 44410 | AO42: 44442 | AS42: TRUE | AT42: N/A | AX42: FALSE | AZ42: FALSE | BA42: FALSE | BC42: Missing Listed: Netsheet Need to split documents | BD42: Y | BE42: Y
A43: UC | B43: 24624 Showbarn Circle Damascus | C43: Justin | F43: TRUE | G43: TRUE | K43: TRUE | M43: 44403 | N43: 44406 | O43: 44656 | P43: MDMC2005928 | Q43: TRUE | R43: FALSE | S43: TRUE | T43: TRUE | U43: TRUE | V43: TRUE | Y43: 0.045 | Z43: 0.02 | AA43: 0.025 | AB43: 495 | AC43: 44286 | AD43: Darwin Tunche & Kimberly Tunche | AE43: Alexander Modaressi | AF43: Conventional | AJ43: 526250 | AK43: 10000 | AN43: 44411 | AO43: 44449 | AS43: TRUE | AT43: N/A | AX43: FALSE | AZ43: FALSE | BA43: FALSE | BC43: Missing Agent signature on KWF Communication Consent, Notice to Buyer and Seller, LBP After 1978. Missing Listed: Netsheet, KWF Communication Consent, Notice to Buyer and Seller, LBP After 1978. Missing UC: EMD | BD43: Y | BE43: Y
A44: UC | B44: 2723 Cornet Ct, Silverspring | C44: Justin | F44: TRUE | G44: TRUE | K44: TRUE | M44: 44383 | N44: 44389 | O44: 44729 | P44: MDMC2002096 | Q44: TRUE | R44: FALSE | S44: TRUE | T44: TRUE | U44: TRUE | V44: TRUE | Y44: 0.05 | Z44: 0.025 | AA44: 0.025 | AB44: 495 | AC44: 44369 | AD44: Germaine Sob | AE44: Jason Clark | AF44: FHA | AJ44: 500000 | AK44: 7000 | AN44: 44406 | AO44: 44469 | AS44: TRUE | AT44: N/A | AX44: FALSE | AZ44: FALSE | BA44: FALSE | BC44: Need signatures on KWF Disclosures and Consent for Dual Agency. Need answers and signature on Financial Disclosure. Need both sellers phone numbers on KWF Communication Consent Addendum. Missing Listed: Missing signed KWF Disclosures, signed MLS Sheet, Financial Disclosure, Signed Consent for Dual Agency, Netsheet. | BD44: Y | BE44: Y
A45: UC | B45: 412 Girard St #79 | C45: Justin | F45: TRUE | G45: TRUE | K45: TRUE | Q45: None | R45: FALSE | S45: TRUE | T45: None | U45: None | V45: FALSE | Y45: 0.04 | Z45: 0.015 | AA45: 0.025 | AB45: 495 | AC45: 44351 | AD45: Jamal Leacock | AE45: Justin Matney | AF45: FHA | AJ45: 150000 | AK45: 1500 | AN45: 44405 | AO45: 44439 | AZ45: FALSE | BA45: FALSE | BC45: Listing Documents has only 1 seller. Contract Documents along with Disclosures has 2 seller signatures. Need 2nd seller to sign all listing documents. Dual Rep. 4% Total Comm | BD45: Y | BE45: Y
A46: UC | B46: 544 Chalcot Sq | C46: Shaq | D46: Michael Kahl Home Phone: 410-375-7319 Home Email: mkahl@jwsons.com | E46: Kristen Kahl Home Phone: 443-934-7861 Home Email: kristen@carboywinery.com | F46: TRUE | G46: TRUE | K46: TRUE | L46: 224900 | M46: 44413 | N46: 44414 | O46: 44561 | P46: MDBC2003178 | Q46: Ordered | R46: TRUE | S46: TRUE | T46: TRUE | U46: TRUE | V46: TRUE | W46: 1822063 | Y46: 0.05 | Z46: 0.025 | AA46: 0.025 | AB46: 495 | AC46: 44383 | AD46: Erick Hernandez | AE46: Jasmin Brown | AF46: FHA | AG46: Mid Atlantic Settlement Services | AH46: Brant Patrick Millham Brant.Millham@grarate.com 443-404-2037 | AI46: 200 | AJ46: 228000 | AK46: 2200 | AL46: Mid Atlantic Settlement Services | AM46: None | AN46: 44417 | AO46: 44441 | AP46: 44442 | AS46: TRUE | AT46: TRUE | AU46: FALSE | AV46: FALSE | AW46: FALSE | AX46: FALSE | AZ46: FALSE | BA46: FALSE | BC46: MLS Sheet (Shared 8/6/2021) Missing UC: EMD | BD46: Y | BE46: Y
A47: UC | B47: 20649 Anndyke Way, Germantown | C47: Justin | F47: TRUE | G47: TRUE | H47: $58/Monthly | K47: TRUE | M47: 44391 | N47: 44392 | O47: 44691 | P47: MDMC764090 | Q47: TRUE | R47: TRUE | S47: TRUE | T47: TRUE | U47: TRUE | V47: TRUE | Y47: 6%% | Z47: 0.035 | AA47: 0.025 | AB47: 495 | AC47: 44329 | AD47: Francis Nolasco-Valle & Ana E Nolasco | AE47: Fadia Shadid | AF47: FHA | AG47: GPN Title | AH47: Carey Ann Cyr mymortgageteam@cmgfi.com 615-456-4456 | AJ47: 533000 | AK47: 20000 | AL47: GPN Title | AM47: None | AN47: 44412 | AO47: 44442 | AQ47: Scheduled with Justin | AR47: 8/7/2021 1PM - As if for info only | AS47: TRUE | AT47: TRUE | AU47: TRUE | AV47: FALSE | AW47: FALSE | AX47: TRUE | AZ47: FALSE | BA47: FALSE | BC47: Missing Listed: Netsheet, Signed KWF Smoke Alarm Disclosure. | BD47: Y | BE47: Y | BF47: HOA $58/Monthly, Order HOA, Call Title, Complete Qualia
A48: UC | B48: 11824 Eton Manor Dr #103 Germantown, MD 20876 | C48: Jen | D48: Gurdip Singh 785-317-5078 singh.gurdip1986@gmail.com | E48: Harleen Singh harleen1971@gmail.com 7853178053 | F48: TRUE | G48: TRUE | K48: TRUE | L48: 250000 | M48: 44405 | N48: 44408 | O48: 44561 | P48: MDMC2006802 | Q48: NA (None on LI) | R48: TRUE | S48: TRUE | T48: TRUE | U48: TRUE | V48: TRUE | Y48: 0.055 | Z48: =Y48-AA48 -> 0.03 | AA48: 0.025 | AB48: 0 | AC48: 44390 | AD48: Huiping Zhang | AE48: Jumei (May) Zhang | AF48: Cash | AG48: Lucy Lu Landmark Title | AH48: None | AI48: None | AJ48: 243000 | AK48: 4000 | AL48: Landmark Title | AM48: None | AN48: 44417 | AO48: 44442 | AR48: No inspections | AS48: TRUE | AT48: TRUE | AU48: TRUE | AV48: TRUE | AW48: FALSE | AX48: TRUE | AZ48: FALSE | BA48: FALSE | BC48: Returned Listed: KWF Smoke Alarm - Last question needs to be answered. Missing UC: Proof of Funds. | BD48: Y | BE48: Y
A49: UC | B49: 5959 Benton Heights Ave Baltimore | C49: Shaq | D49: Kevin Knight 443-876-2364 bigduke94@gmail.com | E49: N/A | F49: TRUE | G49: TRUE | K49: TRUE | L49: 210000 | M49: 44357 | N49: 44349 | O49: 44666 | P49: MDBA547478 | Q49: TRUE | R49: TRUE | S49: TRUE | T49: TRUE | U49: TRUE | V49: TRUE | X49: Sphere | Y49: 0.05 | Z49: =Y49-AA49 -> 0.025 | AA49: 0.025 | AB49: 495 | AC49: 44302 | AD49: Keara Burrell | AE49: Cortney Chaite Amanda Hoffman transactions@mykeyhometeam.com 413-627-5296 TC | AF49: FHA | AG49: Renee Osborne Renee@endeavortitle.com 410-666-3780 | AH49: Brad Restivo brestivo@firsthome.com 443-744-4443 Thomas Laughlin Assistant TLaughlin@firsthome.com | AI49: 500 | AJ49: 210000 | AK49: 2800 | AL49: Endeavor Title Company | AM49: None | AN49: 44417 | AO49: 44446 | AP49: 44447 | AS49: TRUE | AT49: TRUE | AU49: TRUE | AV49: TRUE | AW49: FALSE | AX49: FALSE | AZ49: FALSE | BA49: FALSE | BC49: Netsheet and MLS - Out for signature. Missing UC: EMD | BD49: Y | BE49: Y
A50: UC | B50: 5939 Linthicum Heights | C50: Jen | F50: TRUE | G50: TRUE | K50: TRUE | M50: 44411 | N50: 44412 | O50: 44561 | P50: MDAA472062 | Q50: TRUE | R50: TRUE | S50: TRUE | T50: TRUE | U50: TRUE | V50: TRUE | Y50: 0.06 | Z50: 0.035 | AA50: 0.025 | AB50: 495 | AC50: 44411 | AD50: Stephen Coursey and Amanda Coursey | AE50: Daniel Drechsler Dan@dansellsmd.com Transco TransactionCoordinator@ExitResults.com TC | AF50: Conventional | AG50: Thomas J. Drechsler tom@sagetitlegroup.com 410-499-4039 Donna Gain 410-821-4510 donna.gain@sagetitlegroup.com Virginia Malatt veppley@sagetitlegroup.com | AH50: Kristi Lynn Grams kgrams@westtownbank.com 301-676-5352 (Cell) 240-575-3664 (Office) | AI50: 250 | AJ50: 465000 | AK50: 2500 | AL50: EXIT Results Realty | AM50: None | AN50: 44416 | AO50: 44447 | AP50: 44441 | AR50: 44419.375 | AS50: FALSE | AT50: TRUE | AU50: FALSE | AV50: FALSE | AW50: FALSE | AX50: TRUE | AZ50: FALSE | BA50: FALSE | BC50: Netsheet (Shared 8/4/2021), Missing UC: EMD | BD50: Y | BE50: Y | BF50: AUC, May close 9/7. Can we find out if their title company will offer either presigning or virtual signing since Linda is in TX? She will come out one time before closing to make sure everything is cleared out and could presign then. It would be helpful if she didn’t have to make two trips.
A51: UC | B51: 613 Springfield Ave | C51: Shaq | D51: Jerryn McCray | F51: FALSE | G51: TRUE | K51: FALSE | L51: 125000 | M51: N/A | O51: 44825 | R51: FALSE | S51: FALSE | T51: FALSE | U51: FALSE | V51: TRUE | X51: Personal Sphere | Y51: 0.05 | Z51: 0.025 | AA51: 0.025 | AB51: 495 | AC51: 44400 | AD51: A1 Holdings LLC | AE51: Shaq McCray | AF51: Cash | AG51: Legacy Settlement Services David Euga | AJ51: 117000 | AK51: 1000 | AL51: Keller Williams Flagship | AM51: None | AN51: 44416 | AO51: 44447 | AP51: 44441 | AS51: NA | AT51: NA | AU51: FALSE | AV51: FALSE | AW51: TRUE | AX51: FALSE | AZ51: FALSE | BA51: FALSE | BC51: Need Agent Signature on Exclusive Rights to Sell, KWF Competitive Market, LBP after 1978, Notice to Buyer and Seller. Missing Listed: Netsheet, Signed MLS Sheet. Drafted MLS. | BD51: Y | BE51: Y | BF51: Flagship first form submitted
A52: UC | B52: 27 Clearwater Ct Baltimore, MD 21220 | C52: Justin | E52: James McNamara | F52: TRUE | G52: TRUE | I52: Sewer | K52: TRUE | M52: 44357 | N52: 44406 | O52: 44664 | P52: MDBC532860 | Q52: None | R52: TRUE | S52: TRUE | T52: TRUE | U52: TRUE | V52: TRUE | X52: TNG System | Y52: 0.05 | Z52: =Y52-AA52 -> 0.025 | AA52: 0.025 | AB52: 495 | AC52: 44312 | AD52: Ariana Macahia & Gage Allen | AE52: Christy Kopp Re/Max Components christykopp@gmail.com 443-922-1983 Adrianna Kopp adriannakopp@gmail.com | AF52: FHA | AG52: Kelley Lee Powerhouse Title Group, LLC 443-299-6273 KelleyL@ptgtitle.com | AH52: Sierra Pacific Mortgage | AI52: 500 | AJ52: 233000 | AK52: 1000 | AL52: Re/Max Components | AM52: 0.02 | AN52: 44411 | AO52: 44456 | AP52: 44432 | AR52: 8/11/2021 9AM - As Is with Inspection | AS52: TRUE | AT52: TRUE | AU52: FALSE | AV52: TRUE | AW52: FALSE | AX52: FALSE | AZ52: FALSE | BA52: FALSE | BC52: Returned Listed: Financial Disclosure - Need answers. Missing UC: EMD | BD52: Y | BE52: Y
A53: Closed | B53: 6550 Frietchie Row, Columbia, MD, USA | C53: Justin | F53: TRUE | G53: TRUE | K53: TRUE | N53: 44350 | O53: 44662 | P53: MDHW295308 | Q53: TRUE | R53: FALSE | S53: TRUE | T53: TRUE | U53: TRUE | V53: TRUE | Y53: 0.05 | Z53: =Y53-AA53 -> 0.025 | AA53: 0.025 | AB53: 495 | AC53: 44333 | AD53: Diversified Residential Homes 2 LLC | AE53: Julie Colquitt | AF53: Cash | AJ53: 311999 | AK53: 9150 | AN53: 44363 | AO53: 44414 | AY53: Submitted | AZ53: FALSE | BA53: TRUE | BC53: 50% John, 40% Justin, 10% Lauren | BD53: Y | BE53: N
A54: Closed | B54: 3628 Bay Dr Baltimore MD 21220 | C54: Shaq | M54: N/A | N54: 44336 | O54: 44561 | P54: MDBC529792 | Q54: =N54-2 -> 44334 | T54: Y | U54: Y | Y54: 0.045 | Z54: =Y54-AA54 -> 0.025 | AA54: 0.02 | AB54: 495 | AC54: 44334 | AD54: Brandon Homer Phaneuf and Ericha Lyn Sandoval | AE54: Michael Joseph | AF54: Conventional | AJ54: 560000 | AK54: 5600 | AN54: 44378 | AO54: 44405 | AY54: Submitted | BC54: Clear to close. | BD54: Y | BE54: Y
A55: Closed | B55: 921 Redmore Dr, Severn, MD 21144 | C55: Justin | N55: 44295 | O55: 44544 | P55: MDAA458880 | R55: Y | U55: Y | X55: AO | Y55: 0.06 | Z55: =Y55-AA55 -> 0.035 | AA55: 0.025 | AB55: 495 | AC55: 44310 | AD55: Sylvie Ndonue | AE55: Babatunde Ojajuni | AF55: FHA | AJ55: 480000 | AK55: 10000 | AN55: 44372 | AO55: 44400 | AY55: Submitted | BC55: Returned UC: LBP Disclosure - Buyer Acknowledgement needs to be filled. (Amanda already reached out to coop last week but no response received) | BD55: Y | BE55: N
A56: Closed | B56: 1422 Alberta Dr District Heights MD 20747 | X56: Investor | AB56: 0 | AC56: 44333 | AD56: Christopher Tyree | AE56: Debbie Robinson-Omotosho | AF56: Conventional | AJ56: 369900 | AK56: 4000 | AN56: 44346 | AO56: 44400 | AY56: Submitted | BC56: Clear to close. | BD56: Y | BE56: N
A57: Closed | B57: 1833 Oriole Ct | C57: John | M57: N/A | N57: 44379 | O57: 44563 | P57: MDAA2002212 | U57: Y | AC57: 44379 | AD57: Rebecca Wilmoth | AE57: Rebecca Wilmoth | AF57: No Financing Contigency | AJ57: 195000 | AK57: 5000 | AN57: 44381 | AO57: 44400 | AY57: Submitted | BC57: Clear to close. | BD57: Y | BE57: N
A58: Closed | B58: 1515 Wampanoag Dr Severn, MD 21144 | C58: Justin | N58: 44357 | O58: 44623 | P58: MDAA468904 | Y58: 0.06 | Z58: =Y58-AA58 -> 0.035 | AA58: 0.025 | AC58: 44318 | AD58: Cole Thompson and Shanan McFall | AE58: Dawn Hamilton Smith | AF58: Conventional | AJ58: 433000 | AK58: 15000 | AN58: 44365 | AO58: 44396 | AY58: Submiited | BC58: Clear to close. | BD58: Y | BE58: Y
A59: Closed | B59: 2536 Sandy Run Ct | C59: Justin | M59: 44329 | N59: 44336 | O59: 44599 | P59: MDAA467950 | Q59: No | R59: Y | T59: No | U59: Y | X59: Ideal Agent | Y59: 0.045 | Z59: =Y59-AA59 -> 0.02 | AA59: 0.025 | AB59: 495 | AC59: 44237 | AD59: Helen Dierker | AE59: Gayle Roberts | AF59: Conventional | AJ59: 467000 | AK59: 5000 | AN59: 44354 | AO59: 44389 | AY59: Submitted | BC59: Missing UC: County Addendum, EMD | BD59: Y | BE59: N
A60: Closed | B60: 7945 Charlesmont Road, Dundalk, MD 21222 | C60: Shaq | N60: 44344 | O60: 44561 | X60: SOI | Y60: 0.045 | Z60: =Y60-AA60 -> 0.025 | AA60: 0.02 | AB60: 495 | AC60: 44334 | AD60: Ashley Duverneau | AE60: Briana Thezard | AF60: Conventional | AJ60: 185000 | AK60: 3000 | AN60: 44347 | AO60: 44385 | AY60: Submitted | BC60: Clear to close | BD60: Y | BE60: N
A61: Closed | B61: 3232 Tartarian Ct Halethorpe | C61: Justin | N61: 44351 | O61: 44578 | P61: MDBC531302 | X61: TNG System | Y61: 0.06 | Z61: =Y61-AA61 -> 0.035 | AA61: 0.025 | AB61: 495 | AC61: 44214 | AD61: Brightview Realty LLC | AE61: Bin Liu | AF61: N/A | AJ61: 91500 | AK61: 20000 | AN61: 44354 | AO61: 44383 | AY61: Submitted | BC61: Clear to close. Change in Terms Addendum on loop - Waiting for Buyer's signature for the extension of Closing Date. (7/1 to 7/6) | BD61: Y | BE61: N
A62: Closed | B62: 8075 Catherine Ave Pasadena MD 21122 | C62: Justin | N62: 44291 | O62: 44348 | P62: MDAA464026 | R62: Y | U62: Y | X62: AO | Y62: 0.05 | Z62: =Y62-AA62 -> 0.025 | AA62: 0.025 | AB62: 495 | AC62: 44287 | AD62: Jasper M. Alino | AE62: Michael Hagan | AF62: VA | AJ62: 338000 | AK62: 3400 | AN62: 44327 | AO62: 44377 | AY62: Submitted | BC62: Listed: Financial Condition, MLS Sheet, LA, Consent for Dual Agency - Might move to 6/30
A63: Closed | B63: 2106 Roxanne Place Temple Hills | C63: John | M63: 44333 | N63: 44336 | O63: 44497 | P63: MDPG606630 | Q63: =N63-2 -> 44334 | T63: Y | U63: Y | X63: Investor | Z63: =Y63-AA63 -> 0 | AB63: 495 | AC63: 44329 | AD63: Tevin Williams | AE63: Kimberlee Randall | AF63: FHA | AJ63: 415000 | AK63: 6500 | AN63: 44340 | AO63: 44379 | AY63: Submitted | BC63: waiting on MC's re
A64: Closed | B64: 473 Kenilworth Ct, Glen Burnie MD 21061 | C64: John | N64: 44256 | O64: 44615 | P64: MDAA460380 | R64: Y | U64: Y | X64: Zoho Lead | Y64: 0.0375 | Z64: =Y64-AA64 -> 0.0125 | AA64: 0.025 | AB64: 0 | AC64: 44253 | AD64: Veranna Phillips | AE64: Dru Yokum | AF64: FHA | AJ64: 250000 | AK64: 1500 | AN64: 44323 | AO64: 44378 | AY64: Submitted | BC64: Clear to close. Might closed on 7/30.
A65: Closed | B65: 2243 Autumn Valley Circle Gambrills MD 21054 | C65: Justin | M65: 44270 | N65: 44291 | O65: 44623 | P65: MDAA461824 | Q65: =N65-2 -> 44289 | T65: Y | U65: Y | X65: SOI | Y65: 0.05 | Z65: =Y65-AA65 -> 0.025 | AA65: 0.025 | AB65: 495 | AC65: 44270 | AD65: Stephen Fischer and Demalyn Fischer | AE65: Farrah Morgan | AF65: Conventional | AJ65: 417500 | AK65: 1000 | AN65: 44350 | AO65: 44377 | AY65: Submitted | BC65: Clear to close
A66: Closed | B66: 666 Kittendale Cir Middle River | C66: Shaq | N66: 44281 | O66: 44600 | P66: MDBC523178 | R66: Y | U66: Y | X66: SOI | Y66: 0.045 | Z66: =Y66-AA66 -> 0.02 | AA66: 0.025 | AB66: 495 | AC66: 44277 | AD66: Haritha Vemana | AE66: Jasmin Brown | AF66: Conventional | AJ66: 220000 | AK66: 2250 | AN66: 44333 | AO66: 44372 | AY66: Submitted | BC66: Listed and Under Contract Approved
A67: Closed | B67: 320 Margaret Ave, Baltimore, MD 21221 | C67: Shaq | M67: 44322 | N67: 44323 | O67: 44658 | P67: MDBC524926 | Q67: 44322 | R67: 44322 | S67: 44323 | U67: Y | X67: SOI | Y67: 0.05 | Z67: =Y67-AA67 -> 0.025 | AA67: 0.025 | AB67: 495 | AC67: 44300 | AD67: Mark Mendoza | AJ67: 210000 | AK67: 3000 | AN67: 44333 | AO67: 44368 | AY67: Done | BC67: Listed and Under Contract Approved
A68: Closed | B68: 802 Rambo Ct Halethorpe M 21227 | C68: Justin | N68: 44351 | O68: 44578 | P68: MDBC531288 | X68: TNG System | Y68: 0.06 | Z68: =Y68-AA68 -> 0.035 | AA68: 0.025 | AB68: 495 | AC68: 44216 | AD68: Brightview Realty LLC | AJ68: 91500 | AK68: 20000 | AN68: 44354 | AO68: 44368 | AY68: Done | BC68: Missing UC: EMD. Cash offer there isn’t a loan addendum proof of funds loaded
A69: Closed | B69: 1700 Manning Rd, Glen Burnie, MD 21061 | C69: John | M69: N/A | N69: 44323 | O69: 44497 | P69: MDAA467174 | R69: Y | U69: Y | X69: Investor | Y69: 0.0375 | Z69: =Y69-AA69 -> 0.0125 | AA69: 0.025 | AB69: 0 | AJ69: 300000 | AN69: 44328 | AO69: 44363 | AY69: Done
A70: Closed | B70: 3104 Madison St, Hyattsville, MD, 20782 | C70: Justin | M70: 44322 | N70: 44343 | O70: 44635 | P70: MDPG605598 | Q70: =N70-2 -> 44341 | T70: Y | U70: Y | X70: Ideal Agent | Y70: 0.045 | Z70: =Y70-AA70 -> 0.02 | AA70: 0.025 | AB70: 495 | AJ70: 330000 | AN70: 44341 | AO70: 44365 | AY70: Done | BC70: Resubmitted
A71: Closed | B71: 7802 Summit Dr, Pasadena, MD 21122 | C71: Shaq | M71: 44322 | N71: 44323 | O71: 44561 | P71: MDAA467306 | Q71: 44322 | R71: 44322 | S71: 44323 | U71: Y | X71: SOI | Y71: 0.045 | Z71: =Y71-AA71 -> 0.025 | AA71: 0.02 | AB71: 495 | AJ71: 500000 | AN71: 44326 | AO71: 44355 | AY71: Done
A72: Closed | B72: 6919 Decatur Pl Hyattsville MD 20784 | C72: John | N72: 44287 | O72: 44440 | P72: MDPG601408 | R72: Y | U72: Y | X72: Investor | Y72: 0.0375 | Z72: =Y72-AA72 -> 0.0125 | AA72: 0.025 | AB72: 0 | AJ72: 435000 | AN72: 44313 | AO72: 44349
A73: Closed | B73: 1501 Saunders Way Glen Burnie, MD 21061 | C73: Shaq | M73: 44320 | N73: N/A | O73: 44664 | P73: MDAA464918 | R73: Y | U73: Y | X73: SOI | Y73: 0.05 | Z73: =Y73-AA73 -> 0.025 | AA73: 0.025 | AB73: 495 | AJ73: 292000 | AN73: 44322 | AO73: 44349
A74: Closed | B74: 2404 Chestnut Terrace Ct Unit #101 | C74: Justin | N74: 44280 | O74: 44624 | P74: MDAA463076 | R74: Y | U74: No | X74: AO | Y74: 0.06 | Z74: =Y74-AA74 -> 0.035 | AA74: 0.025 | AB74: 495 | AJ74: 272000 | AN74: 44295 | AO74: 44348
A75: Closed | B75: 6312 Springbrook Ln, Clinton, MD, | C75: Justin | N75: 44280 | O75: 44637 | P75: MDPG600916 | Q75: Y | R75: Y | U75: Y | X75: KW Referral | Y75: 0.06 | Z75: =Y75-AA75 -> 0.035 | AA75: 0.025 | AB75: 495 | AJ75: 300000 | AN75: 44334 | AO75: 44344 | BA75: Y | BC75: 25% Referral, 40/60
A76: Closed | B76: 4901 Gunther Street | C76: John | P76: MDPG596984 | X76: Investor | Y76: 0.0375 | Z76: =Y76-AA76 -> 0.0125 | AA76: 0.025 | AB76: 0 | AJ76: 329000 | AN76: 44293 | AO76: 44344
A77: Closed | B77: 5117 Keota Terrace, College Park, MD 20740 | C77: Justin | X77: AO | Y77: 0.06 | Z77: =Y77-AA77 -> 0.035 | AA77: 0.025 | AB77: 495 | AJ77: 350000 | AN77: 44289 | AO77: 44330
A78: Closed | B78: 3501 Falling Run Laurel | C78: Justin | X78: AO | Y78: 0.05 | Z78: =Y78-AA78 -> 0.025 | AA78: 0.025 | AB78: 495 | AJ78: 390000 | AN78: 44297 | AO78: 44321
A79: Closed | B79: 330 Salisbury Rd Edgewater | C79: Justin | X79: AO | Y79: 0.06 | Z79: =Y79-AA79 -> 0.035 | AA79: 0.025 | AB79: 495 | AJ79: 325000 | AN79: 44293 | AO79: 44321
A80: Closed | B80: 407 Frankle St Brooklyn | C80: Justin | X80: SOI | Y80: 0.05 | Z80: =Y80-AA80 -> 0.025 | AA80: 0.025 | AB80: 495 | AJ80: 247000 | AN80: 44286 | AO80: 44314
A81: Closed | B81: 825 Lannerton Rd Middle River, MD, 21220 | C81: Shaq | X81: SOI | Y81: 0.05 | Z81: =Y81-AA81 -> 0.025 | AA81: 0.025 | AB81: 495 | AJ81: 165000 | AN81: 44291 | AO81: 44315
A82: Closed | B82: 8078 Elton St Glen Burnie | C82: Shaq | X82: SOI | Y82: 0.05 | Z82: =Y82-AA82 -> 0.03 | AA82: 0.02 | AB82: 495 | AJ82: 425000 | AO82: 44274
A83: Closed | B83: 1503 Perrell Lane Bowie | C83: Justin | X83: Investor | Y83: 0.0375 | Z83: =Y83-AA83 -> 0.0125 | AA83: 0.025 | AB83: 0 | AJ83: 417500 | AO83: 44272
A84: Closed | B84: 6 Kilkea Ct Nottingham | C84: Justin | X84: AO | Y84: 0.06 | Z84: =Y84-AA84 -> 0.035 | AA84: 0.025 | AB84: 495 | AJ84: 375000 | AO84: 44287
A85: Closed | B85: 1310 Howard Rd Glen Burnie | C85: John | X85: Investor | Y85: 0.0375 | Z85: =Y85-AA85 -> 0.0125 | AA85: 0.025 | AB85: 0 | AJ85: 330000 | AO85: 44313
A86: Closed | B86: 406 Broadview Blvd. N Glen Burnie | C86: John | X86: Investor | Y86: 0.0375 | Z86: =Y86-AA86 -> 0.0125 | AA86: 0.025 | AB86: 0 | AJ86: 329000 | AO86: 44308
A87: Closed | B87: 10504 Vincent Farm Lane White Marsh | C87: Lee | X87: Sphere | Y87: 0.035 | Z87: =Y87-AA87 -> 0.01 | AA87: 0.025 | AB87: 495 | AJ87: 325000 | AO87: 44319
A88: Terminated | B88: 27 Clearwater Ct Baltimore | C88: Justin | M88: 44357 | N88: 44368 | P88: MDBC532860 | U88: Y | X88: TNG System | Y88: 0.05 | Z88: =Y88-AA88 -> 0.025 | AA88: 0.025 | AB88: 495 | AC88: 44312 | AD88: Chalsie Sennett and Daniel Johnson | AE88: Michael Turiello | AF88: FHA | AJ88: 235000 | AK88: 2500 | AN88: 44375 | AO88: 44407 | AY88: Drafted | BC88: 2% SPCC COE is moving Returned Listed: Financial Disclosure - Need to fill in a,b,c or d Missing UC: Signed County Addendum, Proof of Funds, RPD Disclosure/Disclaimer, EMD | BD88: Y | BE88: Y
A89: Terminated | B89: 5959 Benton Heights Ave Baltimore | C89: Shaq | N89: 44349 | O89: 44666 | P89: MDBA547478 | U89: Y | X89: Sphere | Y89: 0.05 | Z89: =Y89-AA89 -> 0.025 | AA89: 0.025 | AB89: 495 | AC89: 44302 | AD89: Kennard Robinson | AE89: Latonya Dickerson | AF89: Conventional | AJ89: 210000 | AK89: 2100 | AN89: 44378 | AO89: 44407 | AY89: Drafted | BC89: Missing Listed: Netsheet (Shared 7/23/2021), Signed MLS Sheet (Shared). Might move closing. Fell through? | BD89: Y | BE89: Y
A90: Terminated | B90: 789 Old Herald Harbor Rd | C90: Vince | M90: 44392 | N90: 44399 | O90: 44561 | P90: MDAA2003632 | Y90: 0.05 | Z90: 0.025 | AA90: 0.025 | AB90: 495 | AC90: 44378 | AD90: Evan Pickett & Christine Picciot | AE90: Katerina Erhard | AF90: Conventional | AJ90: 475000 | AK90: 10000 | AN90: 44407 | AO90: 44435 | BC90: MLS Sheet (Shared 8/2/2021) Missing UC: EMD | BD90: Y | BE90: Y
A91: Terminated | B91: 2723 Cornet Ct, Silverspring | C91: Justin | M91: 44383 | N91: 44389 | O91: 44729 | P91: MDMC2002096 | S91: Showing requirements, weekdays after 6 pm. Weekends anytime. | Y91: 0.05 | Z91: 0.025 | AA91: 0.025 | AB91: 495 | AC91: 44369 | AD91: Tewodros Weledegabriel and Tigist Abebe Eshete | AE91: Gellal Minie | AF91: Conventional | AJ91: 500000 | AK91: 20000 | AN91: 44396 | AO91: 44439 | BC91: MLS Sheet out for signature. Need signatures on KWF Disclosures and Consent for Dual Agency. Need answers and signature on Financial Disclosure. Need both sellers phone numbers on KWF Communication Consent Addendum. Returned UC: Contract - Need Selling Brokerage info on page 1, #7 (c). Missing Listed: Missing signed KWF Disclosures, signed MLS Sheet, Financial Disclosure, Signed Consent for Dual Agency, Netsheet. | BD91: Y | BE91: Y
A92: Dormant | B92: 1802 Merrimac Drive Hyattsville | C92: John | Q92: FALSE | R92: FALSE | S92: FALSE | T92: FALSE | U92: FALSE | V92: FALSE | Y92: 0.0375 | Z92: =Y92-AA92 -> 0.0125 | AA92: 0.025 | AB92: 0 | BC92: No Loop
A93: Dormant | B93: 7877 Burnside Road Hyattsville | C93: John | Q93: FALSE | R93: FALSE | S93: FALSE | T93: FALSE | U93: FALSE | V93: FALSE | Y93: 0.05 | Z93: =Y93-AA93 -> 0.025 | AA93: 0.025 | AB93: 495 | BC93: No MLS. No signed paperworks
A94: Dormant | B94: 599 Lions Gate Odenton | C94: Justin | Q94: FALSE | R94: FALSE | S94: FALSE | T94: FALSE | U94: FALSE | V94: FALSE | Y94: 0.055 | Z94: =Y94-AA94 -> 0.03 | AA94: 0.025 | AB94: 495 | BC94: No Loop
A95: Dormant | B95: 3175 Bero Rd Halethorpe | C95: Justin | Q95: FALSE | R95: FALSE | S95: FALSE | T95: FALSE | U95: FALSE | V95: FALSE | Y95: 0.06 | Z95: =Y95-AA95 -> 0.035 | AA95: 0.025 | AB95: 495 | BC95: Drafted. LA Signed
A96: Dormant | B96: 125 Blackbird Hill Ln, Laurel MD 20724 | C96: Justin | Q96: FALSE | R96: FALSE | S96: FALSE | T96: FALSE | U96: FALSE | V96: FALSE | Y96: 0.06 | Z96: =Y96-AA96 -> 0.035 | AA96: 0.025 | AB96: 495 | BC96: Drafted. No signed paperworks
A97: Dormant | B97: 810 House Dr Upper Marlboro | C97: Justin | Q97: FALSE | R97: FALSE | S97: FALSE | T97: FALSE | U97: FALSE | V97: FALSE | Y97: 0.06 | Z97: =Y97-AA97 -> 0.035 | AA97: 0.025 | AB97: 495 | BC97: Drafted. No signed paperworks
A98: Dormant | B98: 30 Jones Station Rd Severna Park | C98: Justin | Q98: FALSE | R98: FALSE | S98: FALSE | T98: FALSE | U98: FALSE | V98: FALSE | Y98: 0.06 | Z98: =Y98-AA98 -> 0.035 | AA98: 0.025 | AB98: 495 | BC98: No MLS. No signed paperworks
A99: Dormant | B99: 353 Gatewater Ct Unit #A Glen Burnie | C99: Justin | Q99: FALSE | R99: FALSE | S99: FALSE | T99: FALSE | U99: FALSE | V99: FALSE | Y99: 0.06 | Z99: =Y99-AA99 -> 0.035 | AA99: 0.025 | AB99: 495 | BC99: No MLS. No signed paperworks
A100: Dormant | B100: 21 Trailridge Ct Potomac | C100: Justin | Q100: FALSE | R100: FALSE | S100: FALSE | T100: FALSE | U100: FALSE | V100: FALSE | Y100: 0.05 | Z100: =Y100-AA100 -> 0.025 | AA100: 0.025 | AB100: 495 | BC100: No MLS. No signed paperworks
...

Sheet Sheet64
A1: Property | B1: Status | C1: Agent | D1: Active | E1: Photos | F1: HOA Ordered | G1: UC | H1: COE | I1: HI Schedule | J1: HI Contingency | K1: PIN | L1: EMD Received | M1: Repairs Status | N1: Appraisal | O1: Closing Scheduled | P1: Clear to close | Q1: Prelim ALTA | R1: Compliance | S1: Notes
A2: 3730 Greenmount Ave | B2: Purchase | C2: Shaq
A3: 8330 Pulaski Hwy Unit H | B3: Leased | S3: Tentatively we will put it to Flagship first end of February and coming soon end of March.
A4: 9524 Clocktower Lane | B4: Purchase | C4: Evan
A5: 1105 W 40th St | B5: Under Contract | C5: Jen | D5: 44568 | E5: 44566.438 | F5: N/A | I5: 44573.583 | R5: Listed - Submitted 01/06/2022 | S5: Dryer - Exclusion
A6: 502 Hamlen Rd | B6: Under Contract | C6: John | D6: 44897 | E6: 12/1 10:30 (TRU) | F6: N/A | G6: 44536 | H6: 44573 | I6: 44542.438 | J6: 44543 | K6: Completed | L6: 44545 | N6: Completed | O6: Completed | P6: 44199 | Q6: 44201 | R6: Listed Approve - 01/06/2022 -- -- -- -- -- UC Returned - 01/06/22 * Notice to Buyer and Seller - Buyer Name needed in Page 1 | S6: Clear to close Need repair receipts: The furnace flue vent is rusted and deteriorated down to the roof level of the home. Repair/replace as necessary to restore the integrity of the metal chimney as intended. - Pending Replace/repair the soft wood-rotten wood on the left side rear of the home. - Completed Provide documentation for permits requested through the county for the recently completed property renovations. Repair the gas supply line to the furnace so the section of the fuel line running through the chassis of the furnace is appropriately protected against contact damage. - Completed Repair/replace the missing or fallen insulation in the crawl space and make repairs as necessary to restore the insulation between the floor joists. - Completed Remove the excess construction debris and other materials from the crawl space. - Completed
A7: 737 Concord Point | B7: Purchase | C7: Shaq | D7: N/A | E7: N/A | F7: N/A | G7: 44514 | H7: 44575 | I7: N/A | J7: N/A | K7: N/A | L7: Completed | M7: N/A | N7: N/A | R7: Approved
A8: 404 Carl Avenue | B8: Purchase | C8: Paul | D8: N/A | E8: N/A | F8: N/A | G8: 44554 | H8: 44210 | I8: AS IS W/O | J8: As is w/o Inspections | K8: N/A | L8: Completed | M8: N/A | N8: N/A | P8: N/A | R8: Approved
A9: 733 Stinchcomb Road | B9: Purchase | C9: Paul | D9: N/A | E9: N/A | F9: N/A | G9: 44559 | H9: 44220 | I9: N/A | J9: N/A | K9: N/A | L9: Completed | M9: N/A | N9: N/A | P9: N/A | R9: UC - Notice to Buyer and Seller - not in dotloop
A10: 6 Colonial Dr | B10: Under Contract | C10: John | D10: 44528 | E10: 44526 | F10: N/A | G10: 44558 | H10: 44224 | I10: 12/30/2021 12:30 PM 1/4/2022 10AM WDI | J10: 44200 | K10: DONE 1/1/2021 - PIN 1/6/2021 - Seller | L10: 44564 | N10: At Value | R10: Approved | S10: * MD Lead Prevention needing signature * 1/1 - PIN received Pg.2 "Safety Concerns"- have a licensed HVAC professional remedy the possible gas leak located on the furnace. - Completed Pg. 2 "Safety Concerns"- Have a licensed electrician install a proper drip loop on the service entrance cable - To be done week of 1/3
A11: 302 Bethune Dr | B11: Under Contract | C11: Vince | D11: 44480 | E11: N/A | F11: Completed | G11: 44487 | H11: 44587 | I11: N/A | J11: N/A | K11: N/A | L11: 44491 | M11: N/A | N11: N/A | R11: Approved
A12: 301 Bethune Dr | B12: Under Contract | C12: Vince | D12: 44480 | E12: N/A | F12: Completed | G12: 44546 | H12: 44224 | I12: N/A | J12: N/A | K12: N/A | L12: 44567 | M12: N/A | N12: N/A | R12: Listed Approved - 12/30/2021 UC Approved - 12/30/2021
A13: 4654 Mews Dr | B13: Under Contract | C13: Justin | D13: 44553 | E13: 44552 | F13: 44558 | G13: 44558 | H13: 44224 | I13: 44559.667 | J13: 1/4/2021 As is | L13: 44566 | R13: Listed Resubmitted - 01/07/2022 * Net Proceeds - Uploaded * Financial Condition of Property Disclosure - Select 1 option (same since returned) * Smoke Alarm Disclosure and MAR Infographic - requires option (same since returned) -- -- -- -- -- UC Approved - 01/06/2022
A14: 304 Bethune Dr | B14: Under Contract | C14: Vince | D14: 44480 | E14: N/A | F14: Completed | G14: 44544 | H14: 1/31/2022 or Sooner | I14: N/A | J14: N/A | K14: N/A | L14: 44544 | M14: N/A | N14: N/A | R14: Listed Approved - 12/30/2021 -- -- -- -- -- UC Resubmitted - 01/07/2022 * Conventional Addendum
A15: 305 Bethune Dr | B15: Under Contract | C15: Vince | D15: 44480 | E15: N/A | F15: Completed | G15: 44523 | H15: No Guaranteed Closing | I15: N/A | J15: N/A | K15: N/A | L15: 44554 | M15: N/A | N15: N/A | R15: Approved | S15: · Addendum correcting Kathy to Kathleen. · Provide the occupancy cert when the home is complete.
A16: 303 Bethune Dr | B16: Under Contract | C16: Vince | D16: 44480 | E16: N/A | F16: Completed | G16: 44537 | H16: No Guaranteed Closing | I16: N/A | J16: N/A | K16: N/A | L16: 44543 | M16: N/A | N16: N/A | R16: Approved
A17: 319 Top Cottage Ct | B17: Purchase | C17: Shaq | D17: N/A | E17: N/A | F17: N/A | G17: 44536 | H17: No Guaranteed Closing | I17: N/A | J17: N/A | K17: N/A | L17: 44536 | M17: N/A | R17: UC Returned - 12/16/2021 * Exclusive Buyer/Tenant Representation Agreement - Missing * KWF- Communication Consent Addendum - Missing * KWF- RESPA
A18: 263 S Robinson Street | B18: Purchase | C18: Evan | D18: N/A | E18: N/A | F18: N/A | G18: 44553 | H18: 44228 | I18: TBD | J18: TBD | K18: TBD | L18: 44560 | M18: TBD | R18: Approved
A19: 7507 Overlook Ct | B19: Under Contract | C19: John | D19: 44560 | E19: 44561.5 | G19: 44568 | H19: 44603 | I19: 44574.5 | R19: UC - EMD | S19: OFFER - $549,000 VA, No Concession, AS IS w/ 7 days INSP (Regina Pierce) 1/5/22
A20: 19801 Grave Run Road | B20: Under Contract | C20: Vince | D20: 44448 | E20: N/A | F20: N/A | G20: 44566 | H20: 44631 | R20: Listed - Approved
A21: 1410 N Forest Park Ave | B21: CS | C21: Justin | E21: 44568.521 | R21: Listed Submitted - 01/07/2022
A22: 513 Beebe Ct | B22: Active | C22: John | D22: 44558 | E22: 12/29/2021 11AM | R22: Listed Submitted - 12/30/2021 | S22: OFFER - $285k FHA 1/1/22
A23: 11808 Huggins Dr | B23: Active | C23: John | D23: 44536 | E23: 44535 | F23: N/A | R23: Listed Returned - Exclusive Right To Sell - Seller initials requires in Sec 10, 18, 19 and 21. * Financial Condition of Property Disclosure - Need to select option * MLS Full Listing SIGNED by seller - MLS Listing needed. Wrong docs uploaded
A24: 9531 Burton Ave | B24: Active | C24: Jen | D24: 44534 | E24: 44532.615 | F24: N/A | R24: UC - Resubmitted 01/05/2022
A25: 800 Slacum St | B25: Active | C25: Romont | D25: 44523 | E25: 44520.542 | F25: N/A | R25: Listed - Approved 11/29/2021
A26: 3012 Rices Ln | B26: Active | C26: Justin | D26: 44414 | E26: N/A | F26: N/A | R26: UC Approved - 09/28/2021
A27: 1116 & 1120 Dicus Mill Rd | B27: Active | C27: Justin | D27: 44013 | E27: N/A | F27: N/A
A28: (Farm) 1132 Dicus Mill Rd | B28: Active | C28: Justin | D28: 44013 | E28: N/A | F28: N/A
A29: (Res) 1132 Dicus Mill Rd | B29: Active | C29: Justin | D29: 44013 | E29: N/A | F29: N/A
A30: 5659 Selford Rd | B30: Upcoming | C30: Shaq | S30: 12/26: Seller have covid19
A31: 8028 Maywood Ave | B31: Upcoming | C31: Vince
A32: 2129 Sunnythorn Rd | B32: Upcoming | C32: Jen
A33: 2128 Fountain Hill Dr | B33: Upcoming | C33: Vince
A34: 108 S 3rd St | B34: Upcoming | C34: Romont
A35: 4805 Frazier Neck Rd | B35: Upcoming | C35: Romont
A36: 3033 Lundt Ct | B36: Upcoming | C36: Justin
A37: 990 Dalton Ave | B37: Upcoming | C37: Shaq
A38: 3900 Chesterwood Dr | B38: Upcoming | C38: Vince
A39: 15907 Perkins Ln | B39: Upcoming | C39: John
A40: 3533 Falling Run Rd | B40: Upcoming | C40: Shaq | S40: Some point they will sell this year
A41: 2914 Tarragon Lane | B41: Upcoming | C41: Jen
A42: 1006 Shreve Ct | B42: Upcoming | C42: Justin
A43: 1032 Middlesex Rd | B43: Upcoming | C43: Justin
A44: 529 Grovethorn Rd | B44: Upcoming | C44: Justin
A45: 14502 Golden Eagle Ct | B45: Withdrawn | C45: Shenel
A54: 327 George Ave | B54: Closed | C54: Evan | D54: Off Market Sale | E54: N/A | F54: N/A | G54: 44536 | H54: 44199 | I54: N/A | J54: As Is w/o Inspections | K54: N/A | L54: 44545 | M54: N/A | N54: N/A | O54: 12/29/21 7PM - Seller 1/3/2021 8:30 AM - Buyer | P54: YES | Q54: 44559 | R54: Approved | S54: Need second Loan info from seller
A55: 2104 Goodwood Rd | B55: Closed | C55: John | D55: 44511 | E55: 44511.354 | F55: Completd | G55: 44537 | H55: 44567 | I55: 44539.531 | J55: 12/21/2021 As Is | K55: Completed | L55: 44544 | M55: Completed | N55: N/A | O55: Completed | P55: Completed | Q55: Received | R55: Approved | S55: Need repair receipts

Sheet Sheet65
A1: Property | B1: 2922 Sylvan | C1: 4654 Mews Dr | D1: 9524 Clocktower Lane | E1: 301 Bethune Dr | F1: 303 Bethune Dr | G1: 304 Bethune Dr | H1: 302 Bethune Dr | I1: 305 Bethune Dr | J1: 19801 Grave Run Road | K1: 719 Hamlen Rd Glen Burnie | L1: 1105 W 40Th St Baltimore, MD 21211 | M1: 7507 Overlook Ct | N1: 6 Disney Ave | O1: 2810 Belair Dr | P1: 2129 Sunnythorn Rd | Q1: 513 Beebe Ct | R1: 1410 N Forest Park Ave | S1: 7844 Citadel Dr | T1: 319 Top Cottage Ct | U1: 3730 Greenmount Ave | V1: * | W1: 108 S 3rd St | X1: 3900 Chesterwood Dr | Y1: 505 Arbor Court, Edgewood, MD 21040 | Z1: 505 Wheatley | AA1: 504 Wheatley | AB1: 503 Wheatley | AC1: 502 Wheatley | AD1: 501 Wheatley | AE1: 301 Cheddington Rd | AF1: 11808 Huggins Dr | AG1: 9531 Burton Ave | AH1: 800 Slacum St | AI1: 3012 Rices Ln | AJ1: * | AK1: 321 Magothy Blvd | AL1: 2801 Deepwater Trl | AM1: 12912 Churchill Ridge Cir Unit 5-B, Germantown, MD 20874 | AN1: 440 Century Vista Dr | AO1: 3219 Elliott St, Baltimore, MD 21224 | AP1: 26 Steeplejack Ct. Owings Mills, MD 21117 | AQ1: 5821 Farmview AVe | AR1: 1320 Highland Drive | AS1: 15415 Reprise Terr Rockville | AT1: 814 Glacier Ave | AU1: 11715 Kingtree St | AV1: 1910 Everglade Ct, Crofton, MD 21114 | AW1: 5005 Leroy Graham Dr, Capitol Heights, MD 20743 | AX1: 5659 Selford Rd | AY1: 8028 Maywood Ave | AZ1: 2128 Fountain Hill Dr | BA1: 4805 Frazier Neck Rd | BB1: 3033 Lundt Ct | BC1: 15907 Perkins Ln | BD1: 3533 Falling Run Rd | BE1: 2914 Tarragon Lane | BF1: 1006 Shreve Ct | BG1: 1032 Middlesex Rd | BH1: 529 Grovethorn Rd | BI1: * | BJ1: 263 S Robinson Street | BK1: 737 Concord Point Dr, Perryville, MD 21903 | BL1: 6 Colonial Dr | BM1: 7134 Gough St | BN1: 733 Stinchcomb Road | BO1: 404 Carl Avenue | BP1: 502 Hamlen Rd | BQ1: 8330 Pulaski Hwy Unit H | BR1: 327 George Ave | BS1: 2104 Goodwood Rd | BT1: 990 Dalton Ave | BU1: (Farm) 1132 Dicus Mill Rd | BV1: 1116 & 1120 Dicus Mill Rd | BW1: (Res) 1132 Dicus Mill Rd
A2: Status | B2: Purchase | C2: Under Contract | D2: Purchase | E2: Under Contract | F2: Under Contract | G2: Under Contract | H2: Under Contract | I2: Under Contract | J2: Under Contract | K2: Under Contract | L2: Under Contract | M2: Under Contract | N2: Under Contract | O2: Under Contract | P2: Under Contract | Q2: Under Contract | R2: Under Contract | S2: Under Contract | T2: Purchase | U2: Purchase | V2: * | W2: Coming Soon | X2: Coming Soon | Y2: Coming Soon | Z2: Coming Soon | AA2: Coming Soon | AB2: Coming Soon | AC2: Coming Soon | AD2: Coming Soon | AE2: Active | AF2: Active | AG2: Active | AH2: Active | AI2: Active | AJ2: * | AK2: Signed LA | AL2: Signed LA | AM2: Signed LA | AN2: Signed LA | AO2: Signed LA | AP2: Upcoming | AQ2: Upcoming | AR2: Lease | AS2: Upcoming | AT2: Upcoming | AU2: Upcoming | AV2: Upcoming | AW2: Upcoming | AX2: Upcoming | AY2: Upcoming | AZ2: Upcoming | BA2: Upcoming | BB2: Upcoming | BC2: Upcoming | BD2: Upcoming | BE2: Upcoming | BF2: Upcoming | BG2: Upcoming | BH2: Upcoming | BI2: * | BJ2: Closed | BK2: Closed | BL2: Closed | BM2: Closed | BN2: Closed | BO2: Closed | BP2: Closed | BQ2: Closed | BR2: Closed | BS2: Closed | BT2: Withdrawn | BU2: Withdrawn | BV2: Withdrawn | BW2: Withdrawn | BX2: AS of January 31, 2022
A3: Agent | B3: Shaq | C3: Justin | D3: Evan | E3: Vince | F3: Vince | G3: Vince | H3: Vince | I3: Vince | J3: Vince | K3: John | L3: Jen | M3: John | N3: Vince | O3: John | P3: Jen | Q3: John | R3: Justin | S3: John | T3: Shaq | U3: Shaq | V3: * | W3: Romont | X3: Vince | Y3: Shaq | Z3: Vince | AA3: Vince | AB3: Vince | AC3: Vince | AD3: Vince | AE3: John | AF3: John | AG3: Jen | AH3: Romont | AI3: Justin | AJ3: * | AK3: Cole | AL3: Justin | AM3: Justin | AN3: John | AO3: Jen | AP3: Brandt | AQ3: Jen | AR3: Jen | AS3: John | AT3: John | AU3: John | AV3: Shenel | AW3: Shaq | AX3: Shaq | AY3: Vince | AZ3: Vince | BA3: Romont | BB3: Justin | BC3: John | BD3: Shaq | BE3: Jen | BF3: Justin | BG3: Justin | BH3: Justin | BI3: * | BJ3: Evan | BK3: Shaq | BL3: John | BM3: Shaq | BN3: Paul | BO3: Paul | BP3: John | BQ3: Shaq | BR3: Evan | BS3: John | BT3: Shaq | BU3: Justin | BV3: Justin | BW3: Justin | BX3: Closed | BY3: 10
A4: Active Date | C4: 44553 | D4: N/A | E4: 44480 | F4: 44480 | G4: 44480 | H4: 44480 | I4: 44480 | J4: 44448 | K4: 44575 | L4: 44568 | M4: 44560 | N4: 44589 | O4: 44581 | Q4: 44558 | R4: 44576 | S4: 44585 | T4: N/A | U4: N/A | V4: * | W4: 44595 | X4: 44601 | Y4: 44595 | Z4: 44591 | AA4: 44591 | AB4: 44591 | AC4: 44591 | AD4: 44591 | AE4: 44589 | AF4: 44536 | AG4: 44534 | AH4: 44534 | AI4: 44414 | AJ4: * | AN4: 44595 | BI4: * | BJ4: N/A | BK4: N/A | BL4: 44528 | BM4: N/A | BN4: N/A | BO4: N/A | BP4: 44897 | BQ4: NA | BR4: Off Market Sale | BS4: 44511 | BU4: 44013 | BV4: 44013 | BW4: 44013 | BX4: Target | BY4: 300
A5: List Price | C5: 254500 | D5: N/A | E5: 298900 | F5: 298900 | G5: 279900 | H5: 279900 | I5: 298900 | J5: 499900 | K5: 320000 | L5: 159999 | M5: 549000 | N5: 260000 | O5: 505000 | P5: Off Market | Q5: 279900 | R5: 212000 | S5: 435000 | T5: N/A | U5: N/A | V5: * | W5: 43000 | X5: 289900 | Y5: 240000 | Z5: 298900 | AA5: 279900 | AB5: 279900 | AC5: 279900 | AD5: 298900 | AE5: 399900 | AF5: 549000 | AG5: 294999 | AH5: 160000 | AI5: 500000 | AJ5: * | AN5: 549900 | AR5: 2300 | BI5: * | BJ5: N/A | BK5: N/A | BL5: 379900 | BM5: N/A | BN5: N/A | BO5: N/A | BR5: NA | BY5: 0.0003
A6: Listing Signed Date | C6: 44475 | D6: N/A | E6: 44440 | F6: 44440 | G6: 44440 | H6: 44440 | I6: 44440 | J6: 44399 | K6: 44574 | L6: 44476 | M6: 44468 | N6: 44585 | O6: 44580 | Q6: 44560 | R6: 44550 | S6: 44580 | T6: N/A | U6: N/A | V6: * | W6: 44589 | Y6: 44211 | Z6: 44575 | AA6: 44575 | AB6: 44575 | AC6: 44575 | AD6: 44575 | AE6: 44587 | AF6: 44560 | AG6: 44496 | AH6: 44516 | AJ6: * | AN6: 44592 | BI6: * | BJ6: N/A | BK6: N/A | BL6: 44529 | BM6: N/A | BN6: N/A | BO6: N/A | BR6: NA
A7: Photos | C7: 44552 | D7: N/A | E7: N/A | F7: N/A | G7: N/A | H7: N/A | I7: N/A | J7: N/A | K7: 44576.438 | L7: 44566.438 | M7: 44561.5 | N7: 44589 | O7: 44581.604 | P7: NA | Q7: 12/29/2021 11AM | R7: 44568.521 | S7: 44588 | T7: N/A | U7: N/A | V7: qs | W7: NA | X7: 44596.5 | Y7: 44223 | Z7: N/A | AA7: N/A | AB7: N/A | AC7: N/A | AD7: N/A | AE7: 44226 | AF7: 44535 | AG7: 44532.615 | AH7: 44520.542 | AI7: N/A | AJ7: * | AN7: 2/3/2022 Afternoon | AT7: 44596.562 | BI7: * | BJ7: N/A | BK7: N/A | BL7: 44526 | BM7: 44526 | BN7: N/A | BO7: N/A | BP7: 12/1 10:30 (TRU) | BR7: N/A | BS7: 44511.354 | BU7: N/A | BV7: N/A | BW7: N/A
A8: HOA Ordered | B8: None | C8: 44558 | D8: 44579 | G8: Ordered | J8: N/A | K8: N/A | L8: N/A | M8: 1/26/2022 Completed | O8: N/A | P8: NA | T8: N/A | V8: * | W8: NA | AF8: N/A | AG8: N/A | AH8: N/A | AI8: N/A | AJ8: * | BI8: * | BJ8: N/A | BK8: N/A | BL8: N/A | BM8: N/A | BN8: N/A | BO8: N/A | BP8: N/A | BR8: N/A | BS8: Completd | BU8: N/A | BV8: N/A | BW8: N/A
A9: Closing Date | C9: 44596 | D9: 44596 | E9: 44596 | F9: 44596 | G9: 44596 | H9: 44596 | I9: 44596 | J9: 44602 | K9: 44603 | L9: 44603 | M9: 44603 | N9: 44603 | O9: 44615 | P9: 44616 | Q9: 44617 | R9: 44617 | S9: 44620 | T9: No Guaranteed Closing | U9: 44653 | V9: * | AJ9: * | BI9: * | BJ9: 44224 | BK9: 44589 | BL9: 44224 | BM9: 44582 | BN9: 44220 | BO9: 44210 | BP9: 44573 | BQ9: 44207 | BR9: 44199 | BS9: 44567
A10: Ratified Date | B10: 44592 | C10: 44558 | D10: 44207 | E10: 44546 | F10: 44537 | G10: 44544 | H10: 44487 | I10: 44523 | J10: 44566 | K10: 44578 | L10: 44571 | M10: 44568 | N10: 44589 | O10: 44587 | P10: 44586 | R10: 44585 | S10: 44589 | T10: 44536 | U10: 44207 | V10: * | AJ10: * | BI10: * | BJ10: 44553 | BK10: 44524 | BL10: 44558 | BM10: 44575 | BN10: 44559 | BO10: 44554 | BP10: 44536 | BQ10: 44206 | BR10: 44536 | BS10: 44537
A11: Purchase Price | C11: 265000 | D11: 405500 | E11: 298900 | F11: 289900 | G11: 286300 | H11: 279000 | I11: 298900 | J11: 469900 | K11: 320000 | L11: 162000 | M11: 560000 | N11: 263500 | O11: 525000 | P11: 155000 | R11: 227300 | S11: 450000 | T11: 379685 | U11: 370000 | V11: * | AJ11: * | BI11: * | BJ11: 417500 | BK11: 405000 | BL11: 402000 | BM11: 145000 | BN11: 332000 | BQ11: N/A
A12: EMD Received | C12: 44566 | E12: 44567 | F12: 44543 | G12: 44544 | H12: 44491 | I12: 44554 | J12: 44566 | K12: 44578 | L12: 44580 | M12: 44573 | N12: 44589 | Q12: 44592 | R12: 44587 | S12: 44589 | T12: 44536 | V12: * | AJ12: * | BI12: * | BJ12: 44560 | BK12: Completed | BL12: 44564 | BM12: Completed | BN12: Completed | BO12: Completed | BP12: 44545 | BQ12: N/A | BR12: 44545 | BS12: 44544
A13: TItle Documents | B13: 2/1/22 Qualia | C13: Completed - Qualia | G13: Completed | J13: 44580 | P13: 1/26/2022 1/27 - Title to Seller | R13: 2/1/22 Qualia | V13: * | AJ13: * | BI13: * | BJ13: 1/21/22 Qualia | BK13: Completed | BL13: Completed | BM13: N/A | BN13: Completed | BO13: Completed | BP13: Completed | BQ13: N/A | BR13: Completed | BS13: Completed
A14: HI Schedule | B14: 2/3/2022 10-1PM | C14: 44559.667 | E14: N/A | F14: N/A | G14: N/A | H14: N/A | I14: N/A | K14: 1/21/22 For info only | L14: 44573.583 | M14: 44574.5 | N14: NA | O14: HI - 1/29 10AM Chimney - 2/1 9AM | Q14: 44594.375 | R14: 44588.375 | S14: 44590.542 | T14: N/A | V14: * | AJ14: * | BI14: * | BJ14: 44585.5 | BK14: N/A | BL14: 12/30/2021 12:30 PM 1/4/2022 10AM WDI | BM14: N/A | BN14: N/A | BO14: AS IS W/O | BP14: 44542.438 | BQ14: N/A | BR14: N/A | BS14: 44539.531
A15: HI Contingency | C15: 1/4/2021 As is | E15: N/A | F15: N/A | G15: N/A | H15: N/A | I15: N/A | K15: 44588 | L15: 44576 | M15: 44575 | N15: NA | O15: 44597 | R15: 44592 | T15: N/A | V15: * | AJ15: * | BI15: * | BJ15: TBD | BK15: N/A | BL15: 44200 | BM15: N/A | BN15: N/A | BO15: As is w/o Inspections | BP15: 44543 | BQ15: N/A | BR15: As Is w/o Inspections | BS15: 12/21/2021 As Is
A16: PIN | C16: 1/4/2021 As is | E16: N/A | F16: N/A | G16: N/A | H16: N/A | I16: N/A | K16: 1/24 Repairs completed. No req repairs | L16: None. Pass deadline | M16: 44578 | N16: NA | O16: 1/28 - Received PIN | T16: N/A | V16: * | AJ16: * | BI16: * | BJ16: TBD | BK16: N/A | BL16: DONE 1/1/2021 - PIN 1/6/2021 - Seller | BM16: N/A | BN16: N/A | BO16: N/A | BP16: Completed | BQ16: N/A | BR16: N/A | BS16: Completed
A17: Repairs Status | C17: 1/4/2021 As is | E17: N/A | F17: N/A | G17: N/A | H17: N/A | I17: N/A | K17: No repairs requested | L17: None. Pass deadline | M17: 1/24 Completed | N17: NA | T17: N/A | V17: * | AJ17: * | BI17: * | BJ17: TBD | BK17: N/A | BL17: 1/13 - Completed 1/13 - Receipts sent to BA | BM17: N/A | BN17: N/A | BO17: N/A | BP17: Completed | BQ17: N/A | BR17: N/A | BS17: Completed
A18: Appraisal Schedule | C18: 44567 | G18: Completed | K18: None | L18: 44582 | M18: 44593.542 | N18: NA | Q18: 44222 | S18: 44594.375 | V18: * | AJ18: * | BI18: * | BJ18: Completed | BK18: N/A | BL18: Completed | BM18: N/A | BN18: N/A | BO18: N/A | BP18: Completed | BQ18: N/A | BR18: Approved | BS18: Approved
A19: Appraisal | C19: Completed | E19: N/A | F19: N/A | G19: N/A | H19: N/A | I19: N/A | K19: None | V19: * | AJ19: * | BI19: * | BJ19: Completed | BK19: N/A | BL19: At Value | BM19: N/A | BN19: N/A | BO19: N/A | BP19: Completed | BQ19: N/A | BR19: N/A | BS19: N/A
A20: Closing Scheduled | C20: 1/27/2022 9AM - Seller | D20: 2/4/2022 1:30PM Canton Office 2/4 12:15 - Final Walkthrough | F20: 1/31/2022: Buyer | G20: 1/31/2022 1 PM 210 Island Plaza Court Stevensville, MD 21666 | H20: 2/4/2022: Buyer (Time-TBD) | K20: 44587 | M20: 1/27 8:30AM - Final Walkthru | V20: * | AJ20: * | BI20: * | BJ20: 12/28 12-1PM | BK20: 1/28/2022 11AM - Buyer Presigned - Seller | BL20: Buyer: 2PM 1/28 | BM20: Completed | BN20: Notary | BO20: Completed | BP20: Completed | BQ20: N/A | BR20: 12/29/21 7PM - Seller 1/3/2021 8:30 AM - Buyer | BS20: Completed
A21: Clear to close | D21: Completed | V21: * | AJ21: * | BI21: * | BJ21: Completed | BK21: Completed | BL21: 44582 | BM21: Completed | BN21: N/A | BO21: N/A | BP21: 44199 | BQ21: N/A | BR21: YES | BS21: Completed
A22: Prelim ALTA | L22: 44587 | V22: * | AJ22: * | BI22: * | BJ22: 44588 | BK22: 44587 | BL22: 44581 | BM22: Completed | BN22: Completed | BO22: Completed | BP22: 44201 | BQ22: N/A | BR22: 44559 | BS22: Received
A23: Compliance | C23: Listed Returned - 01/11/2022 * Financial Condition of Property Disclosure - Select 1 option (same since returned) Last checked: 01/14/2022 -- -- -- -- -- UC Approved - 01/06/2022 | D23: Approved | E23: Approved | F23: Approved | G23: Approved | H23: Approved | I23: Approved | J23: Approved | K23: Approved | L23: Listed Approved - 01/11/2022 Last checked: -1/14/2022 -- -- -- -- UC Resubmitted - 01/19/2022 EMD - Uploaded Last checked: 01/19/2022 | M23: Approved | N23: Listed Submitted - 01/26/2022 | O23: Listed Approved - 01/24/2022 Last checked - 01/26/2022 -- -- -- -- -- -- UC Submitted - 01/27/2022 * EMD - missing Last checked - 01/27/2022 | P23: Listed returned - 01/26/2022 (NOTE: Off-Market Sale. MLS Sheet Active is not available) * Financial Condition of Property Disclosure - held by needed. Last checked - 01/27/2022 -- -- -- -- -- -- UC returned - 01/26/2022 (NOTE: Buyer is Unrepresented. This is a Hard Money deal.) * EMD - Missing Last checked - 01/27/2022 | Q23: Listed resubmitted - 01/14/2022 * County Specific Notices Addendum - Uploaded Fred County Last checked - 01/14/2022 | R23: Listed Returned - 01/10/2022 * Net Sheet - In Dotloop but required seller signature * MLS Full Listing SIGNED by seller - Missing Last checked - 01/14/2022 | S23: Listed Approved - 01/25/2022 Last checked - 01/26/2022 | T23: UC Resubmitted - 01/21/2022 * Uploaded Required docs * Notice to Buyer and Seller of Rights & Obligations - Missing * Maryland Residential Property Disclosure and Disclaimer - Missing * Pre-Approval Letter/Proof of Funds - Missing * MLS Full Listing Synopsis - Missing Last checked - 01/21/2022 | U23: UC Submited - 01/26/2022 * EMD - missing * Notice to Buyer and Seller of Rights & Obligations - missing * Pre-Approval Letter/Proof of Funds - missing * MLS Full Listing Synopsis - missing * Tax Records - missing * Buyer's Pre-settlement Walk-through Report - missing | V23: * | Y23: Listed Submitted - 01/19/2022 * MLS Full Listing Latest checked - 01/19/2022 | Z23: Listed Submitted - 01/19/2022 * MLS Full Listing SIGNED by seller - Missing * MLS Tax Record - Missing Last checked - 01/19/2022 | AA23: Listed Submitted - 01/19/2022 * MLS Full Listing SIGNED by seller - Missing * MLS Tax Record - Missing Last checked - 01/19/2022 | AB23: Listed Submitted - 01/19/2022 * MLS Full Listing SIGNED by seller - Missing * MLS Tax Record - Missing Last checked - 01/19/2022 | AC23: Listed Submitted - 01/19/2022 * MLS Full Listing SIGNED by seller - Missing * MLS Tax Record - Missing Last checked - 01/19/2022 | AD23: Listed Resubmitted - 01/19/2022 * County Specific Notices Addendum/Jurisdictional Addendum - Uploaded 01/19/2022 * MLS Full Listing SIGNED by seller - Missing * MLS Tax Record - Missing Last checked - 01/19/2022 | AF23: Listed Resubmitted - 01/14/2022 * Exclusive Right To Sell - Seller initials requires in Sec 10, 18, 19 and 21. * Financial Condition of Property Disclosure - Reuploaded * MLS Full Listing SIGNED by seller - MLS Listing needed. Last checked: 01/14/2022 | AG23: UC Approved - 01/06/2022 Last checked: 01/14/2022 | AH23: Listed - Approved 11/29/2021 | AI23: UC Approved - 09/28/2021 | AJ23: * | BI23: * | BJ23: Approved | BK23: Approved | BL23: Approved | BM23: UC Submitted - 01/19/2022 | BN23: UC - Notice to Buyer and Seller - not in dotloop (REO) last check: 01/14/2022 | BO23: Approved | BP23: Listed Approve - 01/06/2022 -- -- -- -- -- UC Returned - 01/06/22 * Notice to Buyer and Seller - Buyer Name needed in Page 1 | BQ23: Approved | BR23: Approved | BS23: Approved
A24: Notes | C24: Issues with appraisal | D24: 1/12 - Title docs sent by Mallori | F24: Appraisal Contingency moved from 1/13 - 1/19. Issues with appraisal | G24: 1/11 - HOA ordered | I24: · Addendum correcting Kathy to Kathleen. · Provide the occupancy cert when the home is complete. | J24: 1/12 - No appraisal order date yet Will attend closing | K24: $320,000 (Confirm with John) cleaning on friday landscaping by Friday Saturday - Photos. Afternoon. Ground Rent - Paid in Full | L24: Dryer - Exclusion Seller Affidavit - Completed 1/12 | M24: OFFER - $549,000 VA, No Concession, AS IS w/ 7 days INSP (Regina Pierce) 1/5/22 Waiting on HOA and how to order Resale Packet | O24: 3/2 Up half bath on main Gas - HW Collint - Type Electric No cool fuel force central and gas AC - Electric Back up generator, Generac Back up generator New roof, new siding, new kitshcen ss appliances, ceramic tile bathrooms, freshly painted, singele car garage, fenced in yard with shed (1), fireplace (1), an entry room addition, recessed lights throught, large master with walk in closet. Quartz counter top, Conveniently major shopping centers and transportation hubs, Cassidy within 10 miles radius. | P24: Jen's SOI Unrepresented Buyer, no admin fee on Buyer, no commission os Shaq Total commission is 3%. All wil go to Jen Proof of name change - Need divorce decree and marital settlement agreement | Q24: Acquisition: 11/30/2021 OFFER - $285k FHA 1/1/22 OFFER - $258K Conv 1/15/22 OFFER - $275 Conv 1/19/22 | V24: * | X24: No seller phone numbers | Y24: Wants to go live first week of Feb or earlier No admin fee Photo Schedule - 1/27/2022 at 1pm 0522 - Combo for photographer Sentrilock - Shaq to install | Z24: 501 & 505 are 298,900 - 502,503,504, are 279,900! | AA24: 501 & 505 are 298,900 - 502,503,504, are 279,900! | AB24: 501 & 505 are 298,900 - 502,503,504, are 279,900! | AC24: 501 & 505 are 298,900 - 502,503,504, are 279,900! | AD24: 501 & 505 are 298,900 - 502,503,504, are 279,900! | AE24: Acquisition Date - 12/14/2021 | AF24: 1/18: Temp to off market to active $549 Acquisition: 9/20/2021 W/D - No Washer solar panel shed exterior New roof Solar panels to be installed 1/24 | AJ24: * | AK24: Photos on April Active on May Tenant Occupied | AL24: Expected Coming soon 3/3/22 and active 3/17/21 | AO24: Currently tenant occupied with lease ending 4/30/22. More details regarding photo date, coming soon and listing date after we narrow down a walk through time with the seller's property management company. They are also looking for another investment property as well Will be signing hard copies | AQ24: I created a dotloop and haven't sent any paperwork except for the prelisting paperwork so far. I think I did it backwards - I loaded to prelisting into dotloop and sent it to him that way. For now, he would just like to start with Flagship First only and potentially transition into MLS if we are getting strong feedback. There is no lockbox because it will be appointment only - any agent will need to contact me to schedule a showing. I've attached a picture and have a few more of the inside of the house. He's open to Jeff coming for pictures, but isn't in a huge rush. The house is very well maintained and will be easy to photograph. 1 photo | AR24: https://www.zillow.com/homedetails/1320-Highland-Dr-Baltimore-MD-21239/36406160_zpid/ we store some things in the shed under the porch, so that will be off limits to the tenant. $2,300 Leased 50% of rental pay 12-18 Months Rental Needs to have the home cleaned for us to come in to take pics. | AS24: Rehabbed two years ago | AT24: Cap heights 2/1 up 2/1 down New everything Full permits | AV24: Listed by another brokerage | AW24: Sellers divorcing | AX24: 12/26: Seller have covid19 | BD24: Some point they will sell this year | BI24: * | BK24: The seller is going to want a remote closing on this transaction the cost can be covered from my commission. **Buyer*** They're military live on APG 11/30 Appraisal result is good. Came up higher than value | BM24: Has Ground rent | BN24: Completed | BP24: Completed | BQ24: Tentatively we will put it to Flagship first end of February and coming soon end of March. | BR24: Need second Loan info from seller | BS24: Need repair receipts
A25: Repairs | K25: 1/24 - Repairs completed. No requested repairs | M25: 1. Make windows operational to be able to open in all rooms. Windows were painted shut and can't be opened. 2. Place missing screens back on the exterior of the windows and any that are on the interior of the window place them on the outside. 3. Seller will seal crack and fix water issue in the basement. 4. Make hot water heater operational so hot water can be tested prior to settlement. Hot water heater and/or gas at hot water heater was not on during inspection to be tested. | V25: * | AJ25: * | BI25: * | BL25: Pg.2 "Safety Concerns"- have a licensed HVAC professional remedy the possible gas leak located on the furnace. - Completed Pg. 2 "Safety Concerns"- Have a licensed electrician install a proper drip loop on the service entrance cable - To be done week of 1/3
V26: * | AJ26: * | BI26: *

Sheet Sheet66
A1: Property | B1: Status | C1: Agent | D1: Active Date | E1: List Price | F1: Listing Signed Date | G1: Photos | H1: Flagship | I1: HOA Ordered | J1: Closing Date | K1: Ratified Date | L1: Purchase Price | M1: EMD Received | N1: TItle Documents | O1: HI Schedule | P1: HI Contingency | Q1: PIN | R1: Repairs Status | S1: Appraisal Schedule | T1: Appraisal | U1: Closing Scheduled | V1: Clear to close | W1: Prelim ALTA | X1: Compliance | Y1: Notes | Z1: Repairs
A2: 219 South Clinton Street | B2: Purchase | C2: Evan
A3: 505 Arbor Court, Edgewood, MD 21040 | B3: Under Contract | C3: Shaq | D3: 44595 | E3: 240000 | F3: 44211 | G3: 44223 | X3: Listed Submitted - 01/19/2022 * MLS Full Listing Latest checked - 01/19/2022 | Y3: Wants to go live first week of Feb or earlier No admin fee Photo Schedule - 1/27/2022 at 1pm 0522 - Combo for photographer Sentrilock - Shaq to install
A4: 440 Century Vista Dr | B4: Under Contract | C4: John | D4: 44596 | E4: 549900 | F4: 44592 | G4: 2/3/2022 Afternoon | X4: Listed Submitted - 02/04/2022
A5: 4654 Mews Dr | B5: Under Contract | C5: Justin | D5: 44553 | E5: 254500 | F5: 44475 | G5: 44552 | I5: 44558 | J5: 44602 | K5: 44558 | L5: 265000 | M5: 44566 | N5: Completed - Qualia | O5: 44559.667 | P5: 1/4/2021 As is | Q5: 1/4/2021 As is | R5: 1/4/2021 As is | S5: 44567 | T5: Completed | U5: 1/27/2022 9AM - Seller | X5: Fully Approved | Y5: Issues with appraisal
A6: 19801 Grave Run Road | B6: Under Contract | C6: Vince | D6: 44448 | E6: 499900 | F6: 44399 | G6: N/A | I6: N/A | J6: 44602 | K6: 44566 | L6: 469900 | M6: 44566 | N6: 44580 | O6: Completed | P6: Completed | Q6: Completed | R6: Completed | U6: 2/10 at 1pm here in our Westminster office - 531 Old Westminster PIke, Suite 209 | X6: Fully Approved | Y6: 1/12 - No appraisal order date yet Will attend closing
A7: 719 Hamlen Rd Glen Burnie | B7: Under Contract | C7: John | D7: 44575 | E7: 320000 | F7: 44574 | G7: 44576.438 | I7: N/A | J7: 44603 | K7: 44578 | L7: 320000 | M7: 44578 | O7: 1/21/22 For info only | P7: 44588 | Q7: 1/24 Repairs completed. No req repairs | R7: No repairs requested | S7: None | T7: None | U7: 44587 | X7: Fully Approved | Y7: $320,000 (Confirm with John) cleaning on friday landscaping by Friday Saturday - Photos. Afternoon. Ground Rent - Paid in Full | Z7: 1/24 - Repairs completed. No requested repairs
A8: 1105 W 40Th St Baltimore, MD 21211 | B8: Under Contract | C8: Jen | D8: 44568 | E8: 159999 | F8: 44476 | G8: 44566.438 | I8: N/A | J8: 44603 | K8: 44571 | L8: 162000 | M8: 44580 | O8: 44573.583 | P8: 44576 | Q8: None. Pass deadline | R8: None. Pass deadline | S8: 44582 | W8: 44587 | X8: Fully Approved | Y8: Dryer - Exclusion Seller Affidavit - Completed 1/12
A9: 6 Disney Ave | B9: Under Contract | C9: Vince | D9: 44589 | E9: 260000 | F9: 44585 | G9: 44589 | J9: 44603 | K9: 44589 | L9: 263500 | M9: 44589 | O9: NA | P9: NA | Q9: NA | R9: NA | S9: NA | X9: Listed Approved - 01/30/2022 -- -- -- -- -- UC Returned - 02/01/2022 * Contract of Sale - Buyer signature s/b managing member and not LLC name * Notice to Buyer and Seller - Buyer signature s/b managing member and not LLC name * Residential Property Disclosure - Buyer signature s/b managing member and not LLC name * County Specific Notices Addendum - Buyer signature s/b managing member and not LLC name Last checked: 02/04/2022
A10: 301 Bethune Dr | B10: Under Contract | C10: Vince | D10: 44480 | E10: 298900 | F10: 44440 | G10: N/A | J10: 44603 | K10: 44546 | L10: 298900 | M10: 44567 | O10: N/A | P10: N/A | Q10: N/A | R10: N/A | T10: N/A | X10: Fully Approved
A11: 303 Bethune Dr | B11: Under Contract | C11: Vince | D11: 44480 | E11: 298900 | F11: 44440 | G11: N/A | J11: 44603 | K11: 44537 | L11: 289900 | M11: 44543 | O11: N/A | P11: N/A | Q11: N/A | R11: N/A | T11: N/A | U11: 1/31/2022: Buyer | X11: Fully Approved | Y11: Appraisal Contingency moved from 1/13 - 1/19. Issues with appraisal
A12: 304 Bethune Dr | B12: Under Contract | C12: Vince | D12: 44480 | E12: 279900 | F12: 44440 | G12: N/A | I12: 44594 | J12: 44603 | K12: 44544 | L12: 286300 | M12: 44544 | N12: Completed | O12: N/A | P12: N/A | Q12: N/A | R12: N/A | S12: Completed | T12: N/A | U12: 1/31/2022 1 PM 210 Island Plaza Court Stevensville, MD 21666 | X12: Fully Approved | Y12: 1/11 - HOA ordered
A13: 302 Bethune Dr | B13: Under Contract | C13: Vince | D13: 44480 | E13: 279900 | F13: 44440 | G13: N/A | J13: 44603 | K13: 44487 | L13: 279000 | M13: 44491 | O13: N/A | P13: N/A | Q13: N/A | R13: N/A | T13: N/A | U13: 2/4/2022: Buyer (Time-TBD) | X13: Fully Approved
A14: 305 Bethune Dr | B14: Under Contract | C14: Vince | D14: 44480 | E14: 298900 | F14: 44440 | G14: N/A | J14: 44606 | K14: 44523 | L14: 298900 | M14: 44554 | O14: N/A | P14: N/A | Q14: N/A | R14: N/A | T14: N/A | X14: Fully Approved | Y14: · Addendum correcting Kathy to Kathleen. · Provide the occupancy cert when the home is complete.
A15: 7507 Overlook Ct | B15: Under Contract | C15: John | D15: 44560 | E15: 549000 | F15: 44468 | G15: 44561.5 | I15: 1/26/2022 Completed | J15: 44606 | K15: 44568 | L15: 560000 | M15: 44573 | O15: 44574.5 | P15: 44575 | Q15: 44578 | R15: 1/24 Completed | S15: 44593.542 | T15: 2/7 At value | U15: 1/27 8:30AM - Final Walkthru | X15: Fully Approved | Y15: OFFER - $549,000 VA, No Concession, AS IS w/ 7 days INSP (Regina Pierce) 1/5/22 Waiting on HOA and how to order Resale Packet | Z15: 1. Make windows operational to be able to open in all rooms. Windows were painted shut and can't be opened. 2. Place missing screens back on the exterior of the windows and any that are on the interior of the window place them on the outside. 3. Seller will seal crack and fix water issue in the basement. 4. Make hot water heater operational so hot water can be tested prior to settlement. Hot water heater and/or gas at hot water heater was not on during inspection to be tested.
A16: 2810 Belair Dr | B16: Under Contract | C16: John | D16: 44581 | E16: 505000 | F16: 44580 | G16: 44581.604 | I16: N/A | J16: 44615 | K16: 44587 | L16: 525000 | M16: 44595 | O16: HI - 1/29 10AM Chimney - 2/1 9AM | P16: 44597 | Q16: 1/28 - Received PIN 2/3 - Seller Response 2/1 - Chimney PIN 2/7 - Seller Response | S16: 44596 | X16: Fully Approved | Y16: 3/2 Up half bath on main Gas - HW Collint - Type Electric No cool fuel force central and gas AC - Electric Back up generator, Generac Back up generator New roof, new siding, new kitshcen ss appliances, ceramic tile bathrooms, freshly painted, singele car garage, fenced in yard with shed (1), fireplace (1), an entry room addition, recessed lights throught, large master with walk in closet. Quartz counter top, Conveniently major shopping centers and transportation hubs, Cassidy within 10 miles radius.
A17: 513 Beebe Ct | B17: Under Contract | C17: John | D17: 44558 | E17: 279900 | F17: 44560 | G17: 12/29/2021 11AM | I17: 44601 | J17: 44617 | K17: 44563 | L17: 286000 | M17: 44592 | N17: Pinnacle | O17: 44594.375 | Q17: 44597 | S17: 44222 | X17: Listed resubmitted - 01/14/2022 * County Specific Notices Addendum - Uploaded Fred County Last checked - 01/14/2022 | Y17: Acquisition: 11/30/2021 OFFER - $285k FHA 1/1/22 OFFER - $258K Conv 1/15/22 OFFER - $275 Conv 1/19/22
A18: 1410 N Forest Park Ave | B18: Under Contract | C18: Justin | D18: 44576 | E18: 212000 | F18: 44550 | G18: 44568.521 | J18: 44617 | K18: 44585 | L18: 227300 | M18: 44587 | N18: 2/1/22 Qualia | O18: 44588.375 | P18: 44592 | X18: Fully Approved
A19: 7844 Citadel Dr | B19: Under Contract | C19: John | D19: 44585 | E19: 435000 | F19: 44580 | G19: 44588 | J19: 44620 | K19: 44589 | L19: 432500 | M19: 44589 | O19: 44590.542 | Q19: 1/30 - Received 2/2 - Seller | S19: 44594.375 | X19: Listed Approved - 01/25/2022 Last checked - 01/26/2022
A20: 505 Arbor Court, Edgewood, MD 21040 | B20: Under Contract | C20: Shaq | D20: 44595 | E20: 240000 | F20: 44211 | G20: 44223 | J20: 44630 | K20: 44598 | L20: 426000 | M20: 44599 | P20: 44610 | X20: Waiting for Fully Signed Contract | Y20: Has FHA Amendatory Clause.
A21: 1405 Spring Plow Ct | B21: Purchase | C21: Evan
A22: 3730 Greenmount Ave | B22: Purchase | C22: Shaq | D22: N/A | E22: N/A | F22: N/A | G22: N/A | J22: 44653 | K22: 44207 | L22: 370000 | X22: UC Submited - 01/26/2022 * EMD - missing * Notice to Buyer and Seller of Rights & Obligations - missing * County Specific * RPD *Pre-Approval Letter/Proof of Funds - missing * Property Addendum - Missing buyer signature *MLS Full Listing Synopsis - missing * Tax Records - missing * Buyer's Pre-settlement Walk-through Report - missing | Y22: ON HOLD
A23: 319 Top Cottage Ct | B23: Purchase | C23: Shaq | D23: N/A | E23: N/A | F23: N/A | G23: N/A | I23: N/A | J23: TBD | K23: 44536 | L23: 379685 | M23: 44536 | O23: N/A | P23: N/A | Q23: N/A | R23: N/A | X23: UC Resubmitted - 01/21/2022 * Pre-Approval Letter/Proof of Funds - Missing * MLS Full Listing Synopsis - Not needed | Y23: Who is the Title Officer? Inspections? Appraisal?, Need lender letter
A24: * | B24: * | C24: * | D24: * | E24: * | F24: * | G24: * | I24: * | J24: * | K24: * | L24: * | M24: * | N24: * | O24: * | P24: * | Q24: * | R24: * | S24: * | T24: * | U24: * | V24: * | W24: * | X24: * | Y24: * | Z24: *
A25: 9524 Clocktower Lane | B25: Closed | C25: Evan | D25: N/A | E25: N/A | F25: N/A | G25: N/A | I25: 44579 | J25: 44596 | K25: 44207 | L25: 405500 | M25: Completed | N25: Completed | O25: Completed | P25: Completed | Q25: Completed | R25: Completed | S25: Completed | T25: Completed | U25: 2/4/2022 1:30PM Canton Office 2/4 12:15 - Final Walkthrough | V25: Completed | W25: Completed | X25: Fully Approved | Y25: 1/12 - Title docs sent by Mallori
A26: 327 George Ave | B26: Closed | C26: Evan | D26: Off Market Sale | E26: NA | F26: NA | G26: N/A | I26: N/A | J26: 44199 | K26: 44536 | M26: 44545 | N26: Completed | O26: N/A | P26: As Is w/o Inspections | Q26: N/A | R26: N/A | S26: Approved | T26: N/A | U26: 12/29/21 7PM - Seller 1/3/2021 8:30 AM - Buyer | V26: YES | W26: 44559 | X26: Fully Approved | Y26: Need second Loan info from seller
A27: 8330 Pulaski Hwy Unit H | B27: Lease | C27: Shaq | D27: NA | J27: 44207 | K27: 44206 | L27: N/A | M27: N/A | N27: N/A | O27: N/A | P27: N/A | Q27: N/A | R27: N/A | S27: N/A | T27: N/A | U27: N/A | V27: N/A | W27: N/A | X27: Fully Approved | Y27: Tentatively we will put it to Flagship first end of February and coming soon end of March.
A28: 404 Carl Avenue | B28: Closed | C28: Paul | D28: N/A | E28: N/A | F28: N/A | G28: N/A | I28: N/A | J28: 44210 | K28: 44554 | M28: Completed | N28: Completed | O28: AS IS W/O | P28: As is w/o Inspections | Q28: N/A | R28: N/A | S28: N/A | T28: N/A | U28: Completed | V28: N/A | W28: Completed | X28: Fully Approved
A29: 733 Stinchcomb Road | B29: Closed | C29: Paul | D29: N/A | E29: N/A | F29: N/A | G29: N/A | I29: N/A | J29: 44220 | K29: 44559 | L29: 332000 | M29: Completed | N29: Completed | O29: N/A | P29: N/A | Q29: N/A | R29: N/A | S29: N/A | T29: N/A | U29: Notary | V29: N/A | W29: Completed | X29: UC - Notice to Buyer and Seller - not in dotloop (REO) last check: 01/14/2022 | Y29: Completed
A30: 263 S Robinson Street | B30: Closed | C30: Evan | D30: N/A | E30: N/A | F30: N/A | G30: N/A | I30: N/A | J30: 44224 | K30: 44553 | L30: 417500 | M30: 44560 | N30: 1/21/22 Qualia | O30: 44585.5 | P30: TBD | Q30: TBD | R30: TBD | S30: Completed | T30: Completed | U30: 12/28 12-1PM | V30: Completed | W30: 44588 | X30: Fully Approved
A31: 6 Colonial Dr | B31: Closed | C31: John | D31: 44528 | E31: 379900 | F31: 44529 | G31: 44526 | I31: N/A | J31: 44224 | K31: 44558 | L31: 402000 | M31: 44564 | N31: Completed | O31: 12/30/2021 12:30 PM 1/4/2022 10AM WDI | P31: 44200 | Q31: DONE 1/1/2021 - PIN 1/6/2021 - Seller | R31: 1/13 - Completed 1/13 - Receipts sent to BA | S31: Completed | T31: At Value | U31: Buyer: 2PM 1/28 | V31: 44582 | W31: 44581 | X31: Fully Approved | Z31: Pg.2 "Safety Concerns"- have a licensed HVAC professional remedy the possible gas leak located on the furnace. - Completed Pg. 2 "Safety Concerns"- Have a licensed electrician install a proper drip loop on the service entrance cable - To be done week of 1/3
A32: 2104 Goodwood Rd | B32: Closed | C32: John | D32: 44511 | G32: 44511.354 | I32: Completd | J32: 44567 | K32: 44537 | M32: 44544 | N32: Completed | O32: 44539.531 | P32: 12/21/2021 As Is | Q32: Completed | R32: Completed | S32: Approved | T32: N/A | U32: Completed | V32: Completed | W32: Received | X32: Fully Approved | Y32: Need repair receipts
A33: 502 Hamlen Rd | B33: Closed | C33: John | D33: 44897 | G33: 12/1 10:30 (TRU) | I33: N/A | J33: 44573 | K33: 44536 | M33: 44545 | N33: Completed | O33: 44542.438 | P33: 44543 | Q33: Completed | R33: Completed | S33: Completed | T33: Completed | U33: Completed | V33: 44199 | W33: 44201 | X33: Listed Approve - 01/06/2022 -- -- -- -- -- UC Returned - 01/06/22 * Notice to Buyer and Seller - Buyer Name needed in Page 1 | Y33: Completed
A34: 7134 Gough St | B34: Closed | C34: Shaq | D34: N/A | E34: N/A | F34: N/A | G34: 44526 | I34: N/A | J34: 44582 | K34: 44575 | L34: 145000 | M34: Completed | N34: N/A | O34: N/A | P34: N/A | Q34: N/A | R34: N/A | S34: N/A | T34: N/A | U34: Completed | V34: Completed | W34: Completed | X34: UC Submitted - 01/19/2022 | Y34: Has Ground rent
A35: 737 Concord Point Dr, Perryville, MD 21903 | B35: Closed | C35: Shaq | D35: N/A | E35: N/A | F35: N/A | G35: N/A | I35: N/A | J35: 44589 | K35: 44524 | L35: 405000 | M35: Completed | N35: Completed | O35: N/A | P35: N/A | Q35: N/A | R35: N/A | S35: N/A | T35: N/A | U35: 1/28/2022 11AM - Buyer Presigned - Seller | V35: Completed | W35: 44587 | X35: Fully Approved | Y35: The seller is going to want a remote closing on this transaction the cost can be covered from my commission. **Buyer*** They're military live on APG 11/30 Appraisal result is good. Came up higher than value
A36: * | B36: * | C36: * | D36: * | E36: * | F36: * | G36: * | I36: * | J36: * | K36: * | L36: * | M36: * | N36: * | O36: * | P36: * | Q36: * | R36: * | S36: * | T36: * | U36: * | V36: * | W36: * | X36: * | Y36: * | Z36: *
A37: 2922 Sylvan | B37: Terminated | C37: Shaq | D37: None | E37: None | F37: NA | G37: NA | I37: None | J37: 44624 | K37: 44592 | L37: 345000 | N37: 2/1/22 Qualia | O37: 2/3/2022 10-1PM
A38: 2129 Sunnythorn Rd | B38: Terminated | C38: Jen | D38: Off Market | E38: Off Market | G38: NA | I38: NA | J38: 44616 | K38: 44586 | L38: 155000 | N38: 1/26/2022 1/27 - Title to Seller | X38: Listed returned - 01/26/2022 (NOTE: Off-Market Sale. MLS Sheet Active is not available) * Financial Condition of Property Disclosure - held by needed. Last checked - 01/27/2022 -- -- -- -- -- -- UC returned - 01/26/2022 (NOTE: Buyer is Unrepresented. This is a Hard Money deal.) * EMD - Missing Last checked - 01/27/2022 | Y38: Jen's SOI Unrepresented Buyer, no admin fee on Buyer, no commission os Shaq Total commission is 3%. All wil go to Jen Proof of name change - Need divorce decree and marital settlement agreement

Sheet David
A1: Property | B1: Appraisal Schedule | C1: Appraisal | D1: List Price | E1: Sales Price | F1: Closing Date | G1: Ratification Date | H1: Inspection Contingency | I1: Inspection Schedule | J1: PIN | K1: Repairs Status
A2: 719 Hamlen Rd | B2: None | C2: None | D2: 320000 | E2: 320000 | F2: 44603 | G2: 44578 | H2: 44588 | I2: 1/21/22 For info only | J2: No requested repairs | K2: No repairs requested
A3: 7507 Overlook Ct | B3: 44593.542 | C3: Due 2/5/2022 | D3: 549000 | E3: 560000 | F3: 44603 | G3: 44568 | H3: 44575 | I3: 44574.5 | J3: 44578 | K3: 1/24 Completed
A4: 2810 Belair Dr | D4: 505000 | E4: 525000 | F4: 44615 | G4: 44587 | H4: 44597 | I4: Home - 1/29 10AM Chimney - 2/1 9AM | J4: 1/28 - Received PIN
A5: 513 Beebe Ct | B5: 44222 | C5: Due 2/6/2022 | D5: 279900 | E5: 286600 | F5: 44617 | G5: 44586 | H5: 44600 | I5: 44594.375
A6: 7844 Citadel Dr | B6: 44594.375 | D6: 435000 | E6: 450000 | F6: 44620 | G6: 44589 | H6: 44597 | I6: 44590.542 | J6: 1/30 - Received PIN

Sheet White Board
A1: WARNING! PLEASE DO NOT MODIFY
A2: Property Address | B2: Status | C2: Agent | D2: MLS Number | E2: Photos Schedule | F2: CS DATE | G2: Active Date | H2: Expiration | I2: Signed Date | J2: List Price | K2: Commission % Total | L2: List Side % | M2: Buy Side % | N2: Admin Fee | O2: Referral Y/N, Who, % | P2: Seller 1/ Email/ Phone | Q2: Seller 2/ Email/ Phone | R2: Forwarding Address | S2: Occupancy (Occupied, Vacant, Tenant, Leased) | T2: County | U2: Subdivision | V2: Ownership (Fee Simple or Ground Rent?) | W2: Sewer/Septic? If septic, add septic addendum | X2: Front Foot Fee? | Y2: HOA/Condo/Coop Fee/Frequency HOA Management info | Z2: HOA/Condo? Add 2 required addenda | AA2: LBP? Add MD Lead Prevention addendum & add year built in as a note to the cell) | AB2: Lockbox assigned, Location, Showing Instruction, etc | AC2: Add in tcDocs and Sync calendar | AD2: Sync tcDocs to Dotloop | AE2: Add contacts to Google Contacts | AF2: Send listing agreement & flagship form ONLY via dotloop Day 1 | AG2: Send intro email in tcDocs Day 1 | AH2: Request Netsheet from agent & send to sellers for signature (We do netsheet for Shaq & John only) | AI2: Once Listing Agreement is signed, send acknowledgement Email via tcdocs (Once received) | AJ2: Flagship First (Fill-up Form) (Required: signed form, photo, remarks) | AK2: Date Client filled out Pre-Listing Form | AL2: Once seller(s) fill Prelisting Info, prepare disclosures and send for signatures | AM2: HOA Resale Packet Ordered? Put NA if not applicable) | AN2: Photo Schedule (Send to Jeff, add date tin tcDocs) | AO2: Photos Link (Send email to Agent & Seller) Once received | AP2: Add disclosures in MLS (Before publishing) | AQ2: Setup Showing Instructions (Once published) | AR2: Update Status in Command | AS2: KW Ad in Command (Once active) | AT2: KW Direct Mail in Command (Once active) | AU2: Sign Installation Request (Once published) | AV2: Send MLS Sheet out for signature (Once published) | AW2: Send MLS is published (Selller & Agent) | AX2: COMPLIANCE | AY2: NOTES | AZ2: CONTRACT INFO | BA2: Sales Price | BB2: EMD Amount | BC2: EMD Held by | BD2: Seller Contribution | BE2: Escalation Clause | BF2: Increased Value over Appraisal Amt | BG2: Ratification | BH2: Closing | BI2: EMD Received | BJ2: Financing Commitment | BK2: Inspection Contingency | BL2: Inspection Date | BM2: Appraisal Date | BN2: Walkthrough Date | BO2: Title Docs Completed | BP2: FWD/RCV HOA Resale | BQ2: Lender Required Repairs | BR2: Post Settlement Occupancy Deadline Fee, Deposit, Held By, Final Inspection & Disbursement | BS2: FTHB (Tax Split) | BT2: Home Warranty (Cost, Paid By, Provider) | BU2: Financing (Cash, Conv, VA, etc) | BV2: Other Parties Client Under Contract - Buyers Name Purchase - Seller (Owner) Name | BW2: Cooperative Agent Under Contract - Buyers Agent Purchase - Listing Agent | BX2: Title | BY2: Lender | BZ2: Appraiser | CA2: Add/Convert in tcDocs | CB2: Sync Calendar & Dotloop in tcDocs | CC2: Change MLS to Pending/AUC Update status in dotloop, command & ss) | CD2: Review each Ratified Contract file for completeness | CE2: Intro to BA/LA,Title, Lender (tcDocs) | CF2: Intro to Seller/Buyer (tcDocs) | CG2: Send calendar invite to Agent for Projected Closing date | CH2: Confirm Commission Details w/ agent (Email via tcDOcs) | CI2: Order sign down (2 days before COE) (POTENTIALLY TO ADMIN) | CJ2: Commission Tab Submission (day of closing) (Potentially to ADMIN) | CK2: ALTA/HUD Received? Send to seller, Upload to command and dotloop (Potentially to Admin) | CL2: Schedule HUD to Seller 1/22/2022 (Potentially to ADMIN) | CM2: Close in MLS, Dotloop, Command (Potentially to ADMIN) | CN2: KW Direct Mail in Command (Once closed) | CO2: Home Inspection Schedule Add to tcDocs, Send email & Calendar invite | CP2: PIN (Received) | CQ2: HI PIN Due Date | CR2: PIN Response Received | CS2: PIN Final Election | CT2: PIN Satisfied | CU2: Repair Receipts | CV2: Confirm Lender Required Repairs have been completed (5 days before COE) | CW2: Appraisal Order Date | CX2: Appraisal Received | CY2: Confirm Final Walkthrough w/ Coop (5 days before COE) Add date here | CZ2: Request Prelim ALTA | DA2: Agent TP#4 (5 days before COE) - Review ALTA | DB2: Schedule Closing | DC2: Follow up with Title for checks (1 day after closing) | DD2: Agent retrieve lockbox reminder(Day of closing) | DE2: Confirm LB Returned | DF2: Requested Repairs List
A3: {=TRANSPOSE(OFFSET(Contracts!$B$2:$CN$111,0,1))} -> 3012 Rices Ln Windsor Mill, MD 21244 | B3: Under Contract | C3: Justin | D3: MDBC2004306 | E3: - | F3: 44407 | G3: 44414 | H3: 44677 | I3: 44312 | J3: 500000 | K3: 0.06 | L3: 0.0475 | M3: 1.25%% | N3: 495 | O3: N | P3: Sadi Wadi 203-901-2270 Home Email: sadiwadi@hotmail.com zainahwadi@gmail.com | Q3: N/A | R3: - | S3: Owner Occupied | T3: Baltimore | U3: Windsor Mill | V3: Fee Simple | W3: Septic | X3: N/A | Y3: N/A | Z3: TRUE | AA3: TRUE | AB3: 965407 | AC3: TRUE | AD3: TRUE | AE3: TRUE | AF3: TRUE | AG3: TRUE | AH3: TRUE | AI3: TRUE | AJ3: TRUE | AK3: Done | AL3: TRUE | AM3: N/A | AN3: TRUE | AO3: https://nimamohammadi.hd.pics/d/1F65AFDC5A24417BAB442E998B346ED2 | AP3: TRUE | AQ3: TRUE | AR3: TRUE | AS3: TRUE | AT3: TRUE | AU3: TRUE | AV3: TRUE | AW3: TRUE | AX3: Fully approved | AY3: - No Appraisal Contingency - If value is low, SPCC shall be reduced dollar per dollar. - BA comp will be paid entirely by buyer. - Septic system is failed, contract is not contingent upon the septic system. LA commission is 4.75% and we are to co-op 1.25% to the BA | BA3: 525000 | BB3: 5000 | BC3: Berkshire Hathaway HomeServices | BD3: - | BE3: - | BF3: - | BG3: 2/11/2022 | BH3: 4/22/2022 | BI3: 44616 | BJ3: 3/13/2022 | BK3: 2/21/2022 | BO3: 2/24/2022 Qualia | BP3: N/A | BQ3: 0 | BR3: N/A | BS3: Yes, 50/50 Split | BT3: None | BU3: Conventional | BV3: Johnny Charles Carrington Jr. | BW3: Debbie Reynolds Berkshire Hathaway HomeServices dreynoldshomes@gmail.com 410-365-9625 | BX3: Kisha Powell Integrity Title & Escrow Company, LLC. kpowell@integritytitlellc.com 410-581-5230 Keya Queen Integrity Title & Escrow Company, LLC. keya@integritytitlellc.com 410-581-2043 | BY3: Peter Haubruck Heritage Mortgage Banking Corporation peter@hmbccorp.com 973-539-9898 | CA3: Done | CB3: Done | CC3: AUC | CD3: Done | CE3: Done | CF3: Done | CI3: Done | CP3: 5 | CR3: 2 | CV3: N/A | CW3: N/A | CX3: N/A
A4: 312 S 4Th St Denton, MD 21629 | B4: Under Contract | C4: Romont | D4: MDCM2001204 | E4: 2/14/2022 | F4: N/A | G4: 44609 | H4: 44974 | I4: 44600 | J4: 329900 | K4: 0.05 | L4: 0.025 | M4: 0.025 | N4: 695 | O4: N | P4: Jenny Rodenhizer 443-520-5003 jenny_lynn83@hotmail.com | Q4: Brian Rich 410-829-7080 brich912@yahoo.com | R4: - | S4: Vacant | T4: Caroline | U4: Not in a Subdivision | V4: Fee Simple | W4: Sewer | X4: N/A | Y4: N/A | Z4: N/A | AA4: TRUE | AB4: Automated Lock - 0326 Side Door | AC4: TRUE | AD4: TRUE | AE4: TRUE | AF4: TRUE | AG4: TRUE | AH4: TRUE | AI4: TRUE | AJ4: TRUE | AK4: Done | AL4: TRUE | AM4: N/A | AN4: TRUE | AO4: https://drive.google.com/drive/folders/1oZYI9L0TsyL9MXd8oc4pz3UHdjsGT-US?usp=sharing | AP4: TRUE | AQ4: TRUE | AR4: TRUE | AS4: TRUE | AT4: TRUE | AU4: TRUE | AV4: TRUE | AW4: TRUE | AX4: Fully Approved as of 04/01/2022 Last checked: 04/06/2022 | BA4: 330000 | BB4: 3000 | BC4: Douglas Realty, LLC. | BD4: - | BE4: - | BF4: - | BG4: 3/22/2022 | BH4: 4/22/2022 | BI4: 44651 | BJ4: 3/24/2022 | BK4: 3/27/2022 As Is w/ Inspections | BP4: N/A | BQ4: 100 | BR4: N/A | BS4: No, 50/50 Split | BT4: None | BU4: Cash | BV4: Justin Eastman | BW4: Sharon Burkhardt Douglas Realty, LLC. sharonb14@gmail.com 410-375-3177 | BX4: Maryann Hayes Admiral Title Group mhayes@admiraltitlegroup.com 410-263-7336 ext 303 | BY4: Bryan Hooper AnnieMac Home Mortgage bhooper@annie-mac.com 443-875-7345 | CA4: Done | CB4: Done | CC4: Pending | CD4: Done | CE4: Done | CF4: Done | CI4: Done | CT4: w
A5: 3100 Brightseat Road Landover, MD 20785 | B5: Under Contract | C5: John | E5: 3/25/2022 | F5: N/A | G5: 44643 | H5: 45006 | I5: 44642 | P5: Residential Value, LLC. Work Mobile: 301-674-0760 Work Email: dsl227@aol.com | Q5: David Loring | R5: 751 Rockville Pike 1A, Rockville MD 20852 | S5: Vacant | T5: Prince George's | U5: Pointer Ridge at Prince Geoge's | V5: Fee Simple | W5: Sewer | X5: N/A | Y5: N/A | Z5: N/A | AA5: TRUE | AC5: TRUE | AD5: TRUE | AE5: TRUE | AF5: TRUE | AG5: TRUE | AH5: TRUE | AI5: TRUE | AJ5: N/A | AK5: N/A | AL5: N/A | AM5: N/A | AN5: TRUE | AO5: https://drive.google.com/drive/folders/1q16g-a0yIjVhCB_XQR6kp1pVH7jxG1AK?usp=sharing | AP5: TRUE | AQ5: TRUE | AR5: TRUE | AS5: FALSE | AT5: FALSE | AU5: N/A | AV5: FALSE | AW5: TRUE | AX5: Fully Approved as of 04/06/2022 Last checked: 04/06/2022 | BA5: 337500 | BB5: 3350 | BC5: North Frontier Title & Escrow | BD5: - | BE5: - | BF5: - | BG5: 3/26/2022 | BH5: 4/25/2022 | BI5: 44656 | BJ5: 4/16/2022 | BK5: N/A | BL5: N/A | BP5: N/A | BQ5: 500 | BR5: N/A | BV5: Marvin Javier Majano Bonilla | BW5: Elber Olivo First Decision Real Estate elber@olivosrealty.com 703-814-2026 | BX5: (Seller) Jonathan Morgan, Esq. Pinnacle Title and Escrow, Inc. jmorgan@pinnacletitle.com 301-279-4246 (Buyer) Carolina Llina North Frontier Title & Escrow cllinas@northfrontiertitle.com 301-640-5045 | BY5: Ali Jamshidi 4Ever Lending USA ali@4everlendingusa.com 703-309-9395 | CA5: Done | CB5: Done | CC5: Pending | CD5: Done | CE5: Done | CF5: Done | CI5: N/A
A6: 2806 Keating Street Unit #159 Temple Hills, MD 20748 | B6: Under Contract | C6: John | E6: 3/21/2022 | F6: N/A | G6: 44643 | H6: 45007 | I6: 44642 | P6: Residential Value, LLC. Work Mobile: 301-674-0760 Work Email: dsl227@aol.com | Q6: David Loring | Y6: Iverson Square Condominium $275/Monthly | Z6: TRUE | AA6: TRUE | AC6: TRUE | AD6: TRUE | AE6: TRUE | AF6: TRUE | AG6: TRUE | AH6: TRUE | AI6: TRUE | AJ6: N/A | AK6: N/A | AL6: N/A | AM6: FALSE | AN6: FALSE | AO6: https://drive.google.com/drive/folders/14SnkVOdqXS-59rSLv_zY7wjM5-pcowjj | AP6: TRUE | AQ6: TRUE | AR6: TRUE | AS6: FALSE | AT6: FALSE | AU6: N/A | AV6: FALSE | AW6: TRUE | AX6: Fully Approved 04/14/2022 | BA6: 159500 | BB6: 2000 | BC6: Pinnacle Title and Escrow | BD6: - | BE6: - | BF6: - | BG6: 3/28/2022 | BH6: 4/27/2022 | BI6: 44664 | BJ6: 4/18/2022 | BK6: As Is w/o Inspections | BL6: N/A | BP6: N/A | BQ6: 0 | BR6: N/A | BV6: Hedayet Ullah | BW6: Edward Dumitrache eXp Realty, LLC. edwarddumi23@gmail.com 301-357-1170 | BX6: Jonathan Morgan, Esq. Pinnacle Title and Escrow, Inc. jmorgan@pinnacletitle.com 301-279-4246 | BY6: Sharon Kline Allied First Bank SB skline@alliedfirst.com 703-615-1313 | CA6: Done | CB6: Done | CC6: Pending | CD6: Done | CE6: Done | CF6: Done | CI6: N/A
A7: 3219 Elliott St Baltimore, MD 21224 | B7: Under Contract | C7: Jen | D7: MDBA2028492 | E7: 2/28/2022 10 AM | F7: N/A | G7: 44622 | H7: 44938 | I7: 44592 | J7: 269000 | K7: 0.06 | L7: 0.035 | M7: 0.025 | N7: 695 | O7: N | P7: Sandra Andrzejewski 443-912-4622 crab925@aol.com | Q7: Emil Zeller emilzeller3@gmail.com | S7: Tenant Occupied | T7: Baltimore City | U7: Canton | V7: Fee Simple | W7: Sewer | X7: N/A | Y7: N/A | Z7: N/A | AA7: TRUE | AB7: Tenant Occupied Lynn Weikel lynnweikel@gmail.com 801-654-5663 Appointment Required Code for the front door - 943760 | AC7: TRUE | AD7: TRUE | AE7: TRUE | AF7: TRUE | AG7: TRUE | AH7: TRUE | AI7: TRUE | AJ7: TRUE | AK7: TRUE | AL7: TRUE | AM7: N/A | AN7: TRUE | AO7: https://drive.google.com/drive/folders/1S9vDpT3Wnw46YXSa1qyxsI_UD6DTP35n | AP7: TRUE | AQ7: TRUE | AR7: TRUE | AS7: TRUE | AT7: TRUE | AU7: TRUE | AV7: TRUE | AW7: TRUE | AX7: Listed Returned: 3/14/2022 * MLS Full Listing SIGNED by seller needed Last checked: 04/15/2022 | AY7: Currently tenant occupied with lease ending 4/30/22. More details regarding photo date, coming soon and listing date after we narrow down a walk through time with the seller's property management company. They are also looking for another investment property as well Pending: We're going to aim for photos the last week of feb to give them some time to clean up. I'll follow up with her next week to make sure everything is on track. | BA7: 269000 | BB7: 4000 | BC7: RE/MAX Executive | BD7: - | BE7: - | BF7: - | BG7: 3/30/2022 | BH7: 5/6/2022 | BJ7: 4/29/2022 | BK7: 4/07/2022 | BP7: N/A | BQ7: 500 | BR7: N/A | BV7: Damia Yoon | BW7: Jessica Young-Stewart RE/MAX Executive jess@jessyoungrealestate.com 443-623-8271 Tonya Young Transaction Coordinator tonya@jessyoungrealestate.com | BX7: Stacy Cantwell In House Title stacy@ihtitle.com 410-777-5311 | BY7: Rhoda Ngere Bank of America rhoda.ngere@bofa.com 410-892-1207 | CA7: Done | CB7: Done | CC7: Pending | CD7: Done | CE7: Done | CF7: Done
A8: 1523 Tucker Rd Fort Washington, MD 20744 | B8: Under Contract | C8: John | E8: 4/5/2022 | F8: N/A | G8: 44659 | H8: 45016 | I8: 44655 | P8: David Loring 301-674-0760 dsl227@aol.com | Q8: N/A | Y8: N/A | Z8: N/A | AA8: TRUE | AC8: TRUE | AD8: TRUE | AE8: TRUE | AF8: TRUE | AG8: TRUE | AH8: TRUE | AI8: TRUE | AJ8: N/A | AK8: N/A | AL8: N/A | AM8: N/A | AN8: TRUE | AO8: tour.TruPlace.com/property/706/110039/ | AP8: TRUE | AQ8: TRUE | AR8: TRUE | AS8: TRUE | AT8: N/A | AU8: N/A | AV8: TRUE | AW8: TRUE | AX8: Listed approved: 04/06/2022 Last checked: 04/12/2022 -- -- -- -- -- -- UC Submitted: 04/12/2022 * EMD - not yet available Last checked: 04/15/2022 | BA8: 410000 | BB8: 5000 | BC8: Taylor Properties | BD8: - | BE8: - | BF8: - | BG8: 4/12/2022 | BH8: 5/11/2022 | BK8: As Is w/o Inspections | BL8: N/A | BP8: N/A | BQ8: 0 | BR8: N/A | BV8: Jose I Ticas | BW8: Wilmer Bucarelo Taylor Properties wilmer@thebucasteam.com 301-252-7400 | BX8: Jonathan Morgan, Esq. Pinnacle Title and Escrow, Inc. jmorgan@pinnacletitle.com 301-279-4246 | BY8: Adrian Ciaramellano Homespire Mortgage adrianc@homespiremortgage.com 301-230-9731 | CA8: Done | CB8: Done | CC8: Pending | CD8: Done | CE8: Done | CF8: Done | CI8: N/A
A9: 2801 Deepwater Trl Edgewater, MD 21037 | B9: Under Contract | C9: Justin | D9: MDAA2023760 | E9: 4/14/2022 | F9: 44651 | G9: 44665 | H9: 44947 | I9: 44582 | J9: 1000000 | K9: 0.0525 | L9: 0.03 | M9: 0.0225 | N9: 695 | O9: N | P9: Sharon Herr 410-573-9970 sharonherr@hotmail.com | Q9: Contact Person Cody Herr cscottherr@gmail.com | S9: Occupied | T9: Anne Arundel | U9: Poplar Point | V9: Fee Simple | W9: Sewer | X9: N/A | Y9: Poplar Point Community Association $300/Annually | Z9: TRUE | AA9: N/A | AC9: TRUE | AD9: TRUE | AE9: TRUE | AF9: TRUE | AG9: TRUE | AH9: TRUE | AI9: TRUE | AJ9: TRUE | AK9: TRUE | AL9: TRUE | AM9: FALSE | AN9: FALSE | AP9: TRUE | AQ9: TRUE | AR9: FALSE | AS9: FALSE | AT9: FALSE | AU9: FALSE | AV9: FALSE | AW9: FALSE | AX9: 2/23/2022 Upload documents in Command | AY9: Expected Coming soon 3/3/22 & Active 3/17/21
A10: 12912 Churchill Ridge Cir # 5-B Germantown, MD 20874 | B10: Under Contract | C10: Justin | E10: 4/11/2022 | F10: 44640 | G10: 44660 | H10: 44932 | I10: 44585 | J10: 290000 | K10: 0.06 | L10: 0.035 | M10: 0.025 | N10: 495 | O10: N | P10: Michael Kelly 301-473-6464 mikekelly@kellyfloorsllc.com | Q10: N/A | S10: Owner Occupied | T10: Montgomery | U10: Churchill View | V10: Fee Simple | W10: Sewer | X10: N/A | Y10: Churchill View HOA The Management Group Associates $300/Monthly | Z10: TRUE | AA10: N/A | AC10: TRUE | AD10: TRUE | AE10: TRUE | AF10: FALSE | AG10: TRUE | AH10: TRUE | AI10: TRUE | AJ10: TRUE | AK10: TRUE | AL10: TRUE | AM10: FALSE | AN10: FALSE | AO10: http://www.homevisit.com/my/property/contactSheet/?hvid=372813 | AP10: TRUE | AQ10: TRUE | AR10: FALSE | AS10: FALSE | AT10: FALSE | AU10: TRUE | AV10: FALSE | AW10: FALSE | AX10: Listed submitted: 03/24/2022 *MLS Full Listting w/ seller signature not included -- -- -- -- -- -- UC Submitted: 04/19/2022 Uploaded docs
A11: 319 Top Cottage Ct | B11: Purchase | C11: Shaq | D11: N/A | E11: N/A | F11: N/A | G11: N/A | H11: N/A | I11: N/A | K11: N/A | L11: N/A | M11: 0.02 | N11: None | O11: N | R11: N/A | S11: N/A | T11: N/A | U11: N/A | V11: N/A | W11: N/A | X11: N/A | Y11: N/A | Z11: FALSE | AA11: FALSE | AB11: N/A | AC11: NA | AD11: NA | AE11: NA | AF11: NA | AG11: NA | AH11: NA | AI11: NA | AJ11: NA | AK11: NA | AL11: NA | AM11: NA | AN11: NA | AO11: NA | AP11: NA | AQ11: NA | AR11: NA | AS11: NA | AT11: NA | AU11: NA | AV11: NA | AW11: NA | AX11: 1/212022 Pre-Approval Letter/Proof of Funds - Missing Last checked - 04/06/2022 | AY11: in house | BA11: 379685 | BB11: 3800 | BC11: Innovative Builder Solutions LLC | BD11: 20000 | BE11: N/A | BF11: N/A | BG11: 12/06/2021 | BH11: TBD | BJ11: 1/5/2022 | BK11: N/A | BQ11: None | BR11: N/A | BS11: Yes, 50/50 Split | BT11: Builder's Warranty | BU11: FHA | BV11: Sage Custom Homes LLC | BW11: Justin McCurdy Sage Homes 410-942-6611 justin@sagehomesmd.com | BX11: Residential Title Company | BY11: Clint Kohler Sandy Spring Bank 240-517-0589 ckohler@sandyspringbank.com | CH11: 70% Shaq, 30% John | CI11: N/A | CP11: 5 | CR11: 2
A12: 3730 Greenmount Ave | B12: Purchase | C12: Shaq | D12: N/A | E12: N/A | F12: N/A | G12: N/A | H12: N/A | I12: N/A | K12: N/A | L12: N/A | O12: N | Q12: N/A | R12: N/A | S12: N/A | T12: N/A | U12: N/A | V12: N/A | W12: N/A | X12: N/A | Y12: N/A | Z12: FALSE | AA12: FALSE | AB12: N/A | AC12: NA | AD12: NA | AE12: NA | AF12: NA | AG12: NA | AH12: NA | AI12: NA | AJ12: NA | AK12: NA | AL12: NA | AM12: NA | AN12: NA | AO12: NA | AP12: NA | AQ12: NA | AR12: NA | AS12: NA | AT12: NA | AU12: NA | AV12: NA | AW12: NA | AX12: UC Returned: 3/11/2022 * EMD * Pre-Approval Letter * Property Inspection Addendum - Seller to execute Last checked: 04/06/2022 | AY12: Who is the Title Officer? Inspections? Appraisal?, Need lender letter | BA12: 379685 | BB12: 3000 | BC12: Charter Title, LLC. | BD12: 0.03 | BE12: - | BF12: - | BG12: 12/06/2021 | BH12: 4/2/2022 | BI12: 44536 | BJ12: 4/05/2022 | BK12: 3/14/2022 | BP12: N/A | BQ12: 100 | BR12: N/A | BS12: Yes, 50/50 Split | BT12: N/A | BU12: FHA | BV12: Philotes, LLC. | BW12: Austin Carroll The Newman Group at Keller Williams Flagship of Maryland acarroll@kw.com 443-864-2466 | BX12: Erin Donaty Charter Title, LLC. edonaty@chartertitlemd.com 410-946-0200 | BY12: Michael Weinstein Norcom Mortgage michael.weinstein@norcom-usa.com 240-447-2092 | CA12: Done | CB12: Done | CC12: Off-Market | CD12: Done | CE12: Done | CF12: Done | CI12: N/A | CP12: 5 | CR12: 2
A13: 2626 Miles Ave Baltimore, MD 21211 | B13: Purchase | C13: Evan | E13: N/A | F13: N/A | G13: N/A | H13: N/A | I13: N/A | P13: BGATB, LLC. | Q13: Damon Lipscomb damonlipscomb@gmail.com | Y13: N/A | Z13: N/A | AA13: TRUE | AC13: NA | AD13: NA | AE13: NA | AF13: NA | AG13: NA | AH13: NA | AI13: NA | AJ13: NA | AK13: NA | AL13: NA | AM13: NA | AN13: NA | AO13: NA | AP13: NA | AQ13: NA | AR13: NA | AS13: NA | AT13: NA | AU13: NA | AV13: NA | AW13: NA | AX13: UC Resubmitted: 04/15/2022 * EMD - not yet available *Proof of Funds - not yet available *Notice to Buyer and Seller - awaiting for signatures Updated: *Tenant Agr - complete *KW Communication - complete * County Addendum - complete Last checked: 04/15/2022 | BA13: 202250 | BB13: 5000 | BC13: Legacy Settlement Services | BD13: - | BE13: 2500 | BF13: - | BG13: 4/8/2022 | BH13: 4/20/2022 | BJ13: N/A | BK13: 4/15/2022 | BM13: N/A | BP13: N/A | BQ13: 0 | BR13: N/A | BV13: Mayes Capitol Investments Authorized Signee: Rashaad Mayes | BW13: Alainna Cox Amber & Company Real Estate alainnacox@gmail.com 513-607-5435 | BX13: Dave Euga Legacy Settlement Services, LLC. david@legacyfortitle.com 410 925-0566 | BY13: N/A | CA13: Done | CB13: Done | CD13: Done | CE13: Done | CF13: Done | CI13: N/A
A14: 7010 Cresthaven Dr Glen Burnie, MD 21061 | B14: Purchase | C14: Paulo | E14: N/A | F14: N/A | G14: N/A | H14: N/A | I14: N/A | P14: Residential Value, LLC. Work Mobile: 301-674-0760 Work Email: dsl227@aol.com | Q14: David Loring | Y14: N/A | Z14: N/A | AA14: TRUE | AC14: NA | AD14: NA | AE14: NA | AF14: NA | AG14: NA | AH14: NA | AI14: NA | AJ14: NA | AK14: NA | AL14: NA | AM14: NA | AN14: NA | AO14: NA | AP14: NA | AQ14: NA | AR14: NA | AS14: NA | AT14: NA | AU14: NA | AV14: NA | AW14: NA | AX14: UC Resubmitted: 04/15/2022 *County Addendum - updated Last checked: 04/15/2022 | BA14: 283000 | BB14: 5000 | BC14: Pinnacle Title & Escrow | BD14: - | BE14: - | BF14: - | BG14: 4/12/2022 | BH14: 4/21/2022 | BJ14: N/A | BK14: As Is w/o Inspections | BL14: N/A | BM14: N/A | BP14: N/A | BQ14: 0 | BR14: N/A | BV14: Carolyn Silk POA: David Lawrence Sugg & Linda Elizabeth Herb | BW14: Rose Calderone ExecuHome Realty rosecalderonerealtor@gmail.com 443-617-9088 | BX14: Jonathan Morgan, Esq. Pinnacle Title and Escrow, Inc. jmorgan@pinnacletitle.com 301-279-4246 | BY14: N/A | CA14: Done | CB14: Done | CD14: Done | CE14: Done | CF14: Done | CI14: N/A
A15: 10 Butternut Dr Middle River, MD 21220 | B15: Purchase | C15: Shaq | E15: N/A | F15: N/A | G15: N/A | H15: N/A | I15: N/A | P15: Taylor Darnell 443-955-0590 taylordarnell106@gmail.com | Q15: Alex Darnell AlexDarnell92@gmail.com | Y15: N/A | Z15: N/A | AA15: TRUE | AC15: NA | AD15: NA | AE15: NA | AF15: NA | AG15: NA | AH15: NA | AI15: NA | AJ15: NA | AK15: NA | AL15: NA | AM15: NA | AN15: NA | AO15: NA | AP15: NA | AQ15: NA | AR15: NA | AS15: NA | AT15: NA | AU15: NA | AV15: NA | AW15: NA | AX15: Fully Approved as of 04/03/2002 Last checked: 04/06/2022 | BA15: 311000 | BB15: 3000 | BC15: Keller Williams Flagship of MD | BD15: - | BE15: - | BF15: - | BG15: 3/24/2022 | BH15: 4/22/2022 | BJ15: 4/14/2022 | BK15: 3/31/2022 As Is w/ Inspections | BP15: N/A | BQ15: 500 | BR15: N/A | BV15: Pauli Vernon | BW15: Kimberly Grubb Cummings & Co Realtors thegrubbteam@gmail.com 410-322-7981 | BX15: Lauren Daniels Legacy Settlement Services, LLC. Lauren@legacyfortitle.com 410 925-0566 Dave Euga Legacy Settlement Services, LLC. david@legacyfortitle.com 410 925-0566 | BY15: Kyndle Quinones Primary Residential Mortgage, Inc. ksquinones@primeres.com 443-254-0381 | CA15: Done | CB15: Done | CC15: Pending | CD15: Done | CE15: Done | CF15: Done | CI15: N/A
A16: 504 Kathryn Ct Denton, MD 21629 | B16: Purchase | C16: Vince | E16: N/A | F16: N/A | G16: N/A | H16: N/A | I16: N/A | P16: Nancy Pullen njpullen@gmail.com | Q16: Michael Pullen 615-504-2242 mickey.pullen@gmail.com | Y16: N/A | Z16: N/A | AA16: N/A | AC16: NA | AD16: NA | AE16: NA | AF16: NA | AG16: NA | AH16: NA | AI16: NA | AJ16: NA | AK16: NA | AL16: NA | AM16: NA | AN16: NA | AO16: NA | AP16: NA | AQ16: NA | AR16: NA | AS16: NA | AT16: NA | AU16: NA | AV16: NA | AW16: NA | AX16: Fully Approved as of 04/10/2002 Last checked: 04/15/2022 | BA16: 335000 | BB16: 6700 | BC16: Keller Williams Flagship of MD | BD16: - | BE16: - | BF16: 10000 | BG16: 4/4/2022 | BH16: 4/26/2022 | BI16: 44659 | BJ16: 4/18/2022 | BK16: As Is w/o Inspections | BL16: N/A | BP16: N/A | BQ16: 5000 | BR16: N/A | BV16: Julie Slivka & Ralph Sergiovanni | BW16: Barbara McCaffrey Redfin Corp barbara.mccaffrey@redfin.com 443-926-6075 | BX16: Charter Title info@chartertitlemd.com | BY16: A.J. Campitelli FitzGerald Financial Group aj.campitelli@fitzgeraldfinancial.net 410-353-0536 | CA16: Done | CB16: Done | CC16: Pending | CD16: Done | CE16: Done | CF16: Done | CI16: N/A
A17: 100 N Belnord Avenue Baltimore, MD 21224 | B17: Purchase | C17: Evan | E17: N/A | F17: N/A | G17: N/A | H17: N/A | I17: N/A | P17: Austin Seivold austinseivold@gmail.com | Q17: N/A | Y17: N/A | Z17: N/A | AA17: FALSE | AC17: NA | AD17: NA | AE17: NA | AF17: NA | AG17: NA | AH17: NA | AI17: NA | AJ17: NA | AK17: NA | AL17: NA | AM17: NA | AN17: NA | AO17: NA | AP17: NA | AQ17: NA | AR17: NA | AS17: NA | AT17: NA | AU17: NA | AV17: NA | AW17: NA | AX17: Fully Approved as of 04/01/2002 Last checked: 04/06/2022 | BA17: 387000 | BB17: 4000 | BC17: Legacy Settlement Services | BD17: 0.03 | BE17: - | BF17: - | BG17: 3/26/2022 | BH17: 4/29/2022 | BI17: 44651 | BJ17: 4/20/2022 | BK17: 3/31/2022 As Is w/ Inspections | BP17: N/A | BQ17: 500 | BR17: N/A | BV17: Julia Rives Wilson & Giuseppe Bonato | BW17: Photi (Frank) Mavroulis Remax Advantage Realty photi.mavroulis@gmail.com 443-691-6590 | BX17: Lauren Daniels Legacy Settlement Services, LLC. Lauren@legacyfortitle.com 410 925-0566 Dave Euga Legacy Settlement Services, LLC. david@legacyfortitle.com 410 925-0566 | BY17: Charlene Chhang Truist Charlene.Chhang@truist.com | CA17: Done | CB17: Done | CC17: Active Under Contract | CD17: Done | CE17: Done | CF17: Done | CI17: N/A
A18: 208 E Fort Ave Baltimore, MD 21230 | B18: Purchase | C18: Evan | E18: N/A | F18: N/A | G18: N/A | H18: N/A | I18: N/A | P18: Jessica Mariano jesspark92@gmail.com | Q18: N/A | Y18: N/A | Z18: N/A | AA18: FALSE | AC18: NA | AD18: NA | AE18: NA | AF18: NA | AG18: NA | AH18: NA | AI18: NA | AJ18: NA | AK18: NA | AL18: NA | AM18: NA | AN18: NA | AO18: NA | AP18: NA | AQ18: NA | AR18: NA | AS18: NA | AT18: NA | AU18: NA | AV18: NA | AW18: NA | AX18: UC Resubmitted: 04/15/2022 * County Addendum - none in dotloop * Notice ot Buyer Rights - none in dotloop Update: * Exclusive Buyer/Tenant - Complete * KWF- Communication - Complete Last checked: 04/15/2022 | BA18: 360000 | BB18: 3000 | BC18: Presidential Title LLC. | BD18: 0.03 | BE18: - | BF18: - | BG18: 3/30/2022 | BH18: 4/29/2022 | BI18: 44656 | BJ18: 4/24/2022 | BK18: 4/06/2022 | BP18: N/A | BQ18: 500 | BR18: N/A | BV18: Ty Webb LLC. Chris Brusznicki - Authorized Signee | BW18: Keith Brooks Thurston Wyatt Real Estate, LLC. keithbrooks99@hotmail.com 410-320-6785 | BX18: Geoffrey Polk Presidential Title LLC. geoff@geoffreypolk.com 312-929-3861 | BY18: Dino Broccolino Truist Dino.Broccolino@truist.com 443-367-2406 | CA18: Done | CB18: Done | CC18: Pending | CD18: Done | CE18: Done | CF18: Done | CI18: N/A
A19: 4111 Idaho Ave Baltimore, MD 21206 | B19: Purchase | C19: Jen | E19: N/A | F19: N/A | G19: N/A | H19: N/A | I19: N/A | P19: Ava Kelley 240-270-2603 kelleyava12@gmail.com | Q19: Clifford Preston 202-459-8610 cliffordpreston2@gmail.com | Y19: N/A | Z19: N/A | AA19: FALSE | AC19: NA | AD19: NA | AE19: NA | AF19: NA | AG19: NA | AH19: NA | AI19: NA | AJ19: NA | AK19: NA | AL19: NA | AM19: NA | AN19: NA | AO19: NA | AP19: NA | AQ19: NA | AR19: NA | AS19: NA | AT19: NA | AU19: NA | AV19: NA | AW19: NA | AX19: UC Resubmitted: 04/15/2022 * Exclusive Buyer/Tenant - uploaded Last checked: 04/15/2022 | BA19: 300000 | BB19: 2000 | BC19: Legacy Settlement Services | BD19: - | BE19: - | BF19: - | BG19: 3/31/2022 | BH19: 4/29/2022 | BJ19: 4/25/2022 | BK19: 4/07/2022 | BP19: N/A | BQ19: 500 | BR19: N/A | BV19: Omid Land Group, LLC. Alireza Aliaskari - Authorized Signee | BW19: Alex Fox Allfirst Realty, Inc. alex@allfirstmd.com 410-963-3191 | BX19: Nate Kish Legacy Settlement Services, LLC. Nate@legacyfortitle.com 410 925-0566 | BY19: Samuel Miskiel Coastal Lending Group Sam@clgroup.biz 443-808-6788 | CA19: Done | CB19: Done | CC19: Active | CD19: Done | CE19: Done | CF19: Done | CI19: N/A
A20: 40 Sugar Tree Pl Cockeysville, MD 21093 | B20: Purchase | C20: Shaq | E20: N/A | F20: N/A | G20: N/A | H20: N/A | I20: N/A | P20: Brendan Clark 410-507-9140 bdclark8@gmail.com | Q20: N/A | R20: N/A | S20: N/A | T20: N/A | U20: N/A | V20: N/A | W20: N/A | X20: N/A | Y20: N/A | Z20: N/A | AA20: N/A | AC20: NA | AD20: NA | AE20: NA | AF20: NA | AG20: NA | AH20: NA | AI20: NA | AJ20: NA | AK20: NA | AL20: NA | AM20: NA | AN20: NA | AO20: NA | AP20: NA | AQ20: NA | AR20: NA | AS20: NA | AT20: NA | AU20: NA | AV20: NA | AW20: NA | AX20: Fully Approved as of 04/08/2022 Last checked: 04/15/2022 | BA20: 360000 | BB20: 3000 | BC20: Keller Williams Flagship of MD | BD20: - | BE20: - | BF20: 5000 | BG20: 4/4/2022 | BH20: 5/6/2022 | BI20: 44658 | BJ20: 4/25/2022 | BK20: 4/11/2022 As Is w/ Inspections | BL20: 4/5/2022 @ 4:30pm | BP20: N/A | BQ20: 500 | BR20: N/A | BV20: Terry O'Brien and Susann O'Brien | BW20: Cheryl Frederick Long & Foster Real Estate, Inc. CHERYL.FREDERICK@Longandfoster.com 443-622-6113 | BX20: Dave Euga Legacy Settlement Services, LLC. david@legacyfortitle.com 410 925-0566 | BY20: Kyndle Quinones Primary Residential Mortgage, Inc. ksquinones@primeres.com 443-254-0381 | CA20: Done | CB20: Done | CC20: Pending | CD20: Done | CE20: Done | CF20: Done | CI20: N/A
A21: 7419 Gunpowder Rd Middle River, MD 21220 | B21: Purchase | C21: Jen | AX21: UC Resubmitted: 04/20/2022 * Exclusive Buyer/Tenant - uploaded * EMD - not yet available
A22: 4101 Pascal Ave Curtis Bay, MD 21226 | B22: Purchase | C22: Trevor
A23: 81 W West St Baltimore, MD 21230 | B23: Purchase | C23: Evan | AX23: UC Submitted: 04/20/2022 * County Addendum - required signatures * EMD - not yet available
A24: 504 Dewey Dr Annapolis, MD 21401 | B24: Purchase | C24: Cole | E24: N/A | F24: N/A | G24: N/A | H24: N/A | I24: N/A | AC24: NA | AD24: NA | AE24: NA | AF24: NA | AG24: NA | AH24: NA | AI24: NA | AJ24: NA | AK24: NA | AL24: NA | AM24: NA | AN24: NA | AO24: NA | AP24: NA | AQ24: NA | AR24: NA | AS24: NA | AT24: NA | AU24: NA | AV24: NA | AW24: NA | AX24: UC Returned: 04/15/2022 * EMD - Still awaiting Last checked: 04/15/2022
A25: 216 S Patterson Park Ave Baltimore, MD 21231 | B25: Purchase | C25: Evan | E25: N/A | F25: N/A | G25: N/A | H25: N/A | I25: N/A | P25: Benjamin Jealous jealous@benjealous.com | Q25: Benjamin's Assistant damonlipscomb@gmail.com | Y25: N/A | Z25: N/A | AA25: TRUE | AC25: NA | AD25: NA | AE25: NA | AF25: NA | AG25: NA | AH25: NA | AI25: NA | AJ25: NA | AK25: NA | AL25: NA | AM25: NA | AN25: NA | AO25: NA | AP25: NA | AQ25: NA | AR25: NA | AS25: NA | AT25: NA | AU25: NA | AV25: NA | AW25: NA | AX25: UC Submitted: 04/06/2022 * EMD - missing Last checked: 04/15/2022 | BA25: 700000 | BB25: 7000 | BC25: Legacy Settlement Services | BD25: - | BE25: - | BF25: - | BG25: 4/3/2022 | BH25: 6/16/2022 | BJ25: 6/16/2022 | BK25: 4/10/2022 As Is w/ Inspections | BP25: N/A | BQ25: 500 | BR25: 5/26/2022 $1,000 deposit Held By Legacy | BV25: Greg Bortoff and Julia Ambrose | BW25: Ben Garner Monument Sotheby's International Realty ben.garner@monumentsothebysrealty.com 240-216-7841 | BX25: Dave Euga Legacy Settlement Services, LLC. david@legacyfortitle.com 410 925-0566 | BY25: Jake Smith Round Point Mortgage Jake.Smith@roundpointmortgage.com 410-707-7280 | CA25: Done | CB25: Done | CC25: Pending | CD25: Done | CE25: Done | CF25: Done | CI25: N/A
A26: 105 South Curley St Baltimore, MD 21224 | B26: Purchase | C26: Evan | E26: N/A | F26: N/A | G26: N/A | H26: N/A | I26: N/A | P26: Charleigh Holtermann Ceholtermann@gmail.com | Q26: N/A | Y26: N/A | Z26: N/A | AA26: FALSE | AC26: NA | AD26: NA | AE26: NA | AF26: NA | AG26: NA | AH26: NA | AI26: NA | AJ26: NA | AK26: NA | AL26: NA | AM26: NA | AN26: NA | AO26: NA | AP26: NA | AQ26: NA | AR26: NA | AS26: NA | AT26: NA | AU26: NA | AV26: NA | AW26: NA | AX26: UC resubmitted: 04/15/2022 * MLS Sheet - uploaded Last checked: 04/15/2022 | BA26: 427000 | BB26: 5000 | BC26: Keller Williams Flagship of MD | BD26: 10000 | BE26: - | BF26: - | BG26: 3/07/2022 | BH26: 7/29/2022 | BI26: 44636 | BO26: 3/10/2022 Qualia | BP26: N/A | BQ26: 100 | BR26: N/A | BV26: Ben Patterson | BW26: Matt Pecker Berkshire Hathaway Homeservices Homesale matt@suresalesgroup.com 301-325-2277 | BX26: Kimberly Richter Endeavor Title Company kim@endeavortitle.com 410-666-3780 ext. 1002 | BY26: Max Evan Spitalny Lakeview Mortgage mspitalny@lmbankers.com 443-630-8663 | CA26: Done | CB26: Done | CD26: Done | CE26: Done | CF26: Done | CI26: N/A
A27: 1025 Timber Creek Drive Annapolis, MD 21403 | B27: Purchase | C27: Jen | E27: N/A | F27: N/A | G27: N/A | H27: N/A | I27: N/A | AA27: FALSE | AC27: NA | AD27: NA | AE27: NA | AF27: NA | AG27: NA | AH27: NA | AI27: NA | AJ27: NA | AK27: NA | AL27: NA | AM27: NA | AN27: NA | AO27: NA | AP27: NA | AQ27: NA | AR27: NA | AS27: NA | AT27: NA | AU27: NA | AV27: NA | AW27: NA | AX27: Fully Approved as of 04/15/2022 | BG27: 4/6/2022 | BH27: 5/6/2022 | BX27: Dave Euga Legacy Settlement Services, LLC. david@legacyfortitle.com 410 925-0566 | BY27: Kyndle Quinones Primary Residential Mortgage, Inc. ksquinones@primeres.com 443-254-0381
A28: 837 Harlem Ave Baltimore, MD 21201 | B28: Purchase | C28: Vince | E28: N/A | F28: N/A | G28: N/A | H28: N/A | I28: N/A | P28: Desiree Akuchie 919-523-8200 dvakuchie0807@gmail.com | Q28: N/A | Y28: N/A | Z28: N/A | AA28: FALSE | AC28: NA | AD28: NA | AE28: NA | AF28: NA | AG28: NA | AH28: NA | AI28: NA | AJ28: NA | AK28: NA | AL28: NA | AM28: NA | AN28: NA | AO28: NA | AP28: NA | AQ28: NA | AR28: NA | AS28: NA | AT28: NA | AU28: NA | AV28: NA | AW28: NA | AX28: UC Resubmitted: 04/15/2022 *Pre Approval - missing Update: * MLS Full Listing Synopsis - uploaded Last checked: 04/15/2022 | BA28: 297850 | BB28: 5000 | BD28: - | BE28: - | BF28: - | BG28: 3/29/2022 | BH28: 9/30/2022 | BI28: 44656 | BJ28: 5/13/2022 | BK28: N/A | BP28: N/A | BQ28: 500 | BR28: N/A | BV28: Upton Gateway 1 LLC. Dean Harrison - Authorized Signee | BW28: Chris Cooke Berkshire Hathaway HomeServices Homesale Realty chris@chriscookteam.com 443-802-2728 Assistant Brenda Inzana brenda@chriscooketeam.com | BX28: Charter Title | BY28: Ryan Fisher Secured Funding Corporation Ryan@securedfundingcorporation.com 443-885-0060 | CA28: Done | CB28: Done | CC28: Off-Market | CD28: Done | CE28: Done | CF28: Done | CI28: N/A
A29: * | B29: * | C29: * | D29: * | E29: * | F29: * | G29: * | H29: * | I29: * | J29: * | K29: * | L29: * | M29: * | N29: * | O29: * | P29: * | Q29: * | R29: * | S29: * | T29: * | U29: * | V29: * | W29: * | X29: * | Y29: * | Z29: * | AA29: * | AB29: * | AC29: * | AD29: * | AE29: * | AF29: * | AG29: * | AH29: * | AI29: * | AJ29: * | AK29: * | AL29: * | AM29: * | AN29: * | AO29: * | AP29: * | AQ29: * | AR29: * | AS29: * | AT29: * | AU29: * | AV29: * | AW29: * | AX29: * | AY29: * | AZ29: * | BA29: * | BB29: * | BC29: * | BD29: * | BE29: * | BF29: * | BG29: * | BH29: * | BI29: * | BJ29: * | BK29: * | BL29: * | BM29: * | BN29: * | BO29: * | BP29: * | BQ29: * | BR29: * | BS29: * | BT29: * | BU29: * | BV29: * | BW29: * | BX29: * | BY29: * | BZ29: * | CA29: * | CB29: * | CC29: * | CD29: * | CE29: * | CF29: * | CG29: * | CH29: * | CI29: * | CJ29: * | CK29: * | CL29: * | CM29: * | CN29: * | CO29: * | CP29: * | CQ29: * | CR29: * | CS29: * | CT29: * | CU29: * | CV29: * | CW29: * | CX29: * | CY29: * | CZ29: * | DA29: * | DB29: * | DC29: * | DD29: * | DE29: *
A30: 814 Glacier Ave Capitol Heights, MD 20743 | B30: Closed | C30: John | D30: MDPG2029820 | E30: 02/07/2022 | F30: N/A | G30: 44597 | H30: 44960 | I30: 44597 | J30: 369900 | K30: 0.0375 | L30: 0.0125 | M30: 0.025 | N30: 0 | O30: N | P30: Livre, LLC. Work Mobile: 202-802-2045 Work Email: pmacho@kw.com | Q30: Paulo Machado | R30: 751 Rockville Pike 1A, Rockville MD 20852 | S30: Vacant | T30: Prince George's | U30: Greater Capitol Heights | V30: Fee Simple | W30: Sewer | X30: N/A | Y30: N/A | Z30: N/A | AA30: TRUE | AB30: Combo - 8011 Front Door | AC30: TRUE | AD30: TRUE | AE30: TRUE | AF30: TRUE | AG30: TRUE | AH30: TRUE | AI30: TRUE | AJ30: N/A | AK30: N/A | AL30: N/A | AM30: N/A | AN30: TRUE | AO30: https://drive.google.com/drive/folders/1fIn6W2iv8vz6SV99A_dvfqWQpoCApTTP | AP30: TRUE | AQ30: TRUE | AR30: TRUE | AS30: TRUE | AT30: N/A | AU30: N/A | AV30: TRUE | AW30: TRUE | AX30: Fully Approved Last checked: 03/31/2022 | AY30: Cap heights, 2/1 up, 2/1 down, New everything, Full permits | BA30: 365000 | BB30: 5000 | BC30: Household Title & Escrow, LLC. | BD30: 0.03 | BE30: - | BF30: - | BG30: 3/14/2022 | BH30: 4/22/2022 | BI30: 44634 | BJ30: 4/08/2022 | BK30: As Is w/o Inspections | BL30: N/A | BO30: 44635 | BP30: N/A | BQ30: 1000 | BR30: N/A | BV30: Wilber Ramirez Martinez | BW30: Ricky (Luiz) Palacio HomeSmart lhpalacio@comcast.net 301-806-5040 | BX30: Ralph Bernardo Household Title & Escrow, LLC. ralph@householdtitle.com 240-355-3011 | BY30: Helio Fernandes Souza America Trust Funding hsouza@americatrustfunding.com 301-881-5555 | CA30: Done | CB30: Done | CC30: Pending | CD30: Done | CE30: Done | CF30: Done | CI30: N/A
A31: 404 Carl Ave Linthicum Heights, MD 21090 | B31: Closed | C31: John | D31: MDAA2023706 | E31: 02/09/2022 | F31: N/A | G31: 44600 | H31: 44967 | I31: 44599 | J31: 309900 | K31: 0.0375 | L31: 0.0125 | M31: 0.025 | N31: 0 | O31: N | P31: Residential Value, LLC. Work Mobile: 301-674-0760 Work Email: dsl227@aol.com | Q31: David Loring | R31: 751 Rockville Pike 1A, Rockville MD 20852 | S31: Vacant | T31: Anne Arundel | U31: Sweetser Heights | V31: Fee Simple | W31: Sewer | X31: N/A | Y31: N/A | Z31: N/A | AA31: TRUE | AB31: Combo - 1108 Front Door | AC31: TRUE | AD31: TRUE | AE31: TRUE | AF31: TRUE | AG31: TRUE | AH31: TRUE | AI31: TRUE | AJ31: N/A | AK31: N/A | AL31: N/A | AM31: N/A | AN31: TRUE | AO31: https://drive.google.com/drive/folders/1Dk6D1lIbsz5j-cIcVbg1h-BKXEpoEGIZ | AP31: TRUE | AQ31: TRUE | AR31: TRUE | AS31: TRUE | AT31: N/A | AU31: N/A | AV31: TRUE | AW31: TRUE | AX31: Fully Approved Last checked: 03/31/2022 | BA31: 318000 | BB31: 10000 | BC31: Pinnacle Title & Escrow | BD31: - | BE31: - | BF31: - | BG31: 3/18/2022 | BH31: 4/15/2022 | BI31: 44642 | BJ31: 4/17/2022 | BK31: As Is W/O Inspection | BL31: N/A | BP31: N/A | BQ31: 0 | BR31: N/A | BV31: Arlin Javiel Lemus | BW31: Claudia Bordon HomeSmart claudiabordonkw@gmail.com 443-388-3346 | BX31: Jonathan Morgan, Esq. Pinnacle Title and Escrow, Inc. jmorgan@pinnacletitle.com 301-279-4246 | BY31: Alvaro Perez Caliber Home Loans Alvaro.perez@caliberhomeloans.com 703-624-1708 | CA31: Done | CB31: Done | CC31: Pending | CD31: Done | CE31: Done | CF31: Done | CG31: Done | CH31: Done | CI31: N/A | CJ31: Done | CK31: Done | CL31: Done | CM31: Done
A32: 1708 Cass Dr Bel Air, MD 21015 | B32: Closed | C32: Jen | E32: N/A | F32: N/A | G32: N/A | H32: N/A | I32: N/A | P32: Ed McCullen 267-819-7590 edmcmullen15@gmail.com | Q32: N/A | Y32: N/A | Z32: N/A | AA32: FALSE | AC32: NA | AD32: NA | AE32: NA | AF32: NA | AG32: NA | AH32: NA | AI32: NA | AJ32: NA | AK32: NA | AL32: NA | AM32: NA | AN32: NA | AO32: NA | AP32: NA | AQ32: NA | AR32: NA | AS32: NA | AT32: NA | AU32: NA | AV32: NA | AW32: NA | AX32: UC Resubmitted: 04/15/2022 * Exclusive Buyer/Tenant Representation - signed *Contract of Sale - Listing Broker License # unknown Last checked: 04/15/2022 | BA32: 425000 | BB32: 4400 | BC32: Eagle Premier Title | BD32: - | BE32: - | BF32: - | BG32: 3/18/2022 | BH32: 4/14/2022 | BI32: 44644 | BJ32: 4/12/2022 | BK32: 3/25/2022 As Is w/ Inspections | BP32: N/A | BQ32: 500 | BR32: N/A | BV32: LIG Holdings 2, LLC. | BW32: Benjamin Morgan II RE/MAX Ikon ben@thelegacyinvestmentgroup.com 410-905-4735 | BX32: Mary Clark Eagle Premier Title Mary@eaglepremiertitle.com 410-727-1371 | BY32: Kyndle Quinones Primary Residential Mortgage, Inc. ksquinones@primeres.com 443-254-0381 | CA32: Done | CB32: Done | CC32: Active Under Contract | CD32: Done | CE32: Done | CF32: Done | CG32: Done | CH32: Done | CI32: N/A | CJ32: Done | CK32: Done | CL32: Done | CM32: Done
A33: 800 Slacum St Cambridge, MD 21613 | B33: Closed | C33: Romont | D33: MDDO2001132 | E33: 11/20/2021 1PM | F33: N/A | G33: 44523 | H33: 44890 | I33: 44516 | J33: 160000 | K33: 0.05 | L33: 0.025 | M33: 0.025 | N33: 495 | O33: N | P33: Rachell Rich 4434960416 rich_rachell@yahoo.com | Q33: N/A | R33: - | S33: Vacant | T33: Dorchester | U33: Neighborhood | V33: Fee Simple | W33: Sewer | X33: N/A | Y33: N/A | Z33: TRUE | AA33: TRUE | AB33: Combo 0426 | AC33: TRUE | AD33: TRUE | AE33: TRUE | AF33: TRUE | AG33: TRUE | AH33: TRUE | AI33: TRUE | AJ33: TRUE | AK33: Done | AL33: TRUE | AM33: TRUE | AN33: TRUE | AO33: http://www.homevisit.com/my/property/contactSheet/?hvid=360049 | AP33: TRUE | AQ33: TRUE | AR33: TRUE | AS33: TRUE | AT33: TRUE | AU33: TRUE | AV33: TRUE | AW33: TRUE | AX33: Fully Approved | AY33: Yes to signs Yes to OH | BA33: 164300 | BB33: 1600 | BC33: Advantage Settlement, Inc. | BD33: 0.03 | BE33: - | BF33: - | BG33: 3/1/2022 | BH33: 44663 | BI33: 44627 | BJ33: 3/22/2022 | BK33: 3/8/2022 | BL33: 3/8/2022 | BO33: 44622 | BP33: N/A | BQ33: 500 | BR33: N/A | BV33: Mary Maud Barnes | BW33: Diane McCawley United Real Estate unitedreagent@gmail.com 703-606-8884 | BX33: Christie Ekasone Advantage Settlement, Inc. Christie@advantagesettlement.com 703-532-9520 | BY33: David Hawkes Wintrust Mortgage, A Division of Barrington Bank and Trust Co., N.A. 801-493-6623 | CA33: Done | CB33: Done | CC33: Active Under Contract | CD33: Done | CE33: Done | CF33: Done | CG33: Done | CH33: Done | CI33: Done | CJ33: Done | CK33: Done | CL33: Done | CM33: Done
A34: 3900 Chesterwood Dr Aspen Hill, MD 20906 | B34: Closed | C34: Vince | D34: MDMC2020492 | E34: 02/07/2022 | F34: 44596 | G34: 44601 | H34: 44742 | I34: 44489 | J34: 289900 | K34: 0.05 | L34: 0.025 | M34: 0.025 | N34: 495 | O34: N | P34: Jose Cobar josecobar1@gmail.com | Q34: Erika Cobar erika.cobar@gmail.com | R34: - | S34: Occupied | T34: Montgomery | U34: Montgomery Chase Codm | V34: Fee Simple | W34: Sewer | X34: N/A | Y34: Montgomery Chase Condominium Comsource Management $187/Monthly | Z34: TRUE | AA34: TRUE | AB34: Go & Show Combo - 8323 Front Door | AC34: TRUE | AD34: TRUE | AE34: TRUE | AF34: TRUE | AG34: TRUE | AH34: TRUE | AI34: TRUE | AJ34: TRUE | AK34: Done | AL34: TRUE | AM34: TRUE | AN34: TRUE | AO34: https://drive.google.com/drive/folders/1zACagOPDNmwTsfQdATYNckJFfYviM6lD | AP34: TRUE | AQ34: TRUE | AR34: TRUE | AS34: TRUE | AT34: TRUE | AU34: TRUE | AV34: TRUE | AW34: TRUE | AX34: Fully Approved | AY34: 1/28 - List Price changed from $280,000 to $289,900 HOA Resale Packet: Order on Homewise. Search Montgomery Chase. Showing Instruction: Go & Show we'd need a notary to get to our location. We'd sign in Yuba City, CA. HOA Resale Packet (Ordered 2/15) | BA34: 292000 | BB34: 5000 | BC34: Title Forward | BD34: - | BE34: - | BF34: - | BG34: 2/26/2022 | BH34: 4/13/2022 | BI34: 44627 | BJ34: 3/12/2022 | BK34: N/A | BL34: N/A | BP34: 3/7/2022 | BQ34: 0 | BR34: N/A | BV34: Antonino Amano and Alisson Amano | BW34: Matthew Modesitt Redfin Corporation matt.modesitt@redfin.com 240-449-9384 Charlene Gao Transaction Coordinator charlene.gao@redfin.com 301-284-8107 | BX34: Title Forward orders@titleforward.com 267-908-8999 | BY34: Melissa Pacheco Pentagon Federal Credit Union melissa.pacheco@penfed.org 726-333-8201 | CA34: Done | CB34: Done | CC34: Pending | CD34: Done | CE34: Done | CF34: Done | CG34: Done | CH34: Done | CI34: N/A | CJ34: Done | CK34: Done | CL34: Done | CM34: Done | CP34: 5 | CR34: 2
A35: 93 East St Annapolis, MD 21401 | B35: Closed | C35: Vince | E35: N/A | F35: N/A | G35: N/A | H35: N/A | I35: N/A | P35: Conor Shea conorshea.realestate@gmail.com | Q35: Daniel Wallace dannylwallace.realestate@gmail.com | Y35: N/A | Z35: N/A | AA35: TRUE | AC35: NA | AD35: NA | AE35: NA | AF35: NA | AG35: NA | AH35: NA | AI35: NA | AJ35: NA | AK35: NA | AL35: NA | AM35: NA | AN35: NA | AO35: NA | AP35: NA | AQ35: NA | AR35: NA | AS35: NA | AT35: NA | AU35: NA | AV35: NA | AW35: NA | AX35: Fully Approved 03/16/2022 | BA35: 510000 | BB35: 5200 | BC35: Keller Williams Flagship of MD | BD35: - | BE35: - | BF35: - | BG35: 2/25/2022 | BH35: 4/11/2022 | BI35: 44622 | BJ35: 3/18/2022 | BK35: 3/07/2022 As Is w/ Inspections | BL35: 3/2/2022 at 1:30pm | BP35: N/A | BQ35: 1000 | BR35: N/A | BV35: Nancy Wells, PR. | BW35: James Jenkins Keller Williams Capital Properties jamesjenkinskw@gmail.com 240-883-4696 Allison Gyovia Transaction Coordinator KWLSS allison@kwlss.com | BX35: Charter Title info@chartertitlemd.com | BY35: Martin Wallace First Home Mortgage MWallace@firsthome.com 443-926-6106 | CA35: Done | CB35: Done | CC35: Active Under Contract | CD35: Done | CE35: Done | CF35: Done | CG35: Done | CH35: Done | CI35: N/A | CJ35: Done | CK35: Done | CL35: Done | CM35: Done
A36: 319 Greyhound Rd Essex, MD 21221 | B36: Closed | C36: John | E36: 3/2/2022 2:30pm | F36: N/A | G36: 44622 | H36: 44986 | I36: 44616 | P36: Residential Value, LLC. Work Mobile: 301-674-0760 Work Email: dsl227@aol.com | Q36: David Loring | R36: 751 Rockville Pike 1A, Rockville MD 20852 | S36: Vacant | T36: Prince George's | U36: Pointer Ridge at Prince Geoge's | V36: Fee Simple | W36: Sewer | X36: N/A | Y36: N/A | Z36: N/A | AA36: N/A | AC36: TRUE | AD36: TRUE | AE36: TRUE | AF36: TRUE | AG36: TRUE | AH36: TRUE | AI36: TRUE | AJ36: N/A | AK36: N/A | AL36: TRUE | AM36: N/A | AN36: TRUE | AO36: https://drive.google.com/drive/folders/1fauJMjsxquTIyUdojpKJ1boHjn8atQBR?usp=sharing | AP36: TRUE | AQ36: TRUE | AR36: TRUE | AS36: TRUE | AT36: N/A | AU36: N/A | AV36: TRUE | AW36: TRUE | AX36: 3/10/2022 Submitted status in Command Last checked: 03/031/2022 | BA36: 385000 | BB36: 2000 | BC36: RE/MAX Components | BD36: - | BE36: - | BF36: 10000 | BG36: 3/4/2022 | BH36: 4/4/2022 | BI36: 44624 | BJ36: 4/03/2022 | BK36: 3/11/2022 As Is w/ Inspections | BL36: 3/11/2022 12pm to 12:45pm | BP36: N/A | BQ36: 500 | BR36: N/A | BV36: Daniel Hayden and Megan Hayden | BW36: Christy Kopp RE/MAX Components Fallston christykopp@gmail.com 443-992-1983 | BX36: Jonathan Morgan, Esq. Pinnacle Title and Escrow, Inc. jmorgan@pinnacletitle.com 301-279-4246 | BY36: Fred Militello 212 Mortgage Group, Inc. fred@212mortgage.com 410-420-2071 | BZ36: Christine Lobos Lobos Appraisers clobos@lobosappraisers.com 410-459-0507 | CA36: Done | CB36: Done | CC36: Pending | CD36: Done | CE36: Done | CF36: Done | CG36: Done | CH36: Done | CI36: N/A | CJ36: Done | CK36: Done | CL36: Done | CM36: Done
A37: 1410 N Forest Park Ave Baltimore, MD 21207 | B37: Closed | C37: Justin | D37: MDBC165324 | E37: - | F37: 44571 | G37: 44576 | H37: 44910 | I37: 44581 | J37: 210000 | K37: 0.06 | L37: 0.035 | M37: 0.025 | N37: 495 | O37: - | P37: Kimberly Collins 443-629-0325 kcollins63@gmail.com | Q37: N/A | R37: - | S37: Owner Occupied | T37: Baltimore | U37: Edmonson Heights | V37: Fee Simple | W37: Sewer | X37: N/A | Y37: Edmonson Heights Civic Association https://www.ehcaonline.org/ehca-membership/ president@ehcaonline.org $25/Annually | Z37: TRUE | AA37: TRUE | AB37: Sentrilock - 1898355 Front Door | AC37: TRUE | AD37: TRUE | AE37: TRUE | AF37: TRUE | AG37: TRUE | AH37: TRUE | AI37: TRUE | AJ37: TRUE | AK37: Done | AL37: TRUE | AM37: TRUE | AN37: TRUE | AO37: https://nimamohammadi.hd.pics/media/download.asp?EBFE9D4F4150429CB5F9413C1B914045 | AP37: TRUE | AQ37: TRUE | AR37: TRUE | AS37: TRUE | AT37: TRUE | AU37: TRUE | AV37: TRUE | AW37: TRUE | AX37: Fully Approved | AY37: HOA send website to Buyer's Agent. | BA37: 215000 | BB37: 2000 | BC37: Heritage Title Company | BD37: - | BE37: - | BF37: - | BG37: 3/3/2022 | BH37: 3/31/2022 | BI37: 44642 | BJ37: N/A | BK37: As Is W/O Inspection | BL37: N/A | BM37: N/A | BP37: N/A | BQ37: 0 | BR37: N/A | BV37: Huifen Wang | BW37: Ming Guo Signature Home Realty guo_ming@hotmail.com 443-854-5399 | BX37: Delila Habte Heritage Title Company heritagetitle.request@gmail.com 301-816-0604 | BY37: N/A | CA37: Done | CB37: Done | CC37: Pending | CD37: Done | CE37: Done | CF37: Done | CG37: Done | CH37: Done | CI37: Done | CJ37: Done | CK37: Done | CL37: Done | CM37: Done | CP37: 5 | CR37: 2
A38: 3033 Lundt Ct Waldorf, MD 20603 | B38: Closed | C38: Justin | D38: MDCH2004534 | E38: 2/15/2022 10:30 AM | F38: 44603 | G38: 44616 | H38: 44835 | I38: 44473 | J38: 567000 | K38: 0.06 | L38: 0.035 | M38: 0.025 | N38: 495 | O38: N | P38: Erica Gordon 443-618-5886 3sgirl@gmail.com | Q38: Johnny Gordon jgordon.q@gmail.com | R38: - | S38: Occupied | T38: Charles | U38: Charles Crossing | V38: Fee Simple | W38: Sewer | X38: N/A | Y38: Charles Crossing HOA 240-419-3193 email.charlescrossinghoa@gmail.com $1104/Annually | Z38: TRUE | AA38: N/A | AB38: Go and show, 1 hr advanced notice required. Time window 9am-7pm Sentrilock - 1819761 | AC38: TRUE | AD38: TRUE | AE38: TRUE | AF38: TRUE | AG38: TRUE | AH38: TRUE | AI38: TRUE | AJ38: TRUE | AK38: Done | AL38: TRUE | AM38: FALSE | AN38: TRUE | AO38: https://drive.google.com/drive/folders/1eW2zqqe4HBAN1wFjnYyzw25BEkYZUewu?usp=sharing | AP38: TRUE | AQ38: TRUE | AR38: TRUE | AS38: TRUE | AT38: TRUE | AU38: TRUE | AV38: TRUE | AW38: TRUE | AX38: Fully Approved | AY38: Photos: Need to confirm back with seller. ex husband needs to get his things out of the property and floors to be cleaned. HOA $$333 every three months Need a HOA Receipt No front fee No ground rent | BA38: 590000 | BB38: 15000 | BC38: Allied Title and Escrow | BD38: - | BE38: - | BF38: - | BG38: 2/28/2022 | BH38: 3/31/2022 | BI38: 44623 | BJ38: 3/18/2022 | BK38: 3/3/2022 As Is w/ Inspections | BL38: 3/2/2022 10am-2pm 3/5/2022 12:30pm (Radon) | BM38: N/A | BQ38: 0 | BR38: N/A | BV38: Arlandria Green and Amanda Thompson | BW38: Rob Alcorn Optime Realty robalcorn@kerishullteam.com 703-509-7386 | BX38: Allied Title and Escrow info@alliedtitleandescrow.com 703-567-7933 Jake Bosman jake@alliedtitleandescrow.com Jessica Dallessandro jessica@alliedtitleandescrow.com | BY38: Michelle Powstanski Main Street Home Loans mpowstanski@mainstreethl.com 703-909-2570 | CA38: Done | CB38: Done | CC38: Pending | CD38: Done | CE38: Done | CF38: Done | CG38: Done | CH38: Done | CI38: Done | CJ38: Done | CK38: Done | CL38: Done | CM38: Done
A39: 635 West Bel Air Ave Aberdeen, MD 21001 | B39: Closed | C39: Shaq | D39: MDHR2005970 | E39: N/A | F39: N/A | G39: N/A | H39: N/A | I39: N/A | J39: 325000 | K39: 0.025 | L39: 0 | M39: 0.025 | N39: 695 | O39: N | P39: Chris Haskey chrishaskey87@gmail.com 443-851-0960 | Q39: Bernard Pressell lazpunk1104@gmail.com 443-902-1671 | R39: N/A | S39: Owner | T39: Harford | V39: Fee Simple | W39: Septic | X39: N/A | Y39: N/A | Z39: N/A | AA39: N/A | AB39: N/A | AC39: NA | AD39: NA | AE39: NA | AF39: NA | AG39: NA | AH39: NA | AI39: NA | AJ39: NA | AK39: NA | AL39: NA | AM39: NA | AN39: NA | AO39: NA | AP39: NA | AQ39: NA | AR39: NA | AS39: NA | AT39: NA | AU39: NA | AV39: NA | AW39: NA | AX39: 3/23/2022 County Addendum - submitted Last checked: 03/23/2022 | AY39: SPCC $10,000. Waiting for sellers to sign | BA39: 335000 | BB39: 1000 | BC39: Keller Williams Flagship of MD | BD39: - | BE39: - | BF39: - | BG39: 2/14/2022 | BH39: 3/25/2022 | BI39: 44606 | BJ39: 3/07/2022 | BK39: 2/21/2022 As Is w/ Inspections | BP39: N/A | BQ39: 500 | BR39: N/A | BS39: No, 50/50 Split | BT39: N/A | BU39: FHA | BV39: Lilia Simons | BW39: Gina Gladis eXp Realty, LLC. gina@gladisgroup.com 410-420-7900 | BX39: Leigh Sistek Certified Title Corporation leigh@certifiedtitlecorp.com 410-916-3922 Nicole Brecht Nicole@certifiedtitlecorp.com | BY39: Kyndle Quinones Primary Residential Mortgage, Inc. ksquinones@primeres.com 443-254-0381 | CA39: Done | CB39: Done | CC39: Temporary Off-Market | CD39: Done | CE39: Done | CF39: Done | CG39: Done | CH39: Done | CI39: N/A | CJ39: Done | CK39: Done | CL39: Done | CM39: Done | CN39: Done | CO39: Done | CP39: Done | CQ39: Done | CR39: Done | CS39: Done | CT39: Done | CU39: Done | CV39: Done | CW39: Done | CX39: Done | CY39: Done | CZ39: Done | DA39: Done | DB39: Done | DC39: Done | DD39: Done | DE39: Done | DF39: Done
A40: 723 Paldao Ter #2 Landover, MD 20785 | B40: Closed | C40: Vince | E40: N/A | F40: N/A | G40: N/A | H40: N/A | I40: N/A | P40: Sherman Abrams sherm869@gmail.com | Q40: N/A | Y40: Potomac Valley Management $198/Monthly | Z40: TRUE | AA40: N/A | AC40: NA | AD40: NA | AE40: NA | AF40: NA | AG40: NA | AH40: NA | AI40: NA | AJ40: NA | AK40: NA | AL40: NA | AM40: NA | AN40: NA | AO40: NA | AP40: NA | AQ40: NA | AR40: NA | AS40: NA | AT40: NA | AU40: NA | AV40: NA | AW40: NA | AX40: 3/10/2022 Notice to Buyer and Seller of Rights & Obligations Last checked: 03/16/2022 | BA40: 250000 | BB40: 10000 | BC40: Keller Williams Flagship of MD | BD40: - | BE40: - | BF40: - | BG40: 3/2/2022 | BH40: 3/25/2022 | BI40: 3/2/2022 | BJ40: 3/21/2022 | BK40: 3/07/2022 As Is w/ Inspections | BL40: 3/4 9AM | BP40: 3/2/2022 | BQ40: 0 | BR40: N/A | BV40: Estate of Tammy Nadine Wise | BW40: Donald Grant CENTURY 21 Envision Realty donald@winningvisionrealty.com 202-853-1350 | BX40: Smart Settlements orders@smartsettlements.com 301-329-5556 | BY40: Matt Thompson Empower Home Mortgage matt@empowermortgage.com 404-518-9899 | CA40: Done | CB40: Done | CC40: Pending | CD40: Done | CE40: Done | CF40: Done | CI40: N/A | CJ40: Done | CK40: Done | CL40: Done | CM40: Done | CN40: Done | CO40: Done | CP40: Done | CQ40: Done | CR40: Done | CS40: Done | CT40: Done | CU40: Done | CV40: Done | CW40: Done | CX40: Done | CY40: Done | CZ40: Done | DA40: Done | DB40: Done | DC40: Done | DD40: Done | DE40: Done | DF40: Done
A41: 7991 Foxwell Ct Glen Burnie, MD 21061 | B41: Closed | C41: Justin | E41: N/A | F41: N/A | G41: N/A | H41: 44876 | I41: 44202 | P41: Clifton Shillcutt clifshillcutt@gmail.com | Q41: Janice Shirk elainemaryland@gmail.com | Y41: Fox Chase Village Homeowners Association $144/Monthly | Z41: TRUE | AA41: N/A | AC41: TRUE | AD41: TRUE | AE41: TRUE | AF41: N/A | AG41: N/A | AH41: N/A | AI41: N/A | AJ41: N/A | AK41: N/A | AL41: N/A | AM41: TRUE | AN41: N/A | AO41: N/A | AP41: N/A | AQ41: N/A | AR41: TRUE | AS41: N/A | AT41: N/A | AU41: N/A | AV41: N/A | AW41: N/A | AX41: Listed returned: 03/09/2022 Listing Agreement - Will sign once near closing --- --- --- UC (John Newman) 03/10/2022 * EMD - Missing | BA41: 350000 | BB41: 3500 | BC41: Pinnacle Title & Escrow | BD41: - | BE41: - | BF41: - | BG41: 3/6/2022 | BH41: 3/25/2022 | BI41: 44642 | BJ41: N/A | BK41: As Is W/O Inspection | BL41: N/A | BM41: N/A | BQ41: 0 | BR41: N/A | BV41: Residential Value, LLC. | BW41: John Newman The Newman Group at Keller Williams Flagship of Maryland thinknewman@kw.com 301-343-7671 | BX41: Jonathan Morgan, Esq. Pinnacle Title and Escrow, Inc. jmorgan@pinnacletitle.com 301-279-4246 | BY41: N/A | CA41: Done | CB41: Done | CC41: Off-Market Sale | CD41: Done | CE41: Done | CF41: Done | CG41: Done | CH41: Done | CI41: N/A | CJ41: Done | CK41: Done | CL41: Done | CM41: Done
A42: 7991 Foxwell Ct Glen Burnie, MD 21061 | B42: Closed | C42: John | E42: N/A | F42: N/A | G42: N/A | H42: N/A | I42: N/A | P42: Residential Value, LLC. Work Mobile: 301-674-0760 Work Email: dsl227@aol.com | Q42: David Loring | Y42: Fox Chase Village Homeowners Association $144/Monthly | Z42: TRUE | AA42: N/A | AC42: N/A | AD42: N/A | AE42: N/A | AF42: N/A | AG42: N/A | AH42: N/A | AI42: N/A | AJ42: N/A | AK42: N/A | AL42: N/A | AM42: N/A | AN42: N/A | AO42: N/A | AP42: N/A | AQ42: N/A | AR42: N/A | AS42: N/A | AT42: N/A | AU42: N/A | AV42: N/A | AW42: N/A | AX42: 03/09/2022 Listed Returned * Exclusive Right To Sell - Sec 8 to be initialed -- -- -- -- -- 03/11/2022 UC (John Newman) returned * Copy of EMD Last checked: 03/16/2022 | BA42: 350000 | BB42: 3500 | BC42: Pinnacle Title & Escrow | BD42: - | BE42: - | BF42: - | BG42: 3/6/2022 | BH42: 3/25/2022 | BJ42: N/A | BK42: As Is W/O Inspection | BL42: N/A | BM42: N/A | BQ42: 0 | BR42: N/A | BV42: Clifton Shillcutt and Janice Shirk | BW42: Justin Matney The Newman Group at Keller Williams Flagship of Maryland justinmatney@kw.com 301-980-5846 | BX42: Jonathan Morgan, Esq. Pinnacle Title and Escrow, Inc. jmorgan@pinnacletitle.com 301-279-4246 | BY42: N/A | CA42: Done | CB42: Done | CC42: Off-Market Sale | CD42: Done | CE42: Done | CF42: Done | CI42: N/A
A43: 733 Stinchcomb Rd Severna Park, MD 21146 | B43: Closed | C43: John | E43: 3/8/2022 2:30pm | F43: N/A | G43: 44628 | H43: 44991 | I43: 44627 | P43: Residential Value, LLC. Work Mobile: 301-674-0760 Work Email: dsl227@aol.com | Q43: David Loring | Y43: N/A | Z43: N/A | AA43: TRUE | AC43: TRUE | AD43: TRUE | AE43: TRUE | AF43: TRUE | AG43: TRUE | AH43: TRUE | AI43: TRUE | AJ43: N/A | AK43: N/A | AL43: TRUE | AM43: N/A | AN43: TRUE | AO43: https://drive.google.com/drive/folders/1FxtIJubpuI2ERHO8PWWakBQdCwyGzAfh | AP43: TRUE | AQ43: TRUE | AR43: TRUE | AS43: TRUE | AT43: N/A | AU43: N/A | AV43: TRUE | AW43: TRUE | AX43: Fully Approved | BA43: 557290 | BB43: 20000 | BC43: Long & Foster Real Estate, Inc. | BD43: - | BE43: - | BF43: - | BG43: 3/11/2022 | BH43: 3/24/2022 | BI43: 44641 | BJ43: N/A | BK43: 3/21/2022 | BL43: 3/17/2022 9:30am | BM43: N/A | BP43: N/A | BQ43: 0 | BR43: N/A | BV43: Travis Pastrana and Lyndsey Pastrana | BW43: Lynn Adams Long & Foster Real Estate, Inc. lynn.adams@longandfoster.com 760-845-6972 | BX43: Jonathan Morgan, Esq. Pinnacle Title and Escrow, Inc. jmorgan@pinnacletitle.com 301-279-4246 | BY43: N/A | CA43: Done | CB43: Done | CC43: Pending | CD43: Done | CE43: Done | CF43: Done | CG43: Done | CH43: Done | CI43: N/A | CJ43: Done | CK43: Done | CL43: Done | CM43: Done
